Workbook

Sheet Output comparison
J3: €/USD
J4: 0.85
C5: Conversion factor | D5: eSMR | E5: SMR | G5: conservative | H5: Base-scenario | I5: optimistic
B7: Hydrogen, m3 (STP/h) | D7: ='OCMC eSMR'!AY34 -> 5000.5 | E7: ='SMR, WGSR, C-forming, C2H6'!AS34 -> 5000.5 | Q7: eSMR | T7: SMR
B8: Natural gas, MWh/h | C8: =36.6*0.000277778 -> 0.010166675 | D8: =-'OCMC eSMR'!D34*C8 -> -13.90249 | E8: =-'SMR, WGSR, C-forming, C2H6'!D34*C8 -> -21.960018 | G8: 15 | H8: 40 | I8: 40 | J8: €/MWh | K8: USA | L8: https://www.intratec.us/solutions/energy-prices-markets/commodity/natural-gas-price-united-states | M8: Germany | N8: https://www.intratec.us/solutions/energy-prices-markets/commodity/natural-gas-price-germany | O8: China | P8: https://www.intratec.us/solutions/energy-prices-markets/commodity/natural-gas-price-china | Q8: =$D8*G8 -> -208.53735 | R8: =$D8*H8 -> -556.0996 | S8: =$D8*I8 -> -556.0996 | T8: =$E8*G8 -> -329.40026 | U8: =$E8*H8 -> -878.4007 | V8: =$E8*I8 -> -878.4007
B9: MP steam, kg/h | D9: 0 | E9: ='SMR, WGSR, C-forming, C2H6'!V3 -> 985.86697 | G9: =G8*0.95*'OCMC eSMR'!$P$14*0.000000277778 -> 0.012199989 | H9: =H8*0.95*'OCMC eSMR'!$P$14*0.000000277778 -> 0.032533304 | I9: =I8*0.95*'OCMC eSMR'!$P$14*0.000000277778 -> 0.032533304 | J9: €/kg | Q9: =$D9*G9 -> 0 | R9: =$D9*H9 -> 0 | S9: =$D9*I9 -> 0 | T9: =$E9*G9 -> 12.027566 | U9: =$E9*H9 -> 32.07351 | V9: =$E9*I9 -> 32.07351
B10: Electricity, kWh/h | C10: 0.000277778 | D10: =-'OCMC eSMR'!AA45*C10 -> -3496.9106 | E10: 0 | G10: 0.18 | H10: 0.4 | I10: 0.08 | J10: $/kWh | K10: USA | L10: Germany | M10: China/India | N10: https://worldpopulationreview.com/country-rankings/cost-of-electricity-by-country | Q10: =$D10*G10*$J$4 -> -535.02731 | R10: =$D10*H10*$J$4 -> -1188.9496 | S10: =$D10*I10*$J$4 -> -237.78992 | T10: =$E10*G10*$J$4 -> 0 | U10: =$E10*H10*$J$4 -> 0 | V10: =$E10*I10*$J$4 -> 0
B11: Water, kg/h | D11: 0 | E11: =-'SMR, WGSR, C-forming, C2H6'!AJ17 -> -4700 | G11: =3/1000 -> 0.003 | H11: =4/1000 -> 0.004 | I11: =5/1000 -> 0.005 | J11: €/kg | K11: https://www.zfk.de/wasser-abwasser/wasser/industriewasser-wird-im-schnitt-ein-cent-teurer | Q11: =$D11*G11 -> 0 | R11: =$D11*H11 -> 0 | S11: =$D11*I11 -> 0 | T11: =$E11*G11 -> -14.1 | U11: =$E11*H11 -> -18.8 | V11: =$E11*I11 -> -23.5
B12: Waste water, kg/h | D12: ='OCMC eSMR'!AP19 -> 1459.9683 | E12: ='SMR, WGSR, C-forming, C2H6'!AP17 -> 2139.6529 | G12: =-4/1000 -> -0.004 | H12: =-8/1000 -> -0.008 | I12: =-12/1000 -> -0.012 | J12: $/kg | K12: https://porvoo.com.cn/blog/wastewater-treatment-prices-investment-breakdown/ | L12: https://www.sciencedirect.com/science/article/pii/S0921344919305695 | Q12: =$D12*G12*$J$4 -> -4.9638921 | R12: =$D12*H12*$J$4 -> -9.9277841 | S12: =$D12*I12*$J$4 -> -14.891676 | T12: =$E12*G12*$J$4 -> -7.2748197 | U12: =$E12*H12*$J$4 -> -14.549639 | V12: =$E12*I12*$J$4 -> -21.824459
B13: CO2 concentrated, kg/h | D13: ='OCMC eSMR'!AU9 -> 2083.2491 | E13: 0 | G13: =-30/1000 -> -0.03 | H13: =-21/1000 -> -0.021 | I13: =-12/1000 -> -0.012 | J13: $/kg | K13: CCS | L13: https://zeroemissionsplatform.eu/publication/co2-storage-cost/ | M13: https://www.sciencedirect.com/science/article/pii/S1750583621001195 | N13: https://www.globalccsinstitute.com/wp-content/uploads/2025/12/Cost-of-CO2-Storage-1225.pdf | O13: CCU | P13: https://businessanalytiq.com/procurementanalytics/index/carbon-dioxide-price-index/ | Q13: =$D13*G13*$J$4 -> -53.122853 | R13: =$D13*H13*$J$4 -> -37.185997 | S13: =$D13*I13*$J$4 -> -21.249141 | T13: =$E13*G13*$J$4 -> 0 | U13: =$E13*H13*$J$4 -> 0 | V13: =$E13*I13*$J$4 -> 0
B14: CO2 emitted, kg/h | D14: =SUM('OCMC eSMR'!AZ61:AZ63) -> 368.74809 | E14: ='SMR, WGSR, C-forming, C2H6'!AC5 -> 3976.4973 | G14: 0 | H14: =-80/1000 -> -0.08 | I14: =-2.27/1000 -> -0.00227 | J14: €/kg | K14: https://tradingeconomics.com/commodity/carbon | Q14: =$D14*G14 -> 0 | R14: =$D14*H14 -> -29.499847 | S14: =$D14*I14 -> -0.83705816 | T14: =$E14*G14 -> 0 | U14: =$E14*H14 -> -318.11979 | V14: =$E14*I14 -> -9.0266489
C15: https://www.engineeringtoolbox.com/fuels-higher-calorific-values-d_169.html | Q15: =SUM(Q8:Q14) -> -801.65141 | R15: =SUM(R8:R14) -> -1821.6628 | S15: =SUM(S8:S14) -> -830.86739 | T15: =SUM(T8:T14) -> -338.74752 | U15: =SUM(U8:U14) -> -1197.7966 | V15: =SUM(V8:V14) -> -900.6783
U20: ratios
U21: N2/electricity
U22: CO2 tax/electricity
U23: Eingesparte tonne CO2 pro MWh Strom
I25: 87 | J25: CNY/MMBtu | K25: 0.29 | L25: MWh/MMBtu | M25: 0.13 | N25: €/CNY | O25: =I25/K25*M25 -> 39
G26: 5 | H26: USD/MMBtu | I26: 0.29 | J26: MWh/MMBtu | K26: 0.85 | L26: €/USD | M26: =G26/I26*K26 -> 14.655172

Sheet OCMC eSMR
F1: Parameter | G1: Feed, 1 | H1: Before desulfurization, 2 | I1: Reformer inlet, 3 | J1: Reformer outlet, 4 | K1: Pressure swing adsorption, 5 | L1: H2 product, 6
F2: H2, vol % | G2: 0 | H2: 4.8 | I2: 1.1 | J2: 51.9 | K2: 74.6 | L2: 99.99
F3: N2, vol % | G3: 1 | H3: 1 | I3: 0.3 | J3: 0.2 | K3: 0.25 | L3: 0.01
F4: CO, vol % | G4: 0 | H4: 0 | I4: 0 | J4: 10.7 | K4: 5.3 | L4: 0 | AN4: id Gas
F5: CO2, vol % | G5: 0.5 | H5: 0.5 | I5: 0.1 | J5: 5.1 | K5: 14.8 | L5: 0 | AN5: Henry-coefficient | AO5: S_(i/CO2)=H_CO2/H_i | AP5: p_i/p_CO2 | AQ5: n_i=n_CO2*(p_i/p_CO2)*S_(i/CO2) | AR5: Parameter | AS5: CO2 for CCU | AT5: Mole, mol | AU5: Mass flow, kg/h
F6: CH4, vol % | G6: 95 | H6: 90.4 | I6: 26.1 | J6: 3.8 | K6: 4.9 | L6: 0 | AN6: 626 | AO6: =$AN$9/AN6 -> 0.0079872204 | AP6: =AQ27/$AQ$30 -> 4.7907332 | AQ6: =$AT$9*AO6*AP6 -> 1811.6996 | AR6: H2, vol % | AS6: =AT6/$AT$13*100 -> 3.5844871 | AT6: =AQ6 -> 1811.6996
F7: C2+, vol % | G7: 3.5 | H7: 3.3 | I7: 1 | J7: 0 | K7: 0 | L7: 0 | AN7: 364 | AO7: =$AN$9/AN7 -> 0.013736264 | AP7: =AQ28/$AQ$30 -> 0.050140283 | AQ7: =$AT$9*AO7*AP7 -> 32.609485 | AR7: N2, vol % | AS7: =AT7/$AT$13*100 -> 0.064518576 | AT7: =AQ7 -> 32.609485
F8: H2O, vol % | G8: 0 | H8: 0 | I8: 71.4 | J8: 28.3 | K8: 0.15 | L8: 0 | AN8: 239 | AO8: =$AN$9/AN8 -> 0.020920502 | AP8: =AQ29/$AQ$30 -> 0.67961032 | AQ8: =$AT$9*AO8*AP8 -> 673.16357 | AR8: CO, vol % | AS8: =AT8/$AT$13*100 -> 1.3318688 | AT8: =AQ8 -> 673.16357
F9: Quantity, m3 (STP/h) | G9: 2160 | H9: 2070 | I9: 7160 | J9: 10450 | K9: 8180 | L9: 5000.5 | AN9: 5 | AO9: =$AN$9/AN9 -> 1 | AP9: =AQ30/$AQ$30 -> 1 | AQ9: =$AT$9*AO9*AP9 -> 47346.571 | AR9: CO2, vol % | AS9: =AT9/$AT$13*100 -> 93.676223 | AT9: =AQ30-AV30 -> 47346.571 | AU9: =AT9*44/1000 -> 2083.2491
F10: Temperature, °C | G10: 20 | H10: 390 | I10: 520 | J10: 850 | K10: 20 | L10: 20 | AN10: 91.8 | AO10: =$AN$9/AN10 -> 0.054466231 | AP10: =AQ31/$AQ$30 -> 0.06468899 | AQ10: =$AT$9*AO10*AP10 -> 166.81927 | AR10: CH4, vol % | AS10: =AT10/$AT$13*100 -> 0.33005557 | AT10: =AQ10 -> 166.81927
F11: Pressure, MPa | G11: 2 | H11: 1.9 | I11: 1.9 | J11: 1.7 | K11: 1.6 | L11: 1.5 | AN11: 10.25 | AO11: =$AN$9/AN11 -> 0.48780488 | AP11: =AQ32/$AQ$30 -> 0 | AQ11: =$AT$9*AO11*AP11 -> 0 | AR11: C2+, vol % | AS11: =AT11/$AT$13*100 -> 0 | AT11: =AQ11 -> 0
P12: isenthalpic | AR12: H2O, vol % | AS12: =AT12/$AT$13*100 -> 1.0128473 | AT12: =AQ33 -> 511.92124
N13: Parameter | O13: HP reforming steam import | P13: From water to steam | Q13: Mole, mol | R13: Mass flow, kg/h | S13: Energy, kJ/h | AR13: Quantity, m3 (STP/h) | AS13: =AT13*$E$24*$B$34/$A$34/1000 -> 1252.2339 | AT13: =SUM(AT6:AT12) -> 50542.785
N14: Energy, kJ/kg | O14: 3166.1 | P14: =3166.1-84 -> 3082.1 | T14: https://www.peacesoftware.de/einigewerte/wasser_dampf.html | AR14: Temperature, °C | AS14: 20
N15: H2O, vol % | O15: 100 | Q15: =T33-L33 -> 147111.23 | R15: =Q15*18/1000 -> 2648.0021 | S15: =P14*R15 -> 8161407.1 | AR15: Pressure, MPa | AS15: 0.1
N16: Quantity, m3 (STP/h) | O16: =Q15*$E$24*$B$34/$A$34/1000 -> 3644.7865
N17: Temperature, °C | O17: 390 | P17: 390 | AM17: Parameter | AN17: Waste water | AO17: Mole, mol | AP17: Mass flow, kg/h
N18: Pressure, MPa | O18: 5.3 | P18: 5.3 | AM18: Specific enthalpy, kJ/kg | AN18: 84
AM19: H2O, vol % | AN19: 100 | AO19: =AC33-AQ33 -> 81109.348 | AP19: =AO19*18/1000 -> 1459.9683 | AQ19: =AN18*AP19 -> 122637.33
M20: S/C | AM20: Temperature, °C | AN20: 20 | AO20: https://www.peacesoftware.de/einigewerte/wasser_dampf.html
M21: 2.5 | AM21: Pressure, MPa | AN21: 0.1
AH22: T_in | AI22: T_out
E23: R | AD23: T_out HXI | AH23: 313.89263 | AI23: 440 | AR23: 1 – 2 % can even be reached in the main wash part with just ﬂash-regenerated methanol. Therefore external energy input is neglected as first simplification | AV23: 0.82 | AW23: H2 recovery
E24: 0.08314 | AD24: =S35 -> 520
C26: Parameter | D26: Feed, 1 | E26: Mole, mol | G26: Molar heat capacity, kJ/mol | H26: Heat-up energy, kJ/h | J26: Parameter | K26: Before desulfurization, 2 | L26: Mole, mol | O26: Molar heat capacity, kJ/mol | P26: Heat-up energy, kJ/h | R26: Parameter | S26: Reformer inlet, 3 | T26: Mole, mol | U26: Molar heat capacity, kJ/mol | V26: Heat-up energy, kJ/h | W26: Reaction number | X26: Reaction enthalpy, kJ/h | Y26: Insulation losses, kJ | AA26: Parameter | AB26: Reformer outlet, 4 | AC26: Mole, mol | AD26: Molar heat capacity, kJ/mol | AE26: Heat-down energy, kJ/h | AF26: Molar heat capacity, kJ/mol | AG26: Heat-down energy, kJ/h | AK26: Molar heat capacity, kJ/mol | AL26: Heat-down energy, kJ/h | AO26: Parameter | AP26: Pressure swing adsorption, 5 | AQ26: Mole, mol | AT26: Parameter | AU26: Pressure swing adsorption, 5 | AV26: Mole, mol | AX26: Parameter | AY26: H2 product, 6 | AZ26: Mole, mol
C27: H2, vol % | D27: 0 | E27: =($A$34)*($D$34*D27/100*1000)/($E$24*$B$34) -> 0 | G27: {=N91:N97} -> 11.412697 | H27: =G27*L27 -> 404777.26 | J27: H2, vol % | K27: =L27/$L$34*100 -> 28.061119 | L27: =E27+AI58 -> 35467.276 | O27: {=N99:N105} -> 3.9119754 | P27: =T27*O27 -> 138747.11 | R27: H2, vol % | S27: =T27/$T$34*100 -> 12.967727 | T27: =L27 -> 35467.276 | U27: {=N107:N113} -> 17.899022 | V27: =T27*U27 -> 634829.56 | W27: I | X27: =Z108*AC121 -> 12040545 | Y27: min | AA27: H2, vol % | AB27: 54.6059 | AC27: =AB27/100*$AC$34 -> 209963.62 | AD27: {=N115:N121} -> -17.899022 | AE27: =AC27*AD27 -> -3758143.6 | AF27: {=N123:N129} -> -6.2076423 | AG27: =AC27*AF27 -> -1303379.1 | AK27: {=N131:N137} -> -12.917366 | AL27: =AK27*AV27 -> -3178947.2 | AO27: H2, vol % | AP27: =AQ27/$AQ$34*100 -> 72.641178 | AQ27: =AC27+AC29*AH29 -> 247910.41 | AT27: H2, vol % | AU27: =AV27/$AV$34*100 -> 84.646203 | AV27: =AQ27-AT6 -> 246098.71 | AX27: H2, vol % | AY27: 99.99 | AZ27: =AY27/100*$AZ$34 -> 201810.48 | BA27: =AZ27/AV27 -> 0.82003874
C28: N2, vol % | D28: 1 | E28: =($A$34)*($D$34*D28/100*1000)/($E$24*$B$34) -> 551.93428 | G28: 9.0299095 | H28: =G28*L28 -> 23365.142 | J28: N2, vol % | K28: =L28/$L$34*100 -> 2.047209 | L28: =E28+AI59 -> 2587.5278 | O28: 3.7626703 | P28: =T28*O28 -> 9736.0143 | R28: N2, vol % | S28: =T28/$T$34*100 -> 0.9460652 | T28: =L28 -> 2587.5278 | U28: 18.616532 | V28: =T28*U28 -> 48170.796 | W28: IV | X28: =Z107*AC126 -> -286012.52 | Y28: 0.01 | AA28: N2, vol % | AB28: 0.6748 | AC28: =AB28/100*$AC$34 -> 2594.6547 | AD28: -18.616532 | AE28: =AC28*AD28 -> -48303.473 | AF28: -5.8595386 | AG28: =AC28*AF28 -> -15203.479 | AK28: -10.452252 | AL28: =AK28*AV28 -> -26779.141 | AO28: N2, vol % | AP28: =AQ28/$AQ$34*100 -> 0.76026969 | AQ28: =AC28 -> 2594.6547 | AT28: N2, vol % | AU28: =AV28/$AV$34*100 -> 0.88122118 | AV28: =AQ28-AT7 -> 2562.0452 | AX28: N2, vol % | AY28: 0.01 | AZ28: =AY28/100*$AZ$34 -> 20.183066
C29: CO, vol % | D29: 0 | E29: =($A$34)*($D$34*D29/100*1000)/($E$24*$B$34) -> 0 | G29: 10.524394 | H29: =G29*L29 -> 290733.74 | J29: CO, vol % | K29: =L29/$L$34*100 -> 21.856242 | L29: =E29+AI60 -> 27624.749 | O29: 4.0133733 | P29: =T29*O29 -> 110868.43 | R29: CO, vol % | S29: =T29/$T$34*100 -> 10.100303 | T29: =L29 -> 27624.749 | U29: 19.303674 | V29: =T29*U29 -> 533259.15 | W29: VII | X29: not relevant | Y29: max | AA29: CO, vol % | AB29: 19.0153 | AC29: =AB29/100*$AC$34 -> 73115.2 | AD29: -19.303674 | AE29: =AC29*AD29 -> -1411392 | AF29: -6.2944433 | AG29: =AC29*AF29 -> -460219.48 | AH29: 0.519 | AI29: CO-conversion | AK29: -12.051072 | AL29: =AK29*AV29 -> -415704.72 | AO29: CO, vol % | AP29: =AQ29/$AQ$34*100 -> 10.304831 | AQ29: =AC29*(1-AH29) -> 35168.411 | AT29: CO, vol % | AU29: =AV29/$AV$34*100 -> 11.864718 | AV29: =AQ29-AT8 -> 34495.248 | AX29: CO, vol % | AY29: 0 | AZ29: =AY29/100*$AZ$34 -> 0
C30: CO2, vol % | D30: 0.5 | E30: =($A$34)*($D$34*D30/100*1000)/($E$24*$B$34) -> 275.96714 | G30: 16.648488 | H30: =G30*L30 -> 63275.544 | J30: CO2, vol % | K30: =L30/$L$34*100 -> 3.0070332 | L30: =E30+AI61 -> 3800.6781 | O30: 6.580752 | P30: =T30*O30 -> 25011.32 | R30: CO2, vol % | S30: =T30/$T$34*100 -> 1.3896234 | T30: =L30 -> 3800.6781 | U30: 32.044939 | V30: =T30*U30 -> 121792.5 | W30: VIII | X30: =Z109*AC135 -> 834335.5 | Y30: 0.05 | Z30: CH4 Umsatz | AA30: CO2, vol % | AB30: 3.5893 | AC30: =AB30/100*$AC$34 -> 13801.117 | AD30: -32.044939 | AE30: =AC30*AD30 -> -442255.97 | AF30: -10.280325 | AG30: =AC30*AF30 -> -141879.97 | AK30: -19.143103 | AL30: =AK30*AV30 -> -84255.209 | AO30: CO2, vol % | AP30: =AQ30/$AQ$34*100 -> 15.162852 | AQ30: =AC30+(AC29*AH29) -> 51747.906 | AS30: [Ullmann's, Gas Production, 3. Gas Treating, 504] | AT30: CO2, vol % | AU30: 1.5 | AV30: =SUM(AQ27:AQ29,AQ31:AQ32)/(1-(AU30/100))*(AU30/100) -> 4401.335 | AX30: CO2, vol % | AY30: 0 | AZ30: =AY30/100*$AZ$34 -> 0
B31: 74 | C31: CH4, vol % | D31: 95 | E31: =($A$34)*($D$34*D31/100*1000)/($E$24*$B$34) -> 52433.757 | G31: 14.130909 | H31: =G31*L31 -> 776930.81 | J31: CH4, vol % | K31: =L31/$L$34*100 -> 43.500013 | L31: =E31+AI62 -> 54980.95 | O31: 7.3660903 | P31: =T31*O31 -> 404994.64 | R31: CH4, vol % | S31: =T31/$T$34*100 -> 20.102417 | T31: =L31 -> 54980.95 | U31: 42.380994 | V31: =T31*U31 -> 2330147.3 | Y31: 1100°C | Z31: 0.948 | AA31: CH4, vol % | AB31: 0.8706 | AC31: =AB31/100*$AC$34 -> 3347.5198 | AD31: -42.380994 | AE31: =AC31*AD31 -> -141871.22 | AF31: -11.183194 | AG31: =AC31*AF31 -> -37435.963 | AK31: -16.844385 | AL31: =AK31*AV31 -> -53576.944 | AO31: CH4, vol % | AP31: =AQ31/$AQ$34*100 -> 0.98086958 | AQ31: =AC31 -> 3347.5198 | AT31: CH4, vol % | AU31: =AV31/$AV$34*100 -> 1.0940091 | AV31: =AQ31-AT10 -> 3180.7005 | AX31: CH4, vol % | AY31: 0 | AZ31: =AY31/100*$AZ$34 -> 0
C32: C2+, vol % | D32: 3.5 | E32: =($A$34)*($D$34*D32/100*1000)/($E$24*$B$34) -> 1931.77 | G32: 14.130909 | H32: =G32*L32 -> 27297.666 | J32: C2+, vol % | K32: =L32/$L$34*100 -> 1.5283843 | L32: =E32+AI63 -> 1931.77 | O32: 7.3660903 | P32: =T32*O32 -> 14229.592 | R32: C2+, vol % | S32: =T32/$T$34*100 -> 0.70630366 | T32: =L32 -> 1931.77 | U32: 42.380994 | V32: =T32*U32 -> 81870.333 | Y32: 0 | AA32: C2+, vol % | AB32: 0 | AC32: =AB32/100*$AC$34 -> 0 | AD32: -42.380994 | AE32: =AC32*AD32 -> 0 | AF32: -11.183194 | AG32: =AC32*AF32 -> 0 | AK32: -16.844385 | AL32: =AK32*AV32 -> 0 | AO32: C2+, vol % | AP32: =AQ32/$AQ$34*100 -> 0 | AQ32: =AC32 -> 0 | AT32: C2+, vol % | AU32: =AV32/$AV$34*100 -> 0 | AV32: =AQ32-AT11 -> 0 | AX32: C2+, vol % | AY32: 0 | AZ32: =AY32/100*$AZ$34 -> 0
A33: p_0 | B33: T_0 | C33: H2O, vol % | D33: 0 | E33: =($A$34)*($D$34*D33/100*1000)/($E$24*$B$34) -> 0 | G33: 12.671218 | H33: =G33*L33 -> 0 | J33: H2O, vol % | K33: =L33/$L$34*100 -> 0 | L33: =E33+AI64 -> 0 | O33: 4.8794395 | P33: =T33*O33 -> 717820.33 | R33: H2O, vol % | S33: =T33/$T$34*100 -> 53.787561 | T33: =(T31+2*T32)*M21 -> 147111.23 | U33: 24.432108 | V33: =T33*U33 -> 3594237.3 | Z33: mol_out/mol_in | AA33: H2O, vol % | AB33: 21.2275 | AC33: =AB33/100*$AC$34 -> 81621.269 | AD33: -24.432108 | AE33: =AC33*AD33 -> -1994179.6 | AF33: -7.6334962 | AG33: =AC33*AF33 -> -623055.65 | AK33: -14.521697 | AL33: =AK33*AV33 -> 0 | AO33: H2O, vol % | AP33: 0.15 | AQ33: =SUM(AQ27:AQ32)/(1-(AP33/100))*(AP33/100) -> 511.92124 | AT33: H2O, vol % | AU33: =AV33/$AV$34*100 -> 0 | AV33: =AQ33-AT12 -> 0 | AX33: H2O, vol % | AY33: 0 | AZ33: =AY33/100*$AZ$34 -> 0
A34: 1 | B34: 298 | C34: Quantity, m3 (STP/h) | D34: 1367.4569 | E34: =($A$34)*($D$34*1000)/($E$24*$B$34) -> 55193.428 | J34: Quantity, m3 (STP/h) | K34: =L34*$E$24*$B$34/$A$34/1000 -> 3131.4764 | L34: =E34+AI65 -> 126392.95 | R34: Quantity, m3 (STP/h) | S34: =T34*$E$24*$B$34/$A$34/1000 -> 6776.2629 | T34: =SUM(T27:T33) -> 273504.18 | U34: {=SUMPRODUCT(S27:S33/100,_xlfn.ANCHORARRAY(U27))} -> 26.852632 | Z34: 1.405855 | AA34: Quantity, m3 (STP/h) | AB34: =AC34*$E$24*$B$34/$A$34/1000 -> 9526.4431 | AC34: =T34*Z34 -> 384507.21 | AD34: {=SUMPRODUCT(AB27:AB33/100,_xlfn.ANCHORARRAY(AD27))} -> -20.275682 | AF34: SUM | AK34: SUM | AL34: =SUM(AL27:AL33) -> -3759263.2 | AO34: Quantity, m3 (STP/h) | AP34: =AQ34*$E$24*$B$34/$A$34/1000 -> 8455.4782 | AQ34: =SUM(AQ27:AQ33) -> 341280.83 | AT34: Quantity, m3 (STP/h) | AU34: =AV34*$E$24*$B$34/$A$34/1000 -> 7203.2443 | AV34: =SUM(AV27:AV33) -> 290738.04 | AX34: Quantity, m3 (STP/h) | AY34: 5000.5 | AZ34: =($A$34)*($AY$34*1000)/($E$24*$B$34) -> 201830.66
C35: Temperature, °C | D35: 20 | J35: Temperature, °C | K35: 390 | R35: Temperature, °C | S35: 520 | X35: =T31*X36*Z31 -> 12185067 | AA35: Temperature, °C | AB35: 1100 | AF35: {=SUMPRODUCT(AB27:AB33/100,_xlfn.ANCHORARRAY(AF27))} -> -6.7129394 | AO35: Temperature, °C | AP35: 20 | AT35: Temperature, °C | AU35: 20 | AX35: Temperature, °C | AY35: 20
C36: Pressure, MPa | D36: 5.4 | J36: Pressure, MPa | K36: 5.3 | R36: Pressure, MPa | S36: 5.3 | U36: =U34*T34 -> 7344307 | X36: 233.78 | AA36: Pressure, MPa | AB36: 5.1 | AF36: =AF35*AC34 -> -2581173.6 | AO36: Pressure, MPa | AP36: 5 | AT36: Pressure, MPa | AU36: 5 | AX36: Pressure, MPa | AY36: 4.9
H37: =SUM(H27:H33) -> 1586380.2 | J37: SUM | P37: =SUM(P27:P33) -> 1421407.4 | R37: SUM | V37: =SUM(V27:V33) -> 7344307 | X37: =SUM(X27:X28,X30) -> 12588868 | Y37: =SUM(P37,V37,X37)/(1-(Y32))*Y32 -> 0 | AE37: =SUM(AE27:AE33) -> -7796145.8 | AG37: =SUM(AG27:AG33) -> -2581173.6
H38: 1311383.6
D39: =AV23-BA27 -> -3.8743044e-05 | K39: If too high CO CO2 contents for desulphurization, recycle adding after desulphurization | U39: Overall
D40: =(E31-AY63)*4+E32*7-AY61-(AZ27+AT6+AY59) -> 1409.6937 | U40: heat-adding | V40: heat-consuming
AG41: Temperature increase check | AT41: Purge gas recycle | AU41: Mole, mol | AW41: Parameter | AX41: Purge gas recycle | AY41: Mole, mol
E42: =E30+E31+E32*2 -> 56573.264 | S42: Electricity input | U42: =-AA45 -> -12588868 | Y42: =SUM(U42:U43,V47,V55) -> -12588868 | AH42: Reaction | AI42: Molar heat capacity, kJ/mol | AJ42: Heat-up energy, kJ/h | AT42: 49.813924 | AU42: =AT42/100*$AU$49 -> 44288.283 | AW42: H2, vol % | AX42: =AY42/$AY$49*100 -> 49.813901 | AY42: =AV27-AZ27 -> 44288.234
E43: =SUM(AT9,AT8,AY61,AY62,AY63) -> 56400.373 | S43: Reforming steam input | U43: 0 | AG43: Mole CH4, mol | AH43: =AQ29-AC29 -> -37946.789 | AI43: {=N139:N145} -> 3.8003366 | AJ43: =AI43*AQ27 -> 942143.01 | AT43: 2.8589989 | AU43: =AT43/100*$AU$49 -> 2541.8626 | AW43: N2, vol % | AX43: =AY43/$AY$49*100 -> 2.8590002 | AY43: =AV28-AZ28 -> 2541.8621
S44: HXF2- | V44: =P37 -> 1421407.4 | Z44: Electricity | AG44: Reaction enthalpy, kJ/mol | AH44: =AC141 -> -35.785963 | AI44: 3.5192102 | AJ44: =AI44*AQ28 -> 9131.1352 | AT44: 38.799065 | AU44: =AT44/100*$AU$49 -> 34495.255 | AW44: CO, vol % | AX44: =AY44/$AY$49*100 -> 38.799083 | AY44: =AV29-AZ29 -> 34495.248
P45: HXF1 | Q45: =U52+V53+V54 -> 0 | S45: SMR feed warming (HXI-) | V45: =V37 -> 7344307 | Z45: Energy input, kJ/h | AA45: =X37+Y37 -> 12588868 | AG45: Energy. kJ/h | AH45: =-AH43*AH44 -> -1357962.4 | AI45: 3.8077485 | AJ45: =AI45*AQ29 -> 133912.46 | AT45: 4.9504699 | AU45: =AT45/100*$AU$49 -> 4401.3359 | AW45: CO2, vol % | AX45: =AY45/$AY$49*100 -> 4.9504721 | AY45: =AV30-AZ30 -> 4401.335
S46: Reaction enthalpy | V46: =X37 -> 12588868 | AI46: 6.1941876 | AJ46: =AI46*AQ30 -> 320536.24 | AT46: 3.5775423 | AU46: =AT46/100*$AU$49 -> 3180.7012 | AW46: CH4, vol % | AX46: =AY46/$AY$49*100 -> 3.5775439 | AY46: =AV31-AZ31 -> 3180.7005
P47: HXF2 | Q47: =V44+U50+V51 -> 0 | S47: Insulation losses | V47: =Y37 -> 0 | AI47: 6.5305792 | AJ47: =AI47*AQ31 -> 21861.243 | AT47: 0 | AU47: =AT47/100*$AU$49 -> 0 | AW47: C2+, vol % | AX47: =AY47/$AY$49*100 -> 0 | AY47: =AV32-AZ32 -> 0
P48: HXI | Q48: =V45+U48+V49 -> 0 | S48: HXI+ | U48: =AE37 -> -7796145.8 | AI48: 6.5305792 | AJ48: =AI48*AQ32 -> 0 | AT48: 0 | AU48: =AT48/100*$AU$49 -> 0 | AW48: H2O, vol % | AX48: =AY48/$AY$49*100 -> 0 | AY48: =AV33-AZ33 -> 0
S49: HXI difference (for steam production) | V49: =-U48-V45 -> 451838.86 | AI49: 4.604536 | AJ49: =AI49*AQ33 -> 2357.1598 | AT49: 2202.7458 | AU49: =$A$34*AT49*1000/(E24*B34) -> 88907.437 | AW49: Quantity, m3 (STP/h) | AX49: =AU34-AY34-AK68 -> 2202.7443 | AY49: =AV34-AZ34 -> 88907.379
S50: HXF2+ | U50: =AG37 -> -2581173.6 | AH50: =AH45+AJ50 -> 71978.876 | AI50: SUM | AJ50: =SUM(AJ43:AJ49) -> 1429941.3 | AW50: Temperature, °C | AX50: =AU35 -> 20
S51: HXF2 difference (for steam production) | V51: =-U50-V44 -> 1159766.2 | AW51: Pressure, MPa | AX51: 0.1
S52: HXF1+ | U52: =AL34 -> -3759263.2
S53: HXF1- | V53: =H37 -> 1586380.2
S54: HXF1- difference (for steam production) | V54: =-U52-V53 -> 2172883.1 | AH54: R/F
S55: Losses | V55: 0 | X55: =X56/U56 -> 0 | AH55: 1.29
S56: SUM | U56: =SUM(U42:U54) -> -26725451 | V56: =SUM(V42:V54) -> 26725451 | W56: Delta | X56: =SUM(U56:V56) -> 0
AG57: Parameter | AH57: Recycle gas | AI57: Mole, mol
AG58: H2, vol % | AH58: =AT42 -> 49.813924 | AI58: =AH58/100*$AI$65 -> 35467.276 | AW58: Parameter | AX58: Purge gas burn | AY58: Mole, mol | AZ58: Mass CO2, kg/h | BB58: LHV 25°C, kJ/mol | BC58: Combustion energy, kJ/h
S59: C | T59: =T29+T30+T31+T32*2 -> 90269.917 | AB59: C | AC59: =AC29+AC30+AC31+AC32 -> 90263.838 | AG59: N2, vol % | AH59: =AT43 -> 2.8589989 | AI59: =AH59/100*$AI$65 -> 2035.5936 | AW59: H2, vol % | AX59: =AT42 -> 49.813924 | AY59: =AU42-AI58 -> 8821.007 | BB59: 244 | BC59: =BB59*AY59*-1 -> -2152325.7
S60: H | T60: =T27*2+T31*4+T32*6+T33*2 -> 596671.42 | AB60: H | AC60: =AC27*2+AC31*4+AC33*2 -> 596559.87 | AG60: CO, vol % | AH60: =AT44 -> 38.799065 | AI60: =AH60/100*$AI$65 -> 27624.749 | AR60: GGW bei WGS liegt wieder weit bei CH4 und H2O, zur modellierung ist die betrachtung der Kinetik von relevanz (Kat für WGSR aber nicht für SMR) | AW60: N2, vol % | AX60: =AT43 -> 2.8589989 | AY60: =AU43-AI59 -> 506.26908 | BA60: =E28-AT7-AZ28-AY60 -> -7.1273431
S61: O | T61: =T29+T30*2+T33 -> 182337.33 | AB61: O | AC61: =AC29+AC30*2+AC33 -> 182338.7 | AG61: CO2, vol % | AH61: =AT45 -> 4.9504699 | AI61: =AH61/100*$AI$65 -> 3524.7109 | AR61: Daher wird annahme gemacht und eine 50% konversion von CO angenommen | AW61: CO, vol % | AX61: =AT44 -> 38.799065 | AY61: =AU44-AI60 -> 6870.5053 | AZ61: =AY61*44/1000 -> 302.30223 | BB61: 283.24 | BC61: =BB61*AY61*-1 -> -1946001.9
AG62: CH4, vol % | AH62: =AT46 -> 3.5775423 | AI62: =AH62/100*$AI$65 -> 2547.193 | AR62: N2-Inertgas, H2 purity is directly dependant of N2 content in NG | AW62: CO2, vol % | AX62: =AT45 -> 4.9504699 | AY62: =AU45-AI61 -> 876.62497 | AZ62: =AY62*44/1000 -> 38.571499
AG63: C2+, vol % | AH63: =AT47 -> 0 | AI63: =AH63/100*$AI$65 -> 0 | AR63: CO-Nutzung through recycle | AW63: CH4, vol % | AX63: =AT46 -> 3.5775423 | AY63: =AU46-AI62 -> 633.50813 | AZ63: =AY63*44/1000 -> 27.874358 | BB63: 802.34 | BC63: =BB63*AY63*-1 -> -508288.91
AG64: H2O, vol % | AH64: =AT48 -> 0 | AI64: =AH64/100*$AI$65 -> 0 | AR64: Höheres Druckniveau angenommen wegen Rectisol, aber dafür notwendige verdichtung vernachlässigt | AW64: C2+, vol % | AX64: =AT47 -> 0 | AY64: =AU47-AI63 -> 0 | BB64: 1437.2 | BC64: 0
AG65: Quantity, m3 (STP/h) | AH65: =D34*AH55 -> 1764.0194 | AI65: =($A$34)*($AH$65*1000)/($E$24*$B$34) -> 71199.523 | AR65: Durch Recycle und darin included hydrogen no H2-product recycle to desulphurization is necessary | AW65: H2O, vol % | AX65: =AT48 -> 0 | AY65: =AU48-AI64 -> 0
AG66: Temperature, °C | AR66: Simplification, that CO2 removal doesn't need energy | AW66: Quantity, m3 (STP/h) | AX66: =AY66*$E$24*$B$34/$A$34/1000 -> 438.72633 | AY66: =AU49-AI65 -> 17707.914
AG67: Pressure, MPa | AH67: =AE52 -> 0 | AW67: Temperature, °C | AX67: =AU35 -> 20
AW68: Pressure, MPa | AX68: 0.1 | BD68: Boiler efficiency
AW69: SUM | BC69: =SUM(BC59:BC65) -> -4606616.5 | BD69: 0.95 | BE69: =BC69*BD69 -> -4376285.7 | BF69: =S15-V49-V51-V54+BE69 -> 633.31857
BD70: https://www.sciencedirect.com/topics/engineering/boiler-efficiency
F87: Molar heat capacity (temperature dependant), integral | P87: Reaction rate determination
F88: 1 bar, ideal gas | S88: H2 | T88: CO | U88: CO2 | V88: CH4 | W88: C2H6 | X88: H2O | Y88: C | AA88: Comment
G89: A | H89: B | I89: C | J89: D | K89: E | L89: T_1 | M89: T_0 | N89: deltah_Tj, kJ/mol | P89: I | R89: xi_1 | S89: 3 | T89: 1 | V89: -1 | X89: -1
F90: Feed (20->390°C) | P90: II | R90: xi_2 | S90: 1 | T90: -1 | U90: 1 | X90: -1 | Z90: linear dependant equation | AA90: Not possible to choose equation II, as in that case deltaN_C is said to be zero, which leads to a huge error in H balance, as the H balance will be a degree of freedom in that case.
F91: H2 | G91: 33.066178 | H91: -11.363417 | I91: 11.432816 | J91: -2.772874 | K91: -0.158558 | L91: =$K$35+273 -> 663 | M91: =$D$35+273 -> 293 | N91: =(G91*(L91-M91)+H91/2000*(L91^2-M91^2)+I91/(3*10^6)*(L91^3-M91^3)+J91/(4*10^9)*(L91^4-M91^4)-(10^6*K91)*(1/M91-1/L91))/1000 -> 11.412697 | P91: III | S91: 4 | U91: 1 | V91: -1 | X91: -2 | Z91: linear dependant equation
F92: N2 | G92: 19.50583 | H92: 19.88705 | I92: -8.598535 | J92: 1.369784 | K92: 0.527601 | L92: =$K$35+273 -> 663 | M92: =$D$35+273 -> 293 | N92: =(G92*(L92-M92)+H92/2000*(L92^2-M92^2)+I92/(3*10^6)*(L92^3-M92^3)+J92/(4*10^9)*(L92^4-M92^4)-(10^6*K92)*(1/M92-1/L92))/1000 -> 9.0299095 | P92: IV | S92: 2 | T92: 2 | U92: -1 | V92: -1
F93: CO | G93: 25.56759 | H93: 6.09613 | I93: 4.054656 | J93: -2.671301 | K93: 0.131021 | L93: =$K$35+273 -> 663 | M93: =$D$35+273 -> 293 | N93: =(G93*(L93-M93)+H93/2000*(L93^2-M93^2)+I93/(3*10^6)*(L93^3-M93^3)+J93/(4*10^9)*(L93^4-M93^4)-(10^6*K93)*(1/M93-1/L93))/1000 -> 10.524394 | P93: V | Q93: soot-forming | S93: -1 | T93: -1 | X93: 1 | Y93: 1 | Z93: linear dependant equation
F94: CO2 | G94: 24.99735 | H94: 55.18696 | I94: -33.69137 | J94: 7.948387 | K94: -0.136638 | L94: =$K$35+273 -> 663 | M94: =$D$35+273 -> 293 | N94: =(G94*(L94-M94)+H94/2000*(L94^2-M94^2)+I94/(3*10^6)*(L94^3-M94^3)+J94/(4*10^9)*(L94^4-M94^4)-(10^6*K94)*(1/M94-1/L94))/1000 -> 16.648488 | P94: VI | Q94: soot-forming | T94: -2 | U94: 1 | Y94: 1 | Z94: linear dependant equation
F95: CH4 | G95: -0.703029 | H95: 108.4773 | I95: -42.52157 | J95: 5.862788 | K95: 0.678565 | L95: =$K$35+273 -> 663 | M95: =$D$35+273 -> 293 | N95: =(G95*(L95-M95)+H95/2000*(L95^2-M95^2)+I95/(3*10^6)*(L95^3-M95^3)+J95/(4*10^9)*(L95^4-M95^4)-(10^6*K95)*(1/M95-1/L95))/1000 -> 14.130909 | P95: VII | Q95: soot-forming | R95: xi_3 | S95: 2 | V95: -1 | Y95: 1
F96: C2+ | L96: =$K$35+273 -> 663 | M96: =$D$35+273 -> 293 | N96: =N95 -> 14.130909 | O96: approximation with CH4 values | P96: VIII | R96: xi_4 | S96: 5 | T96: 2 | W96: -1 | X96: -2
F97: H2O | G97: 30.092 | H97: 6.832514 | I97: 6.793435 | J97: -2.53448 | K97: 0.082139 | L97: =$K$35+273 -> 663 | M97: =$D$35+273 -> 293 | N97: =(G97*(L97-M97)+H97/2000*(L97^2-M97^2)+I97/(3*10^6)*(L97^3-M97^3)+J97/(4*10^9)*(L97^4-M97^4)-(10^6*K97)*(1/M97-1/L97))/1000 -> 12.671218
F98: Feed (390->520°C) | P98: II* | Q98: I-II | S98: =S89-S90 -> 2 | T98: =T89-T90 -> 2 | U98: =U89-U90 -> -1 | V98: =V89-V90 -> -1 | W98: =W89-W90 -> 0 | X98: =X89-X90 -> 0 | Y98: =Y89-Y90 -> 0
F99: H2 | G99: 33.066178 | H99: -11.363417 | I99: 11.432816 | J99: -2.772874 | K99: -0.158558 | L99: =$S$35+273 -> 793 | M99: =$K$35+273 -> 663 | N99: =(G99*(L99-M99)+H99/2000*(L99^2-M99^2)+I99/(3*10^6)*(L99^3-M99^3)+J99/(4*10^9)*(L99^4-M99^4)-(10^6*K99)*(1/M99-1/L99))/1000 -> 3.9119754 | P99: III* | Q99: 2I-III | S99: =2*S89-S91 -> 2 | T99: =2*T89-T91 -> 2 | U99: =2*U89-U91 -> -1 | V99: =2*V89-V91 -> -1 | W99: =2*W89-W91 -> 0 | X99: =2*X89-X91 -> 0 | Y99: =2*Y89-Y91 -> 0
F100: N2 | G100: 19.50583 | H100: 19.88705 | I100: -8.598535 | J100: 1.369784 | K100: 0.527601 | L100: =$S$35+273 -> 793 | M100: =$K$35+273 -> 663 | N100: =(G100*(L100-M100)+H100/2000*(L100^2-M100^2)+I100/(3*10^6)*(L100^3-M100^3)+J100/(4*10^9)*(L100^4-M100^4)-(10^6*K100)*(1/M100-1/L100))/1000 -> 3.7626703 | P100: V* | Q100: I+V | S100: =S89+S93 -> 2 | T100: =T89+T93 -> 0 | U100: =U89+U93 -> 0 | V100: =V89+V93 -> -1 | W100: =W89+W93 -> 0 | X100: =X89+X93 -> 0 | Y100: =Y89+Y93 -> 1
F101: CO | G101: 25.56759 | H101: 6.09613 | I101: 4.054656 | J101: -2.671301 | K101: 0.131021 | L101: =$S$35+273 -> 793 | M101: =$K$35+273 -> 663 | N101: =(G101*(L101-M101)+H101/2000*(L101^2-M101^2)+I101/(3*10^6)*(L101^3-M101^3)+J101/(4*10^9)*(L101^4-M101^4)-(10^6*K101)*(1/M101-1/L101))/1000 -> 4.0133733 | P101: VI* | Q101: VI-II | S101: =S94-S90 -> -1 | T101: =T94-T90 -> -1 | U101: =U94-U90 -> 0 | V101: =V94-V90 -> 0 | W101: =W94-W90 -> 0 | X101: =X94-X90 -> 1 | Y101: =Y94-Y90 -> 1
F102: CO2 | G102: 24.99735 | H102: 55.18696 | I102: -33.69137 | J102: 7.948387 | K102: -0.136638 | L102: =$S$35+273 -> 793 | M102: =$K$35+273 -> 663 | N102: =(G102*(L102-M102)+H102/2000*(L102^2-M102^2)+I102/(3*10^6)*(L102^3-M102^3)+J102/(4*10^9)*(L102^4-M102^4)-(10^6*K102)*(1/M102-1/L102))/1000 -> 6.580752
F103: CH4 | G103: -0.703029 | H103: 108.4773 | I103: -42.52157 | J103: 5.862788 | K103: 0.678565 | L103: =$S$35+273 -> 793 | M103: =$K$35+273 -> 663 | N103: =(G103*(L103-M103)+H103/2000*(L103^2-M103^2)+I103/(3*10^6)*(L103^3-M103^3)+J103/(4*10^9)*(L103^4-M103^4)-(10^6*K103)*(1/M103-1/L103))/1000 -> 7.3660903 | AB103: Double-check
F104: C2+ | L104: =$S$35+273 -> 793 | M104: =$K$35+273 -> 663 | N104: =N103 -> 7.3660903 | S104: xi_1 | T104: xi_2 | U104: xi_3 | V104: xi_4 | AB104: balance | AC104: calculated | AD104: error
F105: H2O (xxx->520°C) | G105: 30.092 | H105: 6.832514 | I105: 6.793435 | J105: -2.53448 | K105: 0.082139 | L105: =$S$35+273 -> 793 | M105: =$P$17+273 -> 663 | N105: =(G105*(L105-M105)+H105/2000*(L105^2-M105^2)+I105/(3*10^6)*(L105^3-M105^3)+J105/(4*10^9)*(L105^4-M105^4)-(10^6*K105)*(1/M105-1/L105))/1000 -> 4.8794395 | R105: deltaN_H2 | S105: =S89 -> 3 | T105: =S90 -> 1 | U105: =S95 -> 2 | V105: =S96 -> 5 | AB105: =AB27/100*AC34-S27/100*T34 -> 174496.35 | AC105: =S105*Z$108+T105*Z$107+U105*Z$111+V105*Z$109 -> 174559.58 | AD105: =(AC105-AB105)/AB105 -> 0.00036236493
F106: Feed (520->1100°C) | R106: deltaN_CO | S106: =T89 -> 1 | T106: =T90 -> -1 | V106: =T96 -> 2 | AB106: =AB29/100*AC34-S29/100*T34 -> 45490.451 | AC106: =S106*Z$108+T106*Z$107+U106*Z$111+V106*Z$109 -> 45496.531 | AD106: =(AC106-AB106)/AB106 -> 0.00013365408
F107: H2 | G107: 33.066178 | H107: -11.363417 | I107: 11.432816 | J107: -2.772874 | K107: -0.158558 | L107: =$AB$35+273 -> 1373 | M107: =$S$35+273 -> 793 | N107: =(G107*(L107-M107)+H107/2000*(L107^2-M107^2)+I107/(3*10^6)*(L107^3-M107^3)+J107/(4*10^9)*(L107^4-M107^4)-(10^6*K107)*(1/M107-1/L107))/1000 -> 17.899022 | R107: deltaN_CO2 | T107: =U90 -> 1 | W107: =AB30/100*AC34-S30/100*T34 -> 10000.439 | X107: -> | Y107: xi_2 = | Z107: =W107*T107 -> 10000.439 | AA107: mol
F108: N2 | G108: 19.50583 | H108: 19.88705 | I108: -8.598535 | J108: 1.369784 | K108: 0.527601 | L108: =$AB$35+273 -> 1373 | M108: =$S$35+273 -> 793 | N108: =(G108*(L108-M108)+H108/2000*(L108^2-M108^2)+I108/(3*10^6)*(L108^3-M108^3)+J108/(4*10^9)*(L108^4-M108^4)-(10^6*K108)*(1/M108-1/L108))/1000 -> 18.616532 | R108: deltaN_CH4 | S108: =V89 -> -1 | U108: =V95 -> -1 | W108: =AB31/100*AC34-S31/100*T34 -> -51633.43 | X108: -> | Y108: xi_1 = | Z108: =(W108-(U108*Z111))/S108 -> 51633.43 | AA108: mol
F109: CO | G109: 25.56759 | H109: 6.09613 | I109: 4.054656 | J109: -2.671301 | K109: 0.131021 | L109: =$AB$35+273 -> 1373 | M109: =$S$35+273 -> 793 | N109: =(G109*(L109-M109)+H109/2000*(L109^2-M109^2)+I109/(3*10^6)*(L109^3-M109^3)+J109/(4*10^9)*(L109^4-M109^4)-(10^6*K109)*(1/M109-1/L109))/1000 -> 19.303674 | R109: deltaN_C2H6 | V109: =W96 -> -1 | W109: =AB32/100*AC34-S32/100*T34 -> -1931.77 | X109: -> | Y109: xi_4 = | Z109: =W109*V109 -> 1931.77 | AA109: mol
F110: CO2 | G110: 24.99735 | H110: 55.18696 | I110: -33.69137 | J110: 7.948387 | K110: -0.136638 | L110: =$AB$35+273 -> 1373 | M110: =$S$35+273 -> 793 | N110: =(G110*(L110-M110)+H110/2000*(L110^2-M110^2)+I110/(3*10^6)*(L110^3-M110^3)+J110/(4*10^9)*(L110^4-M110^4)-(10^6*K110)*(1/M110-1/L110))/1000 -> 32.044939 | R110: deltaN_H2O | S110: =X89 -> -1 | T110: =X90 -> -1 | V110: -2 | AB110: =AB33/100*AC34-S33/100*T34 -> -65489.956 | AC110: =S110*Z$108+T110*Z$107+U110*Z$111+V110*Z$109 -> -65497.41 | AD110: =(AC110-AB110)/AB110 -> 0.00011380792
F111: CH4 | G111: -0.703029 | H111: 108.4773 | I111: -42.52157 | J111: 5.862788 | K111: 0.678565 | L111: =$AB$35+273 -> 1373 | M111: =$S$35+273 -> 793 | N111: =(G111*(L111-M111)+H111/2000*(L111^2-M111^2)+I111/(3*10^6)*(L111^3-M111^3)+J111/(4*10^9)*(L111^4-M111^4)-(10^6*K111)*(1/M111-1/L111))/1000 -> 42.380994 | R111: deltaN_C | U111: =Y95 -> 1 | W111: 0 | X111: -> | Y111: xi_3 = | Z111: 0 | AA111: mol | AB111: 0 | AC111: =S111*Z$110+T111*Z$107+U111*Z$105+V111*Z$109 -> 0
F112: C2+ | L112: =$AB$35+273 -> 1373 | M112: =$S$35+273 -> 793 | N112: =N111 -> 42.380994
F113: H2O | G113: 30.092 | H113: 6.832514 | I113: 6.793435 | J113: -2.53448 | K113: 0.082139 | L113: =$AB$35+273 -> 1373 | M113: =$S$35+273 -> 793 | N113: =(G113*(L113-M113)+H113/2000*(L113^2-M113^2)+I113/(3*10^6)*(L113^3-M113^3)+J113/(4*10^9)*(L113^4-M113^4)-(10^6*K113)*(1/M113-1/L113))/1000 -> 24.432108
F114: Feed (1100->520°C) | P114: Reaction enthalpy determination
F115: H2 | G115: 33.066178 | H115: -11.363417 | I115: 11.432816 | J115: -2.772874 | K115: -0.158558 | L115: =$AD$24+273 -> 793 | M115: =$AB$35+273 -> 1373 | N115: =(G115*(L115-M115)+H115/2000*(L115^2-M115^2)+I115/(3*10^6)*(L115^3-M115^3)+J115/(4*10^9)*(L115^4-M115^4)-(10^6*K115)*(1/M115-1/L115))/1000 -> -17.899022 | AB115: neglected because ideal gas
F116: N2 | G116: 19.50583 | H116: 19.88705 | I116: -8.598535 | J116: 1.369784 | K116: 0.527601 | L116: =$AD$24+273 -> 793 | M116: =$AB$35+273 -> 1373 | N116: =(G116*(L116-M116)+H116/2000*(L116^2-M116^2)+I116/(3*10^6)*(L116^3-M116^3)+J116/(4*10^9)*(L116^4-M116^4)-(10^6*K116)*(1/M116-1/L116))/1000 -> -18.616532 | Q116: species | R116: nu_j | S116: deltah_j_std, kJ/mol | T116: A | U116: B | V116: C | W116: D | X116: E | Y116: T_1 | Z116: T_0 | AA116: deltah_Tj, kJ/mol | AB116: deltah_pj
F117: CO | G117: 25.56759 | H117: 6.09613 | I117: 4.054656 | J117: -2.671301 | K117: 0.131021 | L117: =$AD$24+273 -> 793 | M117: =$AB$35+273 -> 1373 | N117: =(G117*(L117-M117)+H117/2000*(L117^2-M117^2)+I117/(3*10^6)*(L117^3-M117^3)+J117/(4*10^9)*(L117^4-M117^4)-(10^6*K117)*(1/M117-1/L117))/1000 -> -19.303674 | P117: I | Q117: CH4 | R117: -1 | S117: -74.6 | T117: -0.703029 | U117: 108.4773 | V117: -42.52157 | W117: 5.862788 | X117: 0.678565 | Y117: =$AB$35+273 -> 1373 | Z117: 298 | AA117: =(T117*(Y117-Z117)+U117/2000*(Y117^2-Z117^2)+V117/(3*10^6)*(Y117^3-Z117^3)+W117/(4*10^9)*(Y117^4-Z117^4)-(10^6*X117)*(1/Z117-1/Y117))/1000 -> 63.7779 | AB117: -
...

Sheet OCMC eSMR NASA
F1: Parameter | G1: Feed, 1 | H1: Before desulfurization, 2 | I1: Reformer inlet, 3 | J1: Reformer outlet, 4 | K1: Pressure swing adsorption, 5 | L1: H2 product, 6
F2: H2, vol % | G2: 0 | H2: 4.8 | I2: 1.1 | J2: 51.9 | K2: 74.6 | L2: 99.99
F3: N2, vol % | G3: 1 | H3: 1 | I3: 0.3 | J3: 0.2 | K3: 0.25 | L3: 0.01
F4: CO, vol % | G4: 0 | H4: 0 | I4: 0 | J4: 10.7 | K4: 5.3 | L4: 0 | AN4: id Gas
F5: CO2, vol % | G5: 0.5 | H5: 0.5 | I5: 0.1 | J5: 5.1 | K5: 14.8 | L5: 0 | AN5: Henry-coefficient | AO5: S_(i/CO2)=H_CO2/H_i | AP5: p_i/p_CO2 | AQ5: n_i=n_CO2*(p_i/p_CO2)*S_(i/CO2) | AR5: Parameter | AS5: CO2 for CCU | AT5: Mole, mol | AU5: Mass flow, kg/h
F6: CH4, vol % | G6: 95 | H6: 90.4 | I6: 26.1 | J6: 3.8 | K6: 4.9 | L6: 0 | AN6: 626 | AO6: =$AN$9/AN6 -> 0.0079872204 | AP6: =AQ27/$AQ$30 -> 4.7907332 | AQ6: =$AT$9*AO6*AP6 -> 1811.6996 | AR6: H2, vol % | AS6: =AT6/$AT$13*100 -> 3.5844871 | AT6: =AQ6 -> 1811.6996
F7: C2+, vol % | G7: 3.5 | H7: 3.3 | I7: 1 | J7: 0 | K7: 0 | L7: 0 | AN7: 364 | AO7: =$AN$9/AN7 -> 0.013736264 | AP7: =AQ28/$AQ$30 -> 0.050140283 | AQ7: =$AT$9*AO7*AP7 -> 32.609485 | AR7: N2, vol % | AS7: =AT7/$AT$13*100 -> 0.064518576 | AT7: =AQ7 -> 32.609485
F8: H2O, vol % | G8: 0 | H8: 0 | I8: 71.4 | J8: 28.3 | K8: 0.15 | L8: 0 | AN8: 239 | AO8: =$AN$9/AN8 -> 0.020920502 | AP8: =AQ29/$AQ$30 -> 0.67961032 | AQ8: =$AT$9*AO8*AP8 -> 673.16357 | AR8: CO, vol % | AS8: =AT8/$AT$13*100 -> 1.3318688 | AT8: =AQ8 -> 673.16357
F9: Quantity, m3 (STP/h) | G9: 2160 | H9: 2070 | I9: 7160 | J9: 10450 | K9: 8180 | L9: 5000.5 | AN9: 5 | AO9: =$AN$9/AN9 -> 1 | AP9: =AQ30/$AQ$30 -> 1 | AQ9: =$AT$9*AO9*AP9 -> 47346.571 | AR9: CO2, vol % | AS9: =AT9/$AT$13*100 -> 93.676223 | AT9: =AQ30-AV30 -> 47346.571 | AU9: =AT9*44/1000 -> 2083.2491
F10: Temperature, °C | G10: 20 | H10: 390 | I10: 520 | J10: 850 | K10: 20 | L10: 20 | AN10: 91.8 | AO10: =$AN$9/AN10 -> 0.054466231 | AP10: =AQ31/$AQ$30 -> 0.06468899 | AQ10: =$AT$9*AO10*AP10 -> 166.81927 | AR10: CH4, vol % | AS10: =AT10/$AT$13*100 -> 0.33005557 | AT10: =AQ10 -> 166.81927
F11: Pressure, MPa | G11: 2 | H11: 1.9 | I11: 1.9 | J11: 1.7 | K11: 1.6 | L11: 1.5 | AN11: 10.25 | AO11: =$AN$9/AN11 -> 0.48780488 | AP11: =AQ32/$AQ$30 -> 0 | AQ11: =$AT$9*AO11*AP11 -> 0 | AR11: C2+, vol % | AS11: =AT11/$AT$13*100 -> 0 | AT11: =AQ11 -> 0
P12: isenthalpic | AR12: H2O, vol % | AS12: =AT12/$AT$13*100 -> 1.0128473 | AT12: =AQ33 -> 511.92124
N13: Parameter | O13: HP reforming steam import | P13: From water to steam | Q13: Mole, mol | R13: Mass flow, kg/h | S13: Energy, kJ/h | AR13: Quantity, m3 (STP/h) | AS13: =AT13*$E$24*$B$34/$A$34/1000 -> 1252.2339 | AT13: =SUM(AT6:AT12) -> 50542.785
N14: Energy, kJ/kg | O14: 3166.1 | P14: =3166.1-84 -> 3082.1 | T14: https://www.peacesoftware.de/einigewerte/wasser_dampf.html | AR14: Temperature, °C | AS14: 20
N15: H2O, vol % | O15: 100 | Q15: =T33-L33 -> 147111.23 | R15: =Q15*18/1000 -> 2648.0021 | S15: =P14*R15 -> 8161407.1 | AR15: Pressure, MPa | AS15: 0.1
N16: Quantity, m3 (STP/h) | O16: =Q15*$E$24*$B$34/$A$34/1000 -> 3644.7865
N17: Temperature, °C | O17: 390 | P17: 390 | AM17: Parameter | AN17: Waste water | AO17: Mole, mol | AP17: Mass flow, kg/h
N18: Pressure, MPa | O18: 5.3 | P18: 5.3 | AM18: Specific enthalpy, kJ/kg | AN18: 84
AM19: H2O, vol % | AN19: 100 | AO19: =AC33-AQ33 -> 81109.348 | AP19: =AO19*18/1000 -> 1459.9683 | AQ19: =AN18*AP19 -> 122637.33
M20: S/C | AM20: Temperature, °C | AN20: 20 | AO20: https://www.peacesoftware.de/einigewerte/wasser_dampf.html
M21: 2.5 | AM21: Pressure, MPa | AN21: 0.1
AH22: T_in | AI22: T_out
E23: R | AD23: T_out HXI | AH23: 313.89263 | AI23: 440 | AR23: 1 – 2 % can even be reached in the main wash part with just ﬂash-regenerated methanol. Therefore external energy input is neglected as first simplification | AV23: 0.82 | AW23: H2 recovery
E24: 0.08314 | AD24: =S35 -> 520
C26: Parameter | D26: Feed, 1 | E26: Mole, mol | G26: Molar heat capacity, kJ/mol | H26: Heat-up energy, kJ/h | J26: Parameter | K26: Before desulfurization, 2 | L26: Mole, mol | O26: Molar heat capacity, kJ/mol | P26: Heat-up energy, kJ/h | R26: Parameter | S26: Reformer inlet, 3 | T26: Mole, mol | U26: Molar heat capacity, kJ/mol | V26: Heat-up energy, kJ/h | W26: Reaction number | X26: Reaction enthalpy, kJ/h | Y26: Insulation losses, kJ | AA26: Parameter | AB26: Reformer outlet, 4 | AC26: Mole, mol | AD26: Molar heat capacity, kJ/mol | AE26: Heat-down energy, kJ/h | AF26: Molar heat capacity, kJ/mol | AG26: Heat-down energy, kJ/h | AK26: Molar heat capacity, kJ/mol | AL26: Heat-down energy, kJ/h | AO26: Parameter | AP26: Pressure swing adsorption, 5 | AQ26: Mole, mol | AT26: Parameter | AU26: Pressure swing adsorption, 5 | AV26: Mole, mol | AX26: Parameter | AY26: H2 product, 6 | AZ26: Mole, mol
C27: H2, vol % | D27: 0 | E27: =($A$34)*($D$34*D27/100*1000)/($E$24*$B$34) -> 0 | G27: {=N91:N97} -> 11.412697 | H27: =G27*L27 -> 404777.26 | J27: H2, vol % | K27: =L27/$L$34*100 -> 28.061119 | L27: =E27+AI58 -> 35467.276 | O27: {=N99:N105} -> 3.9119754 | P27: =T27*O27 -> 138747.11 | R27: H2, vol % | S27: =T27/$T$34*100 -> 12.967727 | T27: =L27 -> 35467.276 | U27: {=N107:N113} -> 17.899022 | V27: =T27*U27 -> 634829.56 | W27: I | X27: =Z108*AI121 -> 11665860 | Y27: min | AA27: H2, vol % | AB27: 54.6059 | AC27: =AB27/100*$AC$34 -> 209963.62 | AD27: {=N115:N121} -> -17.899022 | AE27: =AC27*AD27 -> -3758143.6 | AF27: {=N123:N129} -> -6.2076423 | AG27: =AC27*AF27 -> -1303379.1 | AK27: {=N131:N137} -> -12.917366 | AL27: =AK27*AV27 -> -3178947.2 | AO27: H2, vol % | AP27: =AQ27/$AQ$34*100 -> 72.641178 | AQ27: =AC27+AC29*AH29 -> 247910.41 | AT27: H2, vol % | AU27: =AV27/$AV$34*100 -> 84.646203 | AV27: =AQ27-AT6 -> 246098.71 | AX27: H2, vol % | AY27: 99.99 | AZ27: =AY27/100*$AZ$34 -> 201810.48 | BA27: =AZ27/AV27 -> 0.82003874
C28: N2, vol % | D28: 1 | E28: =($A$34)*($D$34*D28/100*1000)/($E$24*$B$34) -> 551.93428 | G28: 9.0299095 | H28: =G28*L28 -> 23365.142 | J28: N2, vol % | K28: =L28/$L$34*100 -> 2.047209 | L28: =E28+AI59 -> 2587.5278 | O28: 3.7626703 | P28: =T28*O28 -> 9736.0143 | R28: N2, vol % | S28: =T28/$T$34*100 -> 0.9460652 | T28: =L28 -> 2587.5278 | U28: 18.616532 | V28: =T28*U28 -> 48170.796 | W28: IV | X28: =Z107*AI126 -> -313301.18 | Y28: 0.01 | AA28: N2, vol % | AB28: 0.6748 | AC28: =AB28/100*$AC$34 -> 2594.6547 | AD28: -18.616532 | AE28: =AC28*AD28 -> -48303.473 | AF28: -5.8595386 | AG28: =AC28*AF28 -> -15203.479 | AK28: -10.452252 | AL28: =AK28*AV28 -> -26779.141 | AO28: N2, vol % | AP28: =AQ28/$AQ$34*100 -> 0.76026969 | AQ28: =AC28 -> 2594.6547 | AT28: N2, vol % | AU28: =AV28/$AV$34*100 -> 0.88122118 | AV28: =AQ28-AT7 -> 2562.0452 | AX28: N2, vol % | AY28: 0.01 | AZ28: =AY28/100*$AZ$34 -> 20.183066
C29: CO, vol % | D29: 0 | E29: =($A$34)*($D$34*D29/100*1000)/($E$24*$B$34) -> 0 | G29: 10.524394 | H29: =G29*L29 -> 290733.74 | J29: CO, vol % | K29: =L29/$L$34*100 -> 21.856242 | L29: =E29+AI60 -> 27624.749 | O29: 4.0133733 | P29: =T29*O29 -> 110868.43 | R29: CO, vol % | S29: =T29/$T$34*100 -> 10.100303 | T29: =L29 -> 27624.749 | U29: 19.303674 | V29: =T29*U29 -> 533259.15 | W29: VII | X29: not relevant | Y29: max | AA29: CO, vol % | AB29: 19.0153 | AC29: =AB29/100*$AC$34 -> 73115.2 | AD29: -19.303674 | AE29: =AC29*AD29 -> -1411392 | AF29: -6.2944433 | AG29: =AC29*AF29 -> -460219.48 | AH29: 0.519 | AI29: CO-conversion | AK29: -12.051072 | AL29: =AK29*AV29 -> -415704.72 | AO29: CO, vol % | AP29: =AQ29/$AQ$34*100 -> 10.304831 | AQ29: =AC29*(1-AH29) -> 35168.411 | AT29: CO, vol % | AU29: =AV29/$AV$34*100 -> 11.864718 | AV29: =AQ29-AT8 -> 34495.248 | AX29: CO, vol % | AY29: 0 | AZ29: =AY29/100*$AZ$34 -> 0
C30: CO2, vol % | D30: 0.5 | E30: =($A$34)*($D$34*D30/100*1000)/($E$24*$B$34) -> 275.96714 | G30: 16.648488 | H30: =G30*L30 -> 63275.544 | J30: CO2, vol % | K30: =L30/$L$34*100 -> 3.0070332 | L30: =E30+AI61 -> 3800.6781 | O30: 6.580752 | P30: =T30*O30 -> 25011.32 | R30: CO2, vol % | S30: =T30/$T$34*100 -> 1.3896234 | T30: =L30 -> 3800.6781 | U30: 32.044939 | V30: =T30*U30 -> 121792.5 | W30: VIII | X30: =Z109*AI135 -> 730269.61 | Y30: 0.05 | Z30: CH4 Umsatz | AA30: CO2, vol % | AB30: 3.5893 | AC30: =AB30/100*$AC$34 -> 13801.117 | AD30: -32.044939 | AE30: =AC30*AD30 -> -442255.97 | AF30: -10.280325 | AG30: =AC30*AF30 -> -141879.97 | AK30: -19.143103 | AL30: =AK30*AV30 -> -84255.209 | AO30: CO2, vol % | AP30: =AQ30/$AQ$34*100 -> 15.162852 | AQ30: =AC30+(AC29*AH29) -> 51747.906 | AS30: [Ullmann's, Gas Production, 3. Gas Treating, 504] | AT30: CO2, vol % | AU30: 1.5 | AV30: =SUM(AQ27:AQ29,AQ31:AQ32)/(1-(AU30/100))*(AU30/100) -> 4401.335 | AX30: CO2, vol % | AY30: 0 | AZ30: =AY30/100*$AZ$34 -> 0
B31: 74 | C31: CH4, vol % | D31: 95 | E31: =($A$34)*($D$34*D31/100*1000)/($E$24*$B$34) -> 52433.757 | G31: 14.130909 | H31: =G31*L31 -> 776930.81 | J31: CH4, vol % | K31: =L31/$L$34*100 -> 43.500013 | L31: =E31+AI62 -> 54980.95 | O31: 7.3660903 | P31: =T31*O31 -> 404994.64 | R31: CH4, vol % | S31: =T31/$T$34*100 -> 20.102417 | T31: =L31 -> 54980.95 | U31: 42.380994 | V31: =T31*U31 -> 2330147.3 | Y31: 1100°C | Z31: 0.948 | AA31: CH4, vol % | AB31: 0.8706 | AC31: =AB31/100*$AC$34 -> 3347.5198 | AD31: -42.380994 | AE31: =AC31*AD31 -> -141871.22 | AF31: -11.183194 | AG31: =AC31*AF31 -> -37435.963 | AK31: -16.844385 | AL31: =AK31*AV31 -> -53576.944 | AO31: CH4, vol % | AP31: =AQ31/$AQ$34*100 -> 0.98086958 | AQ31: =AC31 -> 3347.5198 | AT31: CH4, vol % | AU31: =AV31/$AV$34*100 -> 1.0940091 | AV31: =AQ31-AT10 -> 3180.7005 | AX31: CH4, vol % | AY31: 0 | AZ31: =AY31/100*$AZ$34 -> 0
C32: C2+, vol % | D32: 3.5 | E32: =($A$34)*($D$34*D32/100*1000)/($E$24*$B$34) -> 1931.77 | G32: 14.130909 | H32: =G32*L32 -> 27297.666 | J32: C2+, vol % | K32: =L32/$L$34*100 -> 1.5283843 | L32: =E32+AI63 -> 1931.77 | O32: 7.3660903 | P32: =T32*O32 -> 14229.592 | R32: C2+, vol % | S32: =T32/$T$34*100 -> 0.70630366 | T32: =L32 -> 1931.77 | U32: 42.380994 | V32: =T32*U32 -> 81870.333 | Y32: 0 | AA32: C2+, vol % | AB32: 0 | AC32: =AB32/100*$AC$34 -> 0 | AD32: -42.380994 | AE32: =AC32*AD32 -> 0 | AF32: -11.183194 | AG32: =AC32*AF32 -> 0 | AK32: -16.844385 | AL32: =AK32*AV32 -> 0 | AO32: C2+, vol % | AP32: =AQ32/$AQ$34*100 -> 0 | AQ32: =AC32 -> 0 | AT32: C2+, vol % | AU32: =AV32/$AV$34*100 -> 0 | AV32: =AQ32-AT11 -> 0 | AX32: C2+, vol % | AY32: 0 | AZ32: =AY32/100*$AZ$34 -> 0
A33: p_0 | B33: T_0 | C33: H2O, vol % | D33: 0 | E33: =($A$34)*($D$34*D33/100*1000)/($E$24*$B$34) -> 0 | G33: 12.671218 | H33: =G33*L33 -> 0 | J33: H2O, vol % | K33: =L33/$L$34*100 -> 0 | L33: =E33+AI64 -> 0 | O33: 4.8794395 | P33: =T33*O33 -> 717820.33 | R33: H2O, vol % | S33: =T33/$T$34*100 -> 53.787561 | T33: =(T31+2*T32)*M21 -> 147111.23 | U33: 24.432108 | V33: =T33*U33 -> 3594237.3 | Z33: mol_out/mol_in | AA33: H2O, vol % | AB33: 21.2275 | AC33: =AB33/100*$AC$34 -> 81621.269 | AD33: -24.432108 | AE33: =AC33*AD33 -> -1994179.6 | AF33: -7.6334962 | AG33: =AC33*AF33 -> -623055.65 | AK33: -14.521697 | AL33: =AK33*AV33 -> 0 | AO33: H2O, vol % | AP33: 0.15 | AQ33: =SUM(AQ27:AQ32)/(1-(AP33/100))*(AP33/100) -> 511.92124 | AT33: H2O, vol % | AU33: =AV33/$AV$34*100 -> 0 | AV33: =AQ33-AT12 -> 0 | AX33: H2O, vol % | AY33: 0 | AZ33: =AY33/100*$AZ$34 -> 0
A34: 1 | B34: 298 | C34: Quantity, m3 (STP/h) | D34: 1367.4569 | E34: =($A$34)*($D$34*1000)/($E$24*$B$34) -> 55193.428 | J34: Quantity, m3 (STP/h) | K34: =L34*$E$24*$B$34/$A$34/1000 -> 3131.4764 | L34: =E34+AI65 -> 126392.95 | R34: Quantity, m3 (STP/h) | S34: =T34*$E$24*$B$34/$A$34/1000 -> 6776.2629 | T34: =SUM(T27:T33) -> 273504.18 | U34: {=SUMPRODUCT(S27:S33/100,_xlfn.ANCHORARRAY(U27))} -> 26.852632 | Z34: 1.405855 | AA34: Quantity, m3 (STP/h) | AB34: =AC34*$E$24*$B$34/$A$34/1000 -> 9526.4431 | AC34: =T34*Z34 -> 384507.21 | AD34: {=SUMPRODUCT(AB27:AB33/100,_xlfn.ANCHORARRAY(AD27))} -> -20.275682 | AF34: SUM | AK34: SUM | AL34: =SUM(AL27:AL33) -> -3759263.2 | AO34: Quantity, m3 (STP/h) | AP34: =AQ34*$E$24*$B$34/$A$34/1000 -> 8455.4782 | AQ34: =SUM(AQ27:AQ33) -> 341280.83 | AT34: Quantity, m3 (STP/h) | AU34: =AV34*$E$24*$B$34/$A$34/1000 -> 7203.2443 | AV34: =SUM(AV27:AV33) -> 290738.04 | AX34: Quantity, m3 (STP/h) | AY34: 5000.5 | AZ34: =($A$34)*($AY$34*1000)/($E$24*$B$34) -> 201830.66
C35: Temperature, °C | D35: 20 | J35: Temperature, °C | K35: 390 | R35: Temperature, °C | S35: 520 | X35: =T31*X36 -> 15394666 | AA35: Temperature, °C | AB35: 1100 | AF35: {=SUMPRODUCT(AB27:AB33/100,_xlfn.ANCHORARRAY(AF27))} -> -6.7129394 | AO35: Temperature, °C | AP35: 20 | AT35: Temperature, °C | AU35: 20 | AX35: Temperature, °C | AY35: 20
C36: Pressure, MPa | D36: 5.4 | J36: Pressure, MPa | K36: 5.3 | R36: Pressure, MPa | S36: 5.3 | U36: =U34*T34 -> 7344307 | X36: 280 | AA36: Pressure, MPa | AB36: 5.1 | AF36: =AF35*AC34 -> -2581173.6 | AO36: Pressure, MPa | AP36: 5 | AT36: Pressure, MPa | AU36: 5 | AX36: Pressure, MPa | AY36: 4.9
H37: =SUM(H27:H33) -> 1586380.2 | J37: SUM | P37: =SUM(P27:P33) -> 1421407.4 | R37: SUM | V37: =SUM(V27:V33) -> 7344307 | X37: =SUM(X27:X28,X30) -> 12082829 | Y37: =SUM(P37,V37,X37)/(1-(Y32))*Y32 -> 0 | AE37: =SUM(AE27:AE33) -> -7796145.8 | AG37: =SUM(AG27:AG33) -> -2581173.6
E38: =E30+E31+2*E32 -> 56573.264 | H38: 1311383.6
D39: =AV23-BA27 -> -3.8743044e-05 | E39: =SUM(AY61:AY63)/E38 -> 0.14813779 | K39: If too high CO CO2 contents for desulphurization, recycle adding after desulphurization | U39: Overall
D40: =(E31-AY63)*4+E32*7-AY61-(AZ27+AT6+AY59) -> 1409.6937 | U40: heat-adding | V40: heat-consuming
AG41: Temperature increase check | AT41: Purge gas recycle | AU41: Mole, mol | AW41: Parameter | AX41: Purge gas recycle | AY41: Mole, mol
E42: =E30+E31+E32*2 -> 56573.264 | S42: Electricity input | U42: =-AA45 -> -12082829 | Y42: =SUM(U42:U43,V47,V55) -> -12082829 | AH42: Reaction | AI42: Molar heat capacity, kJ/mol | AJ42: Heat-up energy, kJ/h | AT42: 49.813924 | AU42: =AT42/100*$AU$49 -> 44288.283 | AW42: H2, vol % | AX42: =AY42/$AY$49*100 -> 49.813901 | AY42: =AV27-AZ27 -> 44288.234
E43: =SUM(AT9,AT8,AY61,AY62,AY63) -> 56400.373 | S43: Reforming steam input | U43: 0 | AG43: Mole CH4, mol | AH43: =AQ29-AC29 -> -37946.789 | AI43: {=N139:N145} -> 3.8003366 | AJ43: =AI43*AQ27 -> 942143.01 | AT43: 2.8589989 | AU43: =AT43/100*$AU$49 -> 2541.8626 | AW43: N2, vol % | AX43: =AY43/$AY$49*100 -> 2.8590002 | AY43: =AV28-AZ28 -> 2541.8621
S44: HXF2- | V44: =P37 -> 1421407.4 | Z44: Electricity | AG44: Reaction enthalpy, kJ/mol | AH44: =AI141 -> -37.773932 | AI44: 3.5192102 | AJ44: =AI44*AQ28 -> 9131.1352 | AT44: 38.799065 | AU44: =AT44/100*$AU$49 -> 34495.255 | AW44: CO, vol % | AX44: =AY44/$AY$49*100 -> 38.799083 | AY44: =AV29-AZ29 -> 34495.248
P45: HXF1 | Q45: =U52+V53+V54 -> 0 | S45: SMR feed warming (HXI-) | V45: =V37 -> 7344307 | Z45: Energy input, kJ/h | AA45: =X37+Y37 -> 12082829 | AG45: Energy. kJ/h | AH45: =-AH43*AH44 -> -1433399.4 | AI45: 3.8077485 | AJ45: =AI45*AQ29 -> 133912.46 | AT45: 4.9504699 | AU45: =AT45/100*$AU$49 -> 4401.3359 | AW45: CO2, vol % | AX45: =AY45/$AY$49*100 -> 4.9504721 | AY45: =AV30-AZ30 -> 4401.335
S46: Reaction enthalpy | V46: =X37 -> 12082829 | AI46: 6.1941876 | AJ46: =AI46*AQ30 -> 320536.24 | AT46: 3.5775423 | AU46: =AT46/100*$AU$49 -> 3180.7012 | AW46: CH4, vol % | AX46: =AY46/$AY$49*100 -> 3.5775439 | AY46: =AV31-AZ31 -> 3180.7005
P47: HXF2 | Q47: =V44+U50+V51 -> 0 | S47: Insulation losses | V47: =Y37 -> 0 | AI47: 6.5305792 | AJ47: =AI47*AQ31 -> 21861.243 | AT47: 0 | AU47: =AT47/100*$AU$49 -> 0 | AW47: C2+, vol % | AX47: =AY47/$AY$49*100 -> 0 | AY47: =AV32-AZ32 -> 0
P48: HXI | Q48: =V45+U48+V49 -> 0 | S48: HXI+ | U48: =AE37 -> -7796145.8 | AI48: 6.5305792 | AJ48: =AI48*AQ32 -> 0 | AT48: 0 | AU48: =AT48/100*$AU$49 -> 0 | AW48: H2O, vol % | AX48: =AY48/$AY$49*100 -> 0 | AY48: =AV33-AZ33 -> 0
S49: HXI difference (for steam production) | V49: =-U48-V45 -> 451838.86 | AI49: 4.604536 | AJ49: =AI49*AQ33 -> 2357.1598 | AT49: 2202.7458 | AU49: =$A$34*AT49*1000/(E24*B34) -> 88907.437 | AW49: Quantity, m3 (STP/h) | AX49: =AU34-AY34-AK68 -> 2202.7443 | AY49: =AV34-AZ34 -> 88907.379
S50: HXF2+ | U50: =AG37 -> -2581173.6 | AH50: =AH45+AJ50 -> -3458.1626 | AI50: SUM | AJ50: =SUM(AJ43:AJ49) -> 1429941.3 | AW50: Temperature, °C | AX50: =AU35 -> 20
S51: HXF2 difference (for steam production) | V51: =-U50-V44 -> 1159766.2 | AW51: Pressure, MPa | AX51: 0.1
S52: HXF1+ | U52: =AL34 -> -3759263.2
S53: HXF1- | V53: =H37 -> 1586380.2
S54: HXF1- difference (for steam production) | V54: =-U52-V53 -> 2172883.1 | AH54: R/F
S55: Losses | V55: 0 | X55: =X56/U56 -> 0 | AH55: 1.29
S56: SUM | U56: =SUM(U42:U54) -> -26219412 | V56: =SUM(V42:V54) -> 26219412 | W56: Delta | X56: =SUM(U56:V56) -> 0
AG57: Parameter | AH57: Recycle gas | AI57: Mole, mol
AG58: H2, vol % | AH58: =AT42 -> 49.813924 | AI58: =AH58/100*$AI$65 -> 35467.276 | AW58: Parameter | AX58: Purge gas burn | AY58: Mole, mol | AZ58: Mass CO2, kg/h | BB58: LHV 25°C, kJ/mol | BC58: Combustion energy, kJ/h
S59: C | T59: =T29+T30+T31+T32*2 -> 90269.917 | AB59: C | AC59: =AC29+AC30+AC31+AC32 -> 90263.838 | AG59: N2, vol % | AH59: =AT43 -> 2.8589989 | AI59: =AH59/100*$AI$65 -> 2035.5936 | AW59: H2, vol % | AX59: =AT42 -> 49.813924 | AY59: =AU42-AI58 -> 8821.007 | BB59: 244 | BC59: =BB59*AY59*-1 -> -2152325.7
S60: H | T60: =T27*2+T31*4+T32*6+T33*2 -> 596671.42 | AB60: H | AC60: =AC27*2+AC31*4+AC33*2 -> 596559.87 | AG60: CO, vol % | AH60: =AT44 -> 38.799065 | AI60: =AH60/100*$AI$65 -> 27624.749 | AR60: GGW bei WGS liegt wieder weit bei CH4 und H2O, zur modellierung ist die betrachtung der Kinetik von relevanz (Kat für WGSR aber nicht für SMR) | AW60: N2, vol % | AX60: =AT43 -> 2.8589989 | AY60: =AU43-AI59 -> 506.26908 | BA60: =E28-AT7-AZ28-AY60 -> -7.1273431
S61: O | T61: =T29+T30*2+T33 -> 182337.33 | AB61: O | AC61: =AC29+AC30*2+AC33 -> 182338.7 | AG61: CO2, vol % | AH61: =AT45 -> 4.9504699 | AI61: =AH61/100*$AI$65 -> 3524.7109 | AR61: Daher wird annahme gemacht und eine 50% konversion von CO angenommen | AW61: CO, vol % | AX61: =AT44 -> 38.799065 | AY61: =AU44-AI60 -> 6870.5053 | AZ61: =AY61*44/1000 -> 302.30223 | BB61: 283.24 | BC61: =BB61*AY61*-1 -> -1946001.9
AG62: CH4, vol % | AH62: =AT46 -> 3.5775423 | AI62: =AH62/100*$AI$65 -> 2547.193 | AR62: N2-Inertgas, H2 purity is directly dependant of N2 content in NG | AW62: CO2, vol % | AX62: =AT45 -> 4.9504699 | AY62: =AU45-AI61 -> 876.62497 | AZ62: =AY62*44/1000 -> 38.571499
AG63: C2+, vol % | AH63: =AT47 -> 0 | AI63: =AH63/100*$AI$65 -> 0 | AR63: CO-Nutzung through recycle | AW63: CH4, vol % | AX63: =AT46 -> 3.5775423 | AY63: =AU46-AI62 -> 633.50813 | AZ63: =AY63*44/1000 -> 27.874358 | BB63: 802.34 | BC63: =BB63*AY63*-1 -> -508288.91
AG64: H2O, vol % | AH64: =AT48 -> 0 | AI64: =AH64/100*$AI$65 -> 0 | AR64: Höheres Druckniveau angenommen wegen Rectisol, aber dafür notwendige verdichtung vernachlässigt | AW64: C2+, vol % | AX64: =AT47 -> 0 | AY64: =AU47-AI63 -> 0 | BB64: 1437.2 | BC64: 0
AG65: Quantity, m3 (STP/h) | AH65: =D34*AH55 -> 1764.0194 | AI65: =($A$34)*($AH$65*1000)/($E$24*$B$34) -> 71199.523 | AR65: Durch Recycle und darin included hydrogen no H2-product recycle to desulphurization is necessary | AW65: H2O, vol % | AX65: =AT48 -> 0 | AY65: =AU48-AI64 -> 0
AG66: Temperature, °C | AR66: Simplification, that CO2 removal doesn't need energy | AW66: Quantity, m3 (STP/h) | AX66: =AY66*$E$24*$B$34/$A$34/1000 -> 438.72633 | AY66: =AU49-AI65 -> 17707.914
AG67: Pressure, MPa | AH67: =AE52 -> 0 | AW67: Temperature, °C | AX67: =AU35 -> 20
AW68: Pressure, MPa | AX68: 0.1 | BD68: Boiler efficiency
AW69: SUM | BC69: =SUM(BC59:BC65) -> -4606616.5 | BD69: 0.95 | BE69: =BC69*BD69 -> -4376285.7 | BF69: =S15-V49-V51-V54+BE69 -> 633.31857
BD70: https://www.sciencedirect.com/topics/engineering/boiler-efficiency
F87: Molar heat capacity (temperature dependant), integral | P87: Reaction rate determination
F88: 1 bar, ideal gas | S88: H2 | T88: CO | U88: CO2 | V88: CH4 | W88: C2H6 | X88: H2O | Y88: C | AA88: Comment
G89: A | H89: B | I89: C | J89: D | K89: E | L89: T_1 | M89: T_0 | N89: deltah_Tj, kJ/mol | P89: I | R89: xi_1 | S89: 3 | T89: 1 | V89: -1 | X89: -1
F90: Feed (20->390°C) | P90: II | R90: xi_2 | S90: 1 | T90: -1 | U90: 1 | X90: -1 | Z90: linear dependant equation | AA90: Not possible to choose equation II, as in that case deltaN_C is said to be zero, which leads to a huge error in H balance, as the H balance will be a degree of freedom in that case.
F91: H2 | G91: 33.066178 | H91: -11.363417 | I91: 11.432816 | J91: -2.772874 | K91: -0.158558 | L91: =$K$35+273 -> 663 | M91: =$D$35+273 -> 293 | N91: =(G91*(L91-M91)+H91/2000*(L91^2-M91^2)+I91/(3*10^6)*(L91^3-M91^3)+J91/(4*10^9)*(L91^4-M91^4)-(10^6*K91)*(1/M91-1/L91))/1000 -> 11.412697 | P91: III | S91: 4 | U91: 1 | V91: -1 | X91: -2 | Z91: linear dependant equation
F92: N2 | G92: 19.50583 | H92: 19.88705 | I92: -8.598535 | J92: 1.369784 | K92: 0.527601 | L92: =$K$35+273 -> 663 | M92: =$D$35+273 -> 293 | N92: =(G92*(L92-M92)+H92/2000*(L92^2-M92^2)+I92/(3*10^6)*(L92^3-M92^3)+J92/(4*10^9)*(L92^4-M92^4)-(10^6*K92)*(1/M92-1/L92))/1000 -> 9.0299095 | P92: IV | S92: 2 | T92: 2 | U92: -1 | V92: -1
F93: CO | G93: 25.56759 | H93: 6.09613 | I93: 4.054656 | J93: -2.671301 | K93: 0.131021 | L93: =$K$35+273 -> 663 | M93: =$D$35+273 -> 293 | N93: =(G93*(L93-M93)+H93/2000*(L93^2-M93^2)+I93/(3*10^6)*(L93^3-M93^3)+J93/(4*10^9)*(L93^4-M93^4)-(10^6*K93)*(1/M93-1/L93))/1000 -> 10.524394 | P93: V | Q93: soot-forming | S93: -1 | T93: -1 | X93: 1 | Y93: 1 | Z93: linear dependant equation
F94: CO2 | G94: 24.99735 | H94: 55.18696 | I94: -33.69137 | J94: 7.948387 | K94: -0.136638 | L94: =$K$35+273 -> 663 | M94: =$D$35+273 -> 293 | N94: =(G94*(L94-M94)+H94/2000*(L94^2-M94^2)+I94/(3*10^6)*(L94^3-M94^3)+J94/(4*10^9)*(L94^4-M94^4)-(10^6*K94)*(1/M94-1/L94))/1000 -> 16.648488 | P94: VI | Q94: soot-forming | T94: -2 | U94: 1 | Y94: 1 | Z94: linear dependant equation
F95: CH4 | G95: -0.703029 | H95: 108.4773 | I95: -42.52157 | J95: 5.862788 | K95: 0.678565 | L95: =$K$35+273 -> 663 | M95: =$D$35+273 -> 293 | N95: =(G95*(L95-M95)+H95/2000*(L95^2-M95^2)+I95/(3*10^6)*(L95^3-M95^3)+J95/(4*10^9)*(L95^4-M95^4)-(10^6*K95)*(1/M95-1/L95))/1000 -> 14.130909 | P95: VII | Q95: soot-forming | R95: xi_3 | S95: 2 | V95: -1 | Y95: 1
F96: C2+ | L96: =$K$35+273 -> 663 | M96: =$D$35+273 -> 293 | N96: =N95 -> 14.130909 | O96: approximation with CH4 values | P96: VIII | R96: xi_4 | S96: 5 | T96: 2 | W96: -1 | X96: -2
F97: H2O | G97: 30.092 | H97: 6.832514 | I97: 6.793435 | J97: -2.53448 | K97: 0.082139 | L97: =$K$35+273 -> 663 | M97: =$D$35+273 -> 293 | N97: =(G97*(L97-M97)+H97/2000*(L97^2-M97^2)+I97/(3*10^6)*(L97^3-M97^3)+J97/(4*10^9)*(L97^4-M97^4)-(10^6*K97)*(1/M97-1/L97))/1000 -> 12.671218
F98: Feed (390->520°C) | P98: II* | Q98: I-II | S98: =S89-S90 -> 2 | T98: =T89-T90 -> 2 | U98: =U89-U90 -> -1 | V98: =V89-V90 -> -1 | W98: =W89-W90 -> 0 | X98: =X89-X90 -> 0 | Y98: =Y89-Y90 -> 0
F99: H2 | G99: 33.066178 | H99: -11.363417 | I99: 11.432816 | J99: -2.772874 | K99: -0.158558 | L99: =$S$35+273 -> 793 | M99: =$K$35+273 -> 663 | N99: =(G99*(L99-M99)+H99/2000*(L99^2-M99^2)+I99/(3*10^6)*(L99^3-M99^3)+J99/(4*10^9)*(L99^4-M99^4)-(10^6*K99)*(1/M99-1/L99))/1000 -> 3.9119754 | P99: III* | Q99: 2I-III | S99: =2*S89-S91 -> 2 | T99: =2*T89-T91 -> 2 | U99: =2*U89-U91 -> -1 | V99: =2*V89-V91 -> -1 | W99: =2*W89-W91 -> 0 | X99: =2*X89-X91 -> 0 | Y99: =2*Y89-Y91 -> 0
F100: N2 | G100: 19.50583 | H100: 19.88705 | I100: -8.598535 | J100: 1.369784 | K100: 0.527601 | L100: =$S$35+273 -> 793 | M100: =$K$35+273 -> 663 | N100: =(G100*(L100-M100)+H100/2000*(L100^2-M100^2)+I100/(3*10^6)*(L100^3-M100^3)+J100/(4*10^9)*(L100^4-M100^4)-(10^6*K100)*(1/M100-1/L100))/1000 -> 3.7626703 | P100: V* | Q100: I+V | S100: =S89+S93 -> 2 | T100: =T89+T93 -> 0 | U100: =U89+U93 -> 0 | V100: =V89+V93 -> -1 | W100: =W89+W93 -> 0 | X100: =X89+X93 -> 0 | Y100: =Y89+Y93 -> 1
F101: CO | G101: 25.56759 | H101: 6.09613 | I101: 4.054656 | J101: -2.671301 | K101: 0.131021 | L101: =$S$35+273 -> 793 | M101: =$K$35+273 -> 663 | N101: =(G101*(L101-M101)+H101/2000*(L101^2-M101^2)+I101/(3*10^6)*(L101^3-M101^3)+J101/(4*10^9)*(L101^4-M101^4)-(10^6*K101)*(1/M101-1/L101))/1000 -> 4.0133733 | P101: VI* | Q101: VI-II | S101: =S94-S90 -> -1 | T101: =T94-T90 -> -1 | U101: =U94-U90 -> 0 | V101: =V94-V90 -> 0 | W101: =W94-W90 -> 0 | X101: =X94-X90 -> 1 | Y101: =Y94-Y90 -> 1
F102: CO2 | G102: 24.99735 | H102: 55.18696 | I102: -33.69137 | J102: 7.948387 | K102: -0.136638 | L102: =$S$35+273 -> 793 | M102: =$K$35+273 -> 663 | N102: =(G102*(L102-M102)+H102/2000*(L102^2-M102^2)+I102/(3*10^6)*(L102^3-M102^3)+J102/(4*10^9)*(L102^4-M102^4)-(10^6*K102)*(1/M102-1/L102))/1000 -> 6.580752
F103: CH4 | G103: -0.703029 | H103: 108.4773 | I103: -42.52157 | J103: 5.862788 | K103: 0.678565 | L103: =$S$35+273 -> 793 | M103: =$K$35+273 -> 663 | N103: =(G103*(L103-M103)+H103/2000*(L103^2-M103^2)+I103/(3*10^6)*(L103^3-M103^3)+J103/(4*10^9)*(L103^4-M103^4)-(10^6*K103)*(1/M103-1/L103))/1000 -> 7.3660903 | AB103: Double-check
F104: C2+ | L104: =$S$35+273 -> 793 | M104: =$K$35+273 -> 663 | N104: =N103 -> 7.3660903 | S104: xi_1 | T104: xi_2 | U104: xi_3 | V104: xi_4 | AB104: balance | AC104: calculated | AD104: error
F105: H2O (xxx->520°C) | G105: 30.092 | H105: 6.832514 | I105: 6.793435 | J105: -2.53448 | K105: 0.082139 | L105: =$S$35+273 -> 793 | M105: =$P$17+273 -> 663 | N105: =(G105*(L105-M105)+H105/2000*(L105^2-M105^2)+I105/(3*10^6)*(L105^3-M105^3)+J105/(4*10^9)*(L105^4-M105^4)-(10^6*K105)*(1/M105-1/L105))/1000 -> 4.8794395 | R105: deltaN_H2 | S105: =S89 -> 3 | T105: =S90 -> 1 | U105: =S95 -> 2 | V105: =S96 -> 5 | AB105: =AB27/100*AC34-S27/100*T34 -> 174496.35 | AC105: =S105*Z$108+T105*Z$107+U105*Z$111+V105*Z$109 -> 174559.58 | AD105: =(AC105-AB105)/AB105 -> 0.00036236493
F106: Feed (520->1100°C) | R106: deltaN_CO | S106: =T89 -> 1 | T106: =T90 -> -1 | V106: =T96 -> 2 | AB106: =AB29/100*AC34-S29/100*T34 -> 45490.451 | AC106: =S106*Z$108+T106*Z$107+U106*Z$111+V106*Z$109 -> 45496.531 | AD106: =(AC106-AB106)/AB106 -> 0.00013365408
F107: H2 | G107: 33.066178 | H107: -11.363417 | I107: 11.432816 | J107: -2.772874 | K107: -0.158558 | L107: =$AB$35+273 -> 1373 | M107: =$S$35+273 -> 793 | N107: =(G107*(L107-M107)+H107/2000*(L107^2-M107^2)+I107/(3*10^6)*(L107^3-M107^3)+J107/(4*10^9)*(L107^4-M107^4)-(10^6*K107)*(1/M107-1/L107))/1000 -> 17.899022 | R107: deltaN_CO2 | T107: =U90 -> 1 | W107: =AB30/100*AC34-S30/100*T34 -> 10000.439 | X107: -> | Y107: xi_2 = | Z107: =W107*T107 -> 10000.439 | AA107: mol
F108: N2 | G108: 19.50583 | H108: 19.88705 | I108: -8.598535 | J108: 1.369784 | K108: 0.527601 | L108: =$AB$35+273 -> 1373 | M108: =$S$35+273 -> 793 | N108: =(G108*(L108-M108)+H108/2000*(L108^2-M108^2)+I108/(3*10^6)*(L108^3-M108^3)+J108/(4*10^9)*(L108^4-M108^4)-(10^6*K108)*(1/M108-1/L108))/1000 -> 18.616532 | R108: deltaN_CH4 | S108: =V89 -> -1 | U108: =V95 -> -1 | W108: =AB31/100*AC34-S31/100*T34 -> -51633.43 | X108: -> | Y108: xi_1 = | Z108: =(W108-(U108*Z111))/S108 -> 51633.43 | AA108: mol
F109: CO | G109: 25.56759 | H109: 6.09613 | I109: 4.054656 | J109: -2.671301 | K109: 0.131021 | L109: =$AB$35+273 -> 1373 | M109: =$S$35+273 -> 793 | N109: =(G109*(L109-M109)+H109/2000*(L109^2-M109^2)+I109/(3*10^6)*(L109^3-M109^3)+J109/(4*10^9)*(L109^4-M109^4)-(10^6*K109)*(1/M109-1/L109))/1000 -> 19.303674 | R109: deltaN_C2H6 | V109: =W96 -> -1 | W109: =AB32/100*AC34-S32/100*T34 -> -1931.77 | X109: -> | Y109: xi_4 = | Z109: =W109*V109 -> 1931.77 | AA109: mol
F110: CO2 | G110: 24.99735 | H110: 55.18696 | I110: -33.69137 | J110: 7.948387 | K110: -0.136638 | L110: =$AB$35+273 -> 1373 | M110: =$S$35+273 -> 793 | N110: =(G110*(L110-M110)+H110/2000*(L110^2-M110^2)+I110/(3*10^6)*(L110^3-M110^3)+J110/(4*10^9)*(L110^4-M110^4)-(10^6*K110)*(1/M110-1/L110))/1000 -> 32.044939 | R110: deltaN_H2O | S110: =X89 -> -1 | T110: =X90 -> -1 | V110: -2 | AB110: =AB33/100*AC34-S33/100*T34 -> -65489.956 | AC110: =S110*Z$108+T110*Z$107+U110*Z$111+V110*Z$109 -> -65497.41 | AD110: =(AC110-AB110)/AB110 -> 0.00011380792
F111: CH4 | G111: -0.703029 | H111: 108.4773 | I111: -42.52157 | J111: 5.862788 | K111: 0.678565 | L111: =$AB$35+273 -> 1373 | M111: =$S$35+273 -> 793 | N111: =(G111*(L111-M111)+H111/2000*(L111^2-M111^2)+I111/(3*10^6)*(L111^3-M111^3)+J111/(4*10^9)*(L111^4-M111^4)-(10^6*K111)*(1/M111-1/L111))/1000 -> 42.380994 | R111: deltaN_C | U111: =Y95 -> 1 | W111: 0 | X111: -> | Y111: xi_3 = | Z111: 0 | AA111: mol | AB111: 0 | AC111: =S111*Z$110+T111*Z$107+U111*Z$105+V111*Z$109 -> 0
F112: C2+ | L112: =$AB$35+273 -> 1373 | M112: =$S$35+273 -> 793 | N112: =N111 -> 42.380994
F113: H2O | G113: 30.092 | H113: 6.832514 | I113: 6.793435 | J113: -2.53448 | K113: 0.082139 | L113: =$AB$35+273 -> 1373 | M113: =$S$35+273 -> 793 | N113: =(G113*(L113-M113)+H113/2000*(L113^2-M113^2)+I113/(3*10^6)*(L113^3-M113^3)+J113/(4*10^9)*(L113^4-M113^4)-(10^6*K113)*(1/M113-1/L113))/1000 -> 24.432108
F114: Feed (1100->520°C) | P114: Reaction enthalpy determination
F115: H2 | G115: 33.066178 | H115: -11.363417 | I115: 11.432816 | J115: -2.772874 | K115: -0.158558 | L115: =$AD$24+273 -> 793 | M115: =$AB$35+273 -> 1373 | N115: =(G115*(L115-M115)+H115/2000*(L115^2-M115^2)+I115/(3*10^6)*(L115^3-M115^3)+J115/(4*10^9)*(L115^4-M115^4)-(10^6*K115)*(1/M115-1/L115))/1000 -> -17.899022 | AH115: neglected because ideal gas
F116: N2 | G116: 19.50583 | H116: 19.88705 | I116: -8.598535 | J116: 1.369784 | K116: 0.527601 | L116: =$AD$24+273 -> 793 | M116: =$AB$35+273 -> 1373 | N116: =(G116*(L116-M116)+H116/2000*(L116^2-M116^2)+I116/(3*10^6)*(L116^3-M116^3)+J116/(4*10^9)*(L116^4-M116^4)-(10^6*K116)*(1/M116-1/L116))/1000 -> -18.616532 | Q116: species | R116: nu_j | S116: deltah_j_std, kJ/mol | T116: a1l | U116: a2l | V116: a3l | W116: a4l | X116: a5l | Y116: a1h | Z116: a2h | AA116: a3h | AB116: a4h | AC116: a5h | AD116: T_1 | AE116: T_mid | AF116: T_0 | AG116: deltah_Tj, kJ/mol | AH116: deltah_pj
F117: CO | G117: 25.56759 | H117: 6.09613 | I117: 4.054656 | J117: -2.671301 | K117: 0.131021 | L117: =$AD$24+273 -> 793 | M117: =$AB$35+273 -> 1373 | N117: =(G117*(L117-M117)+H117/2000*(L117^2-M117^2)+I117/(3*10^6)*(L117^3-M117^3)+J117/(4*10^9)*(L117^4-M117^4)-(10^6*K117)*(1/M117-1/L117))/1000 -> -19.303674 | P117: I | Q117: CH4 | R117: -1 | S117: -74.6 | T117: =INDEX(Sheet1!$E$5:$R$11,MATCH($Q117,Sheet1!$A$5:$A$11,0),MATCH(T$116,Sheet1!$E$4:$R$4,0)) -> 5.1498761 | U117: =INDEX(Sheet1!$E$5:$R$11,MATCH($Q117,Sheet1!$A$5:$A$11,0),MATCH(U$116,Sheet1!$E$4:$R$4,0)) -> -0.013670979 | V117: =INDEX(Sheet1!$E$5:$R$11,MATCH($Q117,Sheet1!$A$5:$A$11,0),MATCH(V$116,Sheet1!$E$4:$R$4,0)) -> 4.918006e-05 | W117: =INDEX(Sheet1!$E$5:$R$11,MATCH($Q117,Sheet1!$A$5:$A$11,0),MATCH(W$116,Sheet1!$E$4:$R$4,0)) -> -4.8474303e-08 | X117: =INDEX(Sheet1!$E$5:$R$11,MATCH($Q117,Sheet1!$A$5:$A$11,0),MATCH(X$116,Sheet1!$E$4:$R$4,0)) -> 1.6669396e-11 | Y117: =INDEX(Sheet1!$E$5:$R$11,MATCH($Q117,Sheet1!$A$5:$A$11,0),MATCH(Y$116,Sheet1!$E$4:$R$4,0)) -> 0.074851495 | Z117: =INDEX(Sheet1!$E$5:$R$11,MATCH($Q117,Sheet1!$A$5:$A$11,0),MATCH(Z$116,Sheet1!$E$4:$R$4,0)) -> 0.013390947 | AA117: =INDEX(Sheet1!$E$5:$R$11,MATCH($Q117,Sheet1!$A$5:$A$11,0),MATCH(AA$116,Sheet1!$E$4:$R$4,0)) -> -5.7328581e-06 | ... AC117: =INDEX(Sheet1!$E$5:$R$11,MATCH($Q117,Sheet1!$A$5:$A$11,0),MATCH(AC$116,Sheet1!$E$4:$R$4,0)) -> -1.0181523e-13 | AD117: =$AB$35+273 -> 1373 | AE117: 1000 | AF117: 298 | AG117: =Sheet1!$S$2*(T117*(AE117-AF117)+U117/2*(AE117^2-AF117^2)+V117/3*(AE117^3-AF117^3)+W117/4*(AE117^4-AF117^4)+X117/5*(AE117^5-AF117^5))/1000+Sheet1!$S$2*(Y117*(AD117-AE117)+Z117/2*(AD117^2-AE117^2)+AA117/3*(AD117^3-AE117^3)+AB117/4*(AD117^4-AE117^4)+AC117/5*(AD117^5-AE117^5))/1000 -> 68.758508 | AH117: -
...

Sheet Sheet1
S1: R
S2: 8.314
A3: Spezies | B3: Temperaturgrenzen | E3: Low-T Koeffizienten (T_min → T_mid) | L3: High-T Koeffizienten (T_mid → T_max)
B4: T_min [K] | C4: T_mid [K] | D4: T_max [K] | E4: a1l | F4: a2l | G4: a3l | H4: a4l | I4: a5l | J4: a6l | K4: a7l | L4: a1h | M4: a2h | N4: a3h | O4: a4h | P4: a5h | Q4: a6h | R4: a7h
A5: H2 | B5: 200 | C5: 1000 | D5: 3500 | E5: 2.3443311 | F5: 0.0079805207 | G5: -1.9478151e-05 | H5: 2.0157209e-08 | I5: -7.3761176e-12 | J5: -917.93517 | K5: 0.68301024 | L5: 3.3372792 | M5: -4.9402473e-05 | N5: 4.9945678e-07 | O5: -1.7956639e-10 | P5: 2.0025538e-14 | Q5: -950.15892 | R5: -3.2050233
A6: N2 | B6: 300 | C6: 1000 | D6: 5000 | E6: 3.298677 | F6: 0.0014082404 | G6: -3.963222e-06 | H6: 5.641515e-09 | I6: -2.444854e-12 | J6: -1020.8999 | K6: 3.950372 | L6: 2.92664 | M6: 0.0014879768 | N6: -5.68476e-07 | O6: 1.0097038e-10 | P6: -6.753351e-15 | Q6: -922.7977 | R6: 5.980528
A7: CO | B7: 200 | C7: 1000 | D7: 3500 | E7: 3.5795335 | F7: -0.00061035368 | G7: 1.0168143e-06 | H7: 9.0700588e-10 | I7: -9.044245e-13 | J7: -14344.086 | K7: 3.5084093 | L7: 2.7151856 | M7: 0.0020625274 | N7: -9.9882577e-07 | O7: 2.3005301e-10 | P7: -2.0364772e-14 | Q7: -14151.872 | R7: 7.8186877
A8: CO2 | B8: 200 | C8: 1000 | D8: 3500 | E8: 2.3567735 | F8: 0.0089845968 | G8: -7.1235627e-06 | H8: 2.4591902e-09 | I8: -1.4369955e-13 | J8: -48371.97 | K8: 9.9010522 | L8: 3.8574603 | M8: 0.0044143703 | N8: -2.214814e-06 | O8: 5.2349019e-10 | P8: -4.7208416e-14 | Q8: -48759.166 | R8: 2.2716381
A9: CH4 | B9: 200 | C9: 1000 | D9: 3500 | E9: 5.1498761 | F9: -0.013670979 | G9: 4.918006e-05 | H9: -4.8474303e-08 | I9: 1.6669396e-11 | J9: -10246.648 | K9: -4.6413038 | L9: 0.074851495 | M9: 0.013390947 | N9: -5.7328581e-06 | O9: 1.2229254e-09 | P9: -1.0181523e-13 | Q9: -9468.3446 | R9: 18.437318
A10: C2H6 | B10: 200 | C10: 1000 | D10: 3500 | E10: 4.2914249 | F10: -0.0055015427 | G10: 5.9943829e-05 | H10: -7.0846629e-08 | I10: 2.6868577e-11 | J10: -11522.206 | K10: 2.6668232 | L10: 1.0718815 | M10: 0.021685268 | N10: -1.0025607e-05 | O10: 2.21412e-09 | P10: -1.9000289e-13 | Q10: -11426.393 | R10: 15.115611
A11: H2O | B11: 200 | C11: 1000 | D11: 3500 | E11: 4.1986406 | F11: -0.0020364341 | G11: 6.5204021e-06 | H11: -5.4879706e-09 | I11: 1.7719782e-12 | J11: -30293.727 | K11: -0.84903221 | L11: 3.0339925 | M11: 0.002176918 | N11: -1.6407252e-07 | O11: -9.7041987e-11 | P11: 1.6820099e-14 | Q11: -30004.297 | R11: 4.9667701

Sheet SMR, WGSR, C-forming, C2H6
F1: Parameter | G1: Feed, 1 | H1: Before desulfurization, 2 | I1: Reformer inlet, 3 | J1: Reformer outlet, 4 | K1: Pressure swing adsorption, 5 | L1: H2 product, 6 | U1: Parameter | V1: Steam export | Z1: Parameter | AA1: Flue gas (feed) | AB1: Mole, mol | AC1: Mass CO2, kg/h
F2: H2, vol % | G2: 0 | H2: 4.8 | I2: 1.1 | J2: 51.9 | K2: 74.6 | L2: 99.99 | U2: Specific enthalpy increase relative to input water, kJ/kg | V2: =2871.7 -> 2871.7 | W2: https://www.peacesoftware.de/einigewerte/wasser_dampf.html | Z2: H2, vol % | AA2: =AB2/SUM($AB$2:$AB$8)*100 -> 0 | AB2: 0
F3: N2, vol % | G3: 1 | H3: 1 | I3: 0.3 | J3: 0.2 | K3: 0.25 | L3: 0.01 | U3: Mass flow, kg/h | V3: =W15-S15 -> 985.86697 | Z3: N2, vol % | AA3: =AB3/SUM($AB$2:$AB$8)*100 -> 61.814141 | AB3: =N67+AC43+AB70 -> 289810.03
F4: CO, vol % | G4: 0 | H4: 0 | I4: 0 | J4: 10.7 | K4: 5.3 | L4: 0 | U4: Temperature, °C | V4: 255 | Z4: CO, vol % | AA4: =AB4/SUM($AB$2:$AB$8)*100 -> 0 | AB4: 0
F5: CO2, vol % | G5: 0.5 | H5: 0.5 | I5: 0.1 | J5: 5.1 | K5: 14.8 | L5: 0 | U5: Pressure, MPa | V5: 3 | Z5: CO2, vol % | AA5: =AB5/SUM($AB$2:$AB$8)*100 -> 19.276245 | AB5: =N69+N70+2*N71+AC44+AC45+AC46 -> 90374.939 | AC5: =AB5*44/1000 -> 3976.4973
F6: CH4, vol % | G6: 95 | H6: 90.4 | I6: 26.1 | J6: 3.8 | K6: 4.9 | L6: 0 | Z6: CH4, vol % | AA6: =AB6/SUM($AB$2:$AB$8)*100 -> 0 | AB6: 0
F7: C2+, vol % | G7: 3.5 | H7: 3.3 | I7: 1 | J7: 0 | K7: 0 | L7: 0 | Z7: C2+, vol % | AA7: =AB7/SUM($AB$2:$AB$8)*100 -> 0 | AB7: 0
F8: H2O, vol % | G8: 0 | H8: 0 | I8: 71.4 | J8: 28.3 | K8: 0.15 | L8: 0 | Z8: H2O, vol % | AA8: =AB8/SUM($AB$2:$AB$8)*100 -> 18.909614 | AB8: =N70*2+N71*3+AC42+AC46*2+AC48 -> 88656.022
F9: Quantity, m3 (STP/h) | G9: 2160 | H9: 2070 | I9: 7160 | J9: 10450 | K9: 8180 | L9: 5000.5 | Z9: Quantity, m3 (STP/h) | AA9: =SUM(AB2:AB8)*W11*Y11/X11/1000 -> 11615.873
F10: Temperature, °C | G10: 20 | H10: 390 | I10: 520 | J10: 850 | K10: 20 | L10: 20 | Z10: Temperature, °C | AA10: not stated
F11: Pressure, MPa | G11: 2 | H11: 1.9 | I11: 1.9 | J11: 1.7 | K11: 1.6 | L11: 1.5 | W11: 0.08314 | X11: 1 | Y11: 298 | Z11: Pressure, MPa
Q12: isenthalpic | AA12: min | AB12: max | AC12: average | AD12: Lost energy, kJ/h
O13: Parameter | P13: MP reforming steam | R13: Mole, mol | S13: Mass flow, kg/h | V13: Parameter | W13: Steam byproduct | X13: Energy, kJ/h | Z13: Flue gas losses | AA13: 0.06 | AB13: 0.1 | AC13: =AVERAGE(AA13:AB13) -> 0.08 | AD13: =-AC13*SUM(P76,AG52) -> 2561471
O14: Specific enthalpy, kJ/kg | P14: =2871.7 -> 2871.7 | Q14: 2871.5 | V14: Specific enthalpy increase relative to input water, kJ/kg | W14: =2871.7 -> 2871.7 | X14: https://www.peacesoftware.de/einigewerte/wasser_dampf.html
O15: H2O, vol % | P15: 100 | R15: =($A$34)*($P$16*P15/100*1000)/($E$24*$B$34) -> 206340.72 | S15: =R15*18/1000 -> 3714.133 | V15: Mass flow, kg/h | W15: 4700 | X15: =W14*W15 -> 13496990 | AA15: [Ullmanns, Hydrogen, 2. Production, 266] | AB15: [Ullmanns, Hydrogen, 2. Production, 266] | AI15: Parameter | AJ15: Water | AK15: Energy, kJ/h | AM15: Parameter | AN15: Waste water | AO15: Mole, mol | AP15: Mass flow, kg/h
O16: Quantity, m3 (STP/h) | P16: =S33/100*S34 -> 5112.24 | AI16: Specific enthalpy increase relative to input water, kJ/kg | AJ16: =84 -> 84 | AK16: https://www.peacesoftware.de/einigewerte/wasser_dampf.html | AM16: Specific enthalpy, kJ/kg | AN16: 84
O17: Temperature, °C | P17: =W17 -> 255 | Q17: 236 | R17: https://www.peacesoftware.de/einigewerte/wasser_dampf.html | V17: Temperature, °C | W17: 255 | AI17: Mass flow, kg/h | AJ17: 4700 | AK17: =AJ16*AJ17 -> 394800 | AM17: H2O, vol % | AN17: 100 | AO17: =AC33-AP33 -> 118869.6 | AP17: =AO17*18/1000 -> 2139.6529
O18: Pressure, MPa | P18: 3 | Q18: 1.9 | V18: Pressure, MPa | W18: 3 | AI18: Temperature, °C | AJ18: 255 | AM18: Temperature, °C | AN18: 20 | AO18: https://www.peacesoftware.de/einigewerte/wasser_dampf.html
AI19: Pressure, MPa | AJ19: 3 | AM19: Pressure, MPa | AN19: 0.1
AH22: T_in | AI22: T_out
E23: R | AH23: 350 | AI23: 437.86394
E24: 0.08314
C26: Parameter | D26: Feed, 1 | E26: Mole, mol | G26: Molar heat capacity, kJ/mol | H26: Heat-up energy, kJ/h | J26: Parameter | K26: Before desulfurization, 2 | L26: Mole, mol | O26: Molar heat capacity, kJ/mol | P26: Heat-up energy, kJ/h | R26: Parameter | S26: Reformer inlet, 3 | T26: Mole, mol | U26: Molar heat capacity, kJ/mol | V26: Heat-up energy, kJ/h | W26: Reaction number | X26: Reaction enthalpy, kJ/h | Y26: Insulation losses, kJ | AA26: Parameter | AB26: Reformer outlet, 4 | AC26: Mole, mol | AE26: Molar heat capacity, kJ/mol | AF26: Heat-down energy, kJ/h | AK26: Molar heat capacity, kJ/mol | AL26: Heat-down energy, kJ/h | AN26: Parameter | AO26: Pressure swing adsorption, 5 | AP26: Mole, mol | AR26: Parameter | AS26: H2 product, 6 | AT26: Mole, mol
C27: H2, vol % | D27: 0 | E27: =($A$34)*($D$34*D27/100*1000)/($E$24*$B$34) -> 0 | G27: {=N91:N97} -> 11.412697 | H27: =G27*L27 -> 45769.226 | J27: H2, vol % | K27: 4.8 | L27: =($A$34)*($K$34*K27/100*1000)/($E$24*$B$34) -> 4010.3779 | O27: {=N99:N105} -> 3.9119754 | P27: =T27*O27 -> 12435.852 | R27: H2, vol % | S27: 1.1 | T27: =($A$34)*($S$34*S27/100*1000)/($E$24*$B$34) -> 3178.9187 | U27: {=N107:N113} -> 10.046576 | V27: =T27*U27 -> 31937.249 | W27: I | X27: =Z108*AC121 -> 13778604 | Y27: min | AA27: H2, vol % | AB27: 51.9 | AC27: =($A$34)*($AB$34*AB27/100*1000)/($E$24*$B$34) -> 218905.85 | AE27: {=N115:N121} -> -15.163908 | AF27: =AC27*AE27 -> -3319468.1 | AK27: {=N123:N129} -> -12.853107 | AL27: =AK27*AP27 -> -3165730.7 | AN27: H2, vol % | AO27: 74.6 | AP27: =($A$34)*($AO$34*AO27/100*1000)/($E$24*$B$34) -> 246300.81 | AR27: H2, vol % | AS27: 99.99 | AT27: =AS27/100*$AT$34 -> 201810.48
C28: N2, vol % | D28: 1 | E28: =($A$34)*($D$34*D28/100*1000)/($E$24*$B$34) -> 871.82128 | G28: 9.0299095 | H28: =G28*L28 -> 7544.4479 | J28: N2, vol % | K28: 1 | L28: =($A$34)*($K$34*K28/100*1000)/($E$24*$B$34) -> 835.4954 | O28: 3.7626703 | P28: =T28*O28 -> 3262.1518 | R28: N2, vol % | S28: 0.3 | T28: =($A$34)*($S$34*S28/100*1000)/($E$24*$B$34) -> 866.97783 | U28: 10.307807 | V28: =T28*U28 -> 8936.6404 | W28: IV | X28: =Z107*AC126 -> -659661.69 | Y28: 0.01 | AA28: N2, vol % | AB28: 0.2 | AC28: =($A$34)*($AB$34*AB28/100*1000)/($E$24*$B$34) -> 843.56782 | AE28: -15.183445 | AF28: =AC28*AE28 -> -12808.265 | AK28: -10.39082 | AL28: =AK28*AP28 -> -8576.6335 | AN28: N2, vol % | AO28: 0.25 | AP28: =($A$34)*($AO$34*AO28/100*1000)/($E$24*$B$34) -> 825.40487 | AR28: N2, vol % | AS28: 0.01 | AT28: =AS28/100*$AT$34 -> 20.183066
C29: CO, vol % | D29: 0 | E29: =($A$34)*($D$34*D29/100*1000)/($E$24*$B$34) -> 0 | G29: 0 | H29: =G29*L29 -> 0 | J29: CO, vol % | K29: 0 | L29: =($A$34)*($K$34*K29/100*1000)/($E$24*$B$34) -> 0 | O29: 0 | P29: =T29*O29 -> 0 | R29: CO, vol % | S29: 0 | T29: =($A$34)*($S$34*S29/100*1000)/($E$24*$B$34) -> 0 | U29: 0 | V29: =T29*U29 -> 0 | W29: VII | X29: not relevant | Y29: max | AA29: CO, vol % | AB29: 10.7 | AC29: =($A$34)*($AB$34*AB29/100*1000)/($E$24*$B$34) -> 45130.878 | AE29: -15.976905 | AF29: =AC29*AE29 -> -721051.75 | AK29: -11.985409 | AL29: =AK29*AP29 -> -209727.68 | AN29: CO, vol % | AO29: 5.3 | AP29: =($A$34)*($AO$34*AO29/100*1000)/($E$24*$B$34) -> 17498.583 | AR29: CO, vol % | AS29: 0 | AT29: =AS29/100*$AT$34 -> 0
C30: CO2, vol % | D30: 0.5 | E30: =($A$34)*($D$34*D30/100*1000)/($E$24*$B$34) -> 435.91064 | G30: 16.648488 | H30: =G30*L30 -> 6954.8676 | J30: CO2, vol % | K30: 0.5 | L30: =($A$34)*($K$34*K30/100*1000)/($E$24*$B$34) -> 417.7477 | O30: 6.580752 | P30: =T30*O30 -> 1901.7887 | R30: CO2, vol % | S30: 0.1 | T30: =($A$34)*($S$34*S30/100*1000)/($E$24*$B$34) -> 288.99261 | U30: 17.816398 | V30: =T30*U30 -> 5148.8074 | W30: VIII | X30: =Z109*AC135 -> 1206475.2 | Y30: 0.05 | AA30: CO2, vol % | AB30: 5.1 | AC30: =($A$34)*($AB$34*AB30/100*1000)/($E$24*$B$34) -> 21510.979 | AE30: -26.356923 | AF30: =AC30*AE30 -> -566963.22 | AK30: -19.035557 | AL30: =AK30*AP30 -> -930152.83 | AN30: CO2, vol % | AO30: 14.8 | AP30: =($A$34)*($AO$34*AO30/100*1000)/($E$24*$B$34) -> 48863.968 | AR30: CO2, vol % | AS30: 0 | AT30: =AS30/100*$AT$34 -> 0
C31: CH4, vol % | D31: 95 | E31: =($A$34)*($D$34*D31/100*1000)/($E$24*$B$34) -> 82823.022 | G31: 14.130909 | H31: =G31*L31 -> 1067290.4 | J31: CH4, vol % | K31: 90.4 | L31: =($A$34)*($K$34*K31/100*1000)/($E$24*$B$34) -> 75528.784 | O31: 7.3660903 | P31: =T31*O31 -> 555602.62 | R31: CH4, vol % | S31: 26.1 | T31: =($A$34)*($S$34*S31/100*1000)/($E$24*$B$34) -> 75427.071 | U31: 22.55655 | V31: =T31*U31 -> 1701374.5 | Y31: average | AA31: CH4, vol % | AB31: 3.8 | AC31: =($A$34)*($AB$34*AB31/100*1000)/($E$24*$B$34) -> 16027.788 | AE31: -31.977801 | AF31: =AC31*AE31 -> -512533.42 | AK31: -16.725299 | AL31: =AK31*AP31 -> -270580.81 | AN31: CH4, vol % | AO31: 4.9 | AP31: =($A$34)*($AO$34*AO31/100*1000)/($E$24*$B$34) -> 16177.935 | AR31: CH4, vol % | AS31: 0 | AT31: =AS31/100*$AT$34 -> 0
C32: C2+, vol % | D32: 3.5 | E32: =($A$34)*($D$34*D32/100*1000)/($E$24*$B$34) -> 3051.3745 | G32: 14.130909 | H32: =G32*L32 -> 38960.822 | J32: C2+, vol % | K32: 3.3 | L32: =($A$34)*($K$34*K32/100*1000)/($E$24*$B$34) -> 2757.1348 | O32: 7.3660903 | P32: =T32*O32 -> 21287.457 | R32: C2+, vol % | S32: 1 | T32: =($A$34)*($S$34*S32/100*1000)/($E$24*$B$34) -> 2889.9261 | U32: 22.55655 | V32: =T32*U32 -> 65186.764 | Y32: =AVERAGE(Y28,Y30) -> 0.03 | AA32: C2+, vol % | AB32: 0 | AC32: =($A$34)*($AB$34*AB32/100*1000)/($E$24*$B$34) -> 0 | AE32: -31.977801 | AF32: =AC32*AE32 -> 0 | AK32: -16.725299 | AL32: =AK32*AP32 -> 0 | AN32: C2+, vol % | AO32: 0 | AP32: =($A$34)*($AO$34*AO32/100*1000)/($E$24*$B$34) -> 0 | AR32: C2+, vol % | AS32: 0 | AT32: =AS32/100*$AT$34 -> 0
A33: p_0 | B33: T_0 | C33: H2O, vol % | D33: 0 | E33: =($A$34)*($D$34*D33/100*1000)/($E$24*$B$34) -> 0 | G33: 12.671218 | H33: =G33*L33 -> 0 | J33: H2O, vol % | K33: 0 | L33: =($A$34)*($K$34*K33/100*1000)/($E$24*$B$34) -> 0 | O33: 10.374144 | P33: =T33*O33 -> 2140608.4 | R33: H2O, vol % | S33: 71.4 | T33: =($A$34)*($S$34*S33/100*1000)/($E$24*$B$34) -> 206340.72 | U33: 13.380599 | V33: =T33*U33 -> 2760962.5 | AA33: H2O, vol % | AB33: 28.3 | AC33: =($A$34)*($AB$34*AB33/100*1000)/($E$24*$B$34) -> 119364.85 | AE33: -19.716905 | AF33: =AC33*AE33 -> -2353505.3 | AK33: -14.441973 | AL33: =AK33*AP33 -> -7152.2852 | AN33: H2O, vol % | AO33: 0.15 | AP33: =($A$34)*($AO$34*AO33/100*1000)/($E$24*$B$34) -> 495.24292 | AR33: H2O, vol % | AS33: 0 | AT33: =AS33/100*$AT$34 -> 0
A34: 1 | B34: 298 | C34: Quantity, m3 (STP/h) | D34: 2160 | E34: =($A$34)*($D$34*1000)/($E$24*$B$34) -> 87182.128 | J34: Quantity, m3 (STP/h) | K34: 2070 | L34: =($A$34)*($K$34*1000)/($E$24*$B$34) -> 83549.54 | R34: Quantity, m3 (STP/h) | S34: 7160 | T34: =($A$34)*($S$34*1000)/($E$24*$B$34) -> 288992.61 | AA34: Quantity, m3 (STP/h) | AB34: 10450 | AC34: =($A$34)*($AB$34*1000)/($E$24*$B$34) -> 421783.91 | AE34: SUM | AF34: =SUM(AF27:AF33) -> -7486330.1 | AK34: SUM (HXF+HX5) | AL34: =SUM(AL27:AL33) -> -4591920.9 | AN34: Quantity, m3 (STP/h) | AO34: 8180 | AP34: =($A$34)*($AO$34*1000)/($E$24*$B$34) -> 330161.95 | AR34: Quantity, m3 (STP/h) | AS34: 5000.5 | AT34: =($A$34)*($AS$34*1000)/($E$24*$B$34) -> 201830.66
C35: Temperature, °C | D35: 20 | J35: Temperature, °C | K35: 390 | R35: Temperature, °C | S35: 520 | AA35: Temperature, °C | AB35: 850 | AK35: HX5 | AL35: =AL34+H37 -> -3425401.2 | AN35: Temperature, °C | AO35: 20 | AR35: Temperature, °C | AS35: 20
C36: Pressure, MPa | D36: 2 | J36: Pressure, MPa | K36: 1.9 | R36: Pressure, MPa | S36: 1.9 | AA36: Pressure, MPa | AB36: 1.7 | AN36: Pressure, MPa | AO36: 1.6 | AR36: Pressure, MPa | AS36: 1.5
H37: =SUM(H27:H33) -> 1166519.8 | J37: SUM | P37: =SUM(P27:P33) -> 2735098.3 | R37: SUM | V37: =SUM(V27:V33) -> 4573546.5 | X37: =SUM(X27:X28,X30) -> 14325418 | Y37: =-Y32*SUM(P76,AG52) -> 960551.62
Q39: Flue gas balance | S39: Steam balance | U39: Overall
Q40: heat-adding | R40: heat-consuming | S40: heat-adding | T40: heat-consuming | U40: heat-adding | V40: heat-consuming
AA41: Parameter | AB41: Purge gas | AC41: Mole, mol | AD41: Molar heat capacity, kJ/mol | AE41: Vapourisation enthalpy 25°C, kJ/mol | AF41: LHV 25°C, kJ/mol | AG41: Combustion energy, kJ/h | AI41: Temperature increase check
N42: balance closing over 5 and 6 | O42: Purge gas combustion | Q42: =AG52 -> -25807960 | U42: =Q42 -> -25807960 | AA42: H2, vol % | AB42: =AC42/$AC$49*100 -> 32.560964 | AC42: =AP27-AT27-AL61 -> 40479.956 | AF42: 244 | AG42: =AF42*AC42*-1 -> -9877109.2 | AJ42: Reaction | AK42: Molar heat capacity, kJ/mol | AL42: Heat-up energy, kJ/h
N43: balance cloxing over 1 and 2 | O43: Fuel gas combustion | Q43: =P76 -> -6210427.3 | U43: =Q43 -> -6210427.3 | AA43: N2, vol % | AB43: =AC43/$AC$49*100 -> 0.64737568 | AC43: =AP28-AT28-AL62 -> 804.82073 | AD43: =N142 -> 23.100387 | AG43: =AC43*AD43 -> 18591.67 | AI43: Mole CH4, mol | AJ43: =AP29-AC29 -> -27632.295 | AK43: {=N131:N137} -> 2.6457666 | AL43: =AK43*AP27 -> 651654.46
N44: balance closing over HXA | O44: HXA+ | Q44: =R49*-1 -> -4886049.5 | U44: =Q44 -> -4886049.5 | AA44: CO, vol % | AB44: =AC44/$AC$49*100 -> 14.07538 | AC44: =AP29-AT29-AL63 -> 17498.583 | AF44: 283.24 | AG44: =AF44*AC44*-1 -> -4956298.7 | AI44: Reaction enthalpy, kJ/mol | AJ44: =AC141 -> -35.812382 | AK44: 2.4738775 | AL44: =AK44*AP28 -> 2041.9506
N45: balance closing over 3 (Composition+Temp) and 4 (Temp) | O45: SMR feed warming | R45: =V37 -> 4573546.5 | V45: =R45 -> 4573546.5 | AA45: CO2, vol % | AB45: =AC45/$AC$49*100 -> 39.304834 | AC45: =AP30-AT30-AL64 -> 48863.968 | AD45: =N143 -> 41.045638 | AG45: =AC45*AD45 -> 2005652.8 | AI45: Energy. kJ/h | AJ45: =-AJ43*AJ44 -> -989578.29 | AK45: 2.6664667 | AL45: =AK45*AP29 -> 46659.39
N46: balance closing over reaction enthalpy | O46: Reaction enthalpy | R46: =X37 -> 14325418 | V46: =R46 -> 14325418 | AA46: CH4, vol % | AB46: =AC46/$AC$49*100 -> 13.013087 | AC46: =AP31-AT31-AL65 -> 16177.935 | AF46: 802.34 | AG46: =AF46*AC46*-1 -> -12980205 | AK46: 4.3468411 | AL46: =AK46*AP30 -> 212403.91
O47: Insulation losses | R47: =Y37 -> 960551.62 | V47: =R47 -> 960551.62 | AA47: C2+, vol % | AB47: =AC47/$AC$49*100 -> 0 | AC47: =AP32-AT32-AL66 -> 0 | AF47: 1437.2 | AG47: 0 | AK47: 4.6495501 | AL47: =AK47*AP31 -> 75220.121
N48: balance closing over 2 (Temp) and 3 (Composition+Temp) | O48: HX1- | R48: =P37 -> 2735098.3 | V48: =R48 -> 2735098.3 | AA48: H2O, vol % | AB48: =AC48/$AC$49*100 -> 0.3983598 | AC48: =AP33-AT33-AL67 -> 495.24292 | AD48: =N144 -> 28.349045 | AE48: 43.99 | AG48: =AC48*(AD48+AE48) -> 35825.4 | AK48: 4.6495501 | AL48: =AK48*AP32 -> 0
O49: HXA- | R49: =AD75 -> 4886049.5 | V49: =R49 -> 4886049.5 | AA49: Quantity, m3 (STP/h) | AB49: =AO34-AS34-AK68 -> 3080.1301 | AC49: =AP34-AT34-AL68 -> 124320.51 | AK49: 3.2276216 | AL49: =AK49*AP33 -> 1598.4568
O50: Flue gas losses | R50: =AD13 -> 2561471 | V50: =R50 -> 2561471 | AA50: Temperature, °C | AB50: =AO35 -> 20 | AJ50: =AJ45+AL50 -> 9.1534108e-05 | AK50: SUM | AL50: =SUM(AL43:AL49) -> 989578.29
N51: balance closing over flue gas balance | O51: HX4 & HX2 | R51: =-SUM(Q42:R50) -> 6862302.1 | S51: =-R51 -> -6862302.1 | AA51: Pressure, MPa | AB51: =AO36 -> 1.6
N52: balance closing over HXF+ and T_out WGS and 5 (Composition+Temp) | O52: HX5 | S52: =AL35 -> -3425401.2 | U52: =AL35 -> -3425401.2 | AA52: SUM | AG52: =SUM(AG42,AG44:AG46) -> -25807960
N53: balance closing over 4 (Copmposition+Temp) and T_in WGS | O53: HX3 | S53: =AF34 -> -7486330.1 | U53: =AF34 -> -7486330.1 | AE53: https://de.wikipedia.org/wiki/Verdampfungsenthalpie | AF53: https://en.wikipedia.org/wiki/Heat_of_combustion
O54: Steam byproduct | T54: =X15-AK17 -> 13102190 | V54: =X15-AK17 -> 13102190
N55: balance closing over 1 (Temp) and 2 (Composition+Temp) | O55: HXF- | V55: =H37 -> 1166519.8
N56: balance closing over HXF | O56: HXF+ | U56: =V55*-1 -> -1166519.8 | X56: =X57/U57 -> 0.095377439
O57: SUM | Q57: =SUM(Q42:Q56) -> -36904437 | R57: =SUM(R42:R56) -> 36904437 | S57: =SUM(S42:S56) -> -17774033 | T57: =SUM(T42:T56) -> 13102190 | U57: =SUM(U42:U56) -> -48982688 | V57: =SUM(V42:V56) -> 44310844 | W57: Delta | X57: =SUM(U57:V57) -> -4671843.3
R58: Kann c_p Wert Betrachtung zwischen in und out nicht machen, da ich Abgastemperatur nicht weiß
AJ60: Parameter | AK60: Hydrogenation gas
AJ61: H2, vol % | AK61: {=AS27:AS33} -> 99.99 | AL61: =($A$34)*($AK$68*AK61/100*1000)/($E$24*$B$34) -> 4010.3779
AJ62: N2, vol % | AK62: 0.01 | AL62: =($A$34)*($AK$68*AK62/100*1000)/($E$24*$B$34) -> 0.4010779
AJ63: CO, vol % | AK63: 0 | AL63: =($A$34)*($AK$68*AK63/100*1000)/($E$24*$B$34) -> 0
L64: Parameter | M64: Fuel gas (feed) | N64: Mole, mol | O64: LHV 25°C, kJ/mol | P64: Combustion energy, kJ/h | AJ64: CO2, vol % | AK64: 0 | AL64: =($A$34)*($AK$68*AK64/100*1000)/($E$24*$B$34) -> 0
L65: Combustion energy, kJ/h | M65: =SUM(V37:Y37,AG52)*-1 -> 5948444 | AJ65: CH4, vol % | AK65: 0 | AL65: =($A$34)*($AK$68*AK65/100*1000)/($E$24*$B$34) -> 0
L66: H2, vol % | M66: {=D27:D33} -> 0 | N66: =M66/100*$N$73 -> 0 | AJ66: C2+, vol % | AK66: 0 | AL66: =($A$34)*($AK$68*AK66/100*1000)/($E$24*$B$34) -> 0
L67: N2, vol % | M67: 1 | N67: =M67/100*$N$73 -> 76.433677 | AJ67: H2O, vol % | AK67: 0 | AL67: =($A$34)*($AK$68*AK67/100*1000)/($E$24*$B$34) -> 0
L68: CO, vol % | M68: 0 | N68: =M68/100*$N$73 -> 0 | AJ68: Quantity, m3 (STP/h) | AK68: =K27/100*K34/(AK61/100) -> 99.369937 | AL68: =($A$34)*($AK$68*1000)/($E$24*$B$34) -> 4010.779
L69: CO2, vol % | M69: 0.5 | N69: =M69/100*$N$73 -> 38.216838 | Z69: Parameter | AA69: Combustion air | AB69: Mole, mol | AC69: Molar heat capacity, kJ/mol | AJ69: Temperature, °C | AK69: =AS35 -> 20
L70: CH4, vol % | M70: 95 | N70: =M70/100*$N$73 -> 7261.1993 | O70: {=AF46:AF47} -> 802.34 | P70: =O70*N70*-1 -> -5825950.6 | Z70: N2, vol % | AA70: 79 | AB70: =AB71*AA70/AA71 -> 288928.78 | AC70: {=N139:N140} -> 12.200532 | AD70: =AB70*AC70 -> 3525084.7 | AJ70: Pressure, MPa | AK70: =K36 -> 1.9
L71: C2+, vol % | M71: 3.5 | N71: =M71/100*$N$73 -> 267.51787 | O71: 1437.2 | P71: =O71*N71*-1 -> -384476.68 | Z71: O2, vol % | AA71: 21 | AB71: =N70*2+N71*3.5+AC42*0.5+AC44*0.5+AC46*2 -> 76803.852 | AC71: 17.720007 | AD71: =AB71*AC71 -> 1360964.8
L72: H2O, vol % | M72: 0 | N72: =M72/100*$N$73 -> 0 | W72: 0.08314 | X72: 1 | Y72: 298 | Z72: Quantity min., m3 (STP/h) | AA72: =SUM(AB70:AB71)*W72*Y72/X72/1000 -> 9061.2892
I73: 0.08314 | J73: 1 | K73: 298 | L73: Quantity, m3 (STP/h) | M73: =N73*I73*K73/J73/1000 -> 189.36994 | N73: =E34+AL68-L34 -> 7643.3677 | Z73: Temperature, °C | AA73: =M74 -> 20
L74: Temperature, °C | M74: =D35 -> 20 | Z74: Pressure, MPa | AA74: =M75 -> 2
L75: Pressure, MPa | M75: =D36 -> 2 | Z75: SUM | AD75: =SUM(AD70:AD71) -> 4886049.5
L76: SUM | P76: =SUM(P70:P71) -> -6210427.3
F87: Molar heat capacity (temperature dependant), integral | P87: Reaction rate determination
F88: 1 bar, ideal gas | S88: H2 | T88: CO | U88: CO2 | V88: CH4 | W88: C2H6 | X88: H2O | Y88: C | AA88: Comment
G89: A | H89: B | I89: C | J89: D | K89: E | L89: T_1 | M89: T_0 | N89: deltah_Tj, kJ/mol | P89: I | R89: xi_1 | S89: 3 | T89: 1 | V89: -1 | X89: -1
F90: Feed (20->390°C) | P90: II | R90: xi_2 | S90: 1 | T90: -1 | U90: 1 | X90: -1 | Z90: linear dependant equation | AA90: Not possible to choose equation II, as in that case deltaN_C is said to be zero, which leads to a huge error in H balance, as the H balance will be a degree of freedom in that case.
F91: H2 | G91: 33.066178 | H91: -11.363417 | I91: 11.432816 | J91: -2.772874 | K91: -0.158558 | L91: =$K$35+273 -> 663 | M91: =$D$35+273 -> 293 | N91: =(G91*(L91-M91)+H91/2000*(L91^2-M91^2)+I91/(3*10^6)*(L91^3-M91^3)+J91/(4*10^9)*(L91^4-M91^4)-(10^6*K91)*(1/M91-1/L91))/1000 -> 11.412697 | P91: III | S91: 4 | U91: 1 | V91: -1 | X91: -2 | Z91: linear dependant equation
F92: N2 | G92: 19.50583 | H92: 19.88705 | I92: -8.598535 | J92: 1.369784 | K92: 0.527601 | L92: =$K$35+273 -> 663 | M92: =$D$35+273 -> 293 | N92: =(G92*(L92-M92)+H92/2000*(L92^2-M92^2)+I92/(3*10^6)*(L92^3-M92^3)+J92/(4*10^9)*(L92^4-M92^4)-(10^6*K92)*(1/M92-1/L92))/1000 -> 9.0299095 | P92: IV | S92: 2 | T92: 2 | U92: -1 | V92: -1
F93: CO | L93: =$K$35+273 -> 663 | M93: =$D$35+273 -> 293 | P93: V | Q93: soot-forming | S93: -1 | T93: -1 | X93: 1 | Y93: 1 | Z93: linear dependant equation
F94: CO2 | G94: 24.99735 | H94: 55.18696 | I94: -33.69137 | J94: 7.948387 | K94: -0.136638 | L94: =$K$35+273 -> 663 | M94: =$D$35+273 -> 293 | N94: =(G94*(L94-M94)+H94/2000*(L94^2-M94^2)+I94/(3*10^6)*(L94^3-M94^3)+J94/(4*10^9)*(L94^4-M94^4)-(10^6*K94)*(1/M94-1/L94))/1000 -> 16.648488 | P94: VI | Q94: soot-forming | T94: -2 | U94: 1 | Y94: 1 | Z94: linear dependant equation
F95: CH4 | G95: -0.703029 | H95: 108.4773 | I95: -42.52157 | J95: 5.862788 | K95: 0.678565 | L95: =$K$35+273 -> 663 | M95: =$D$35+273 -> 293 | N95: =(G95*(L95-M95)+H95/2000*(L95^2-M95^2)+I95/(3*10^6)*(L95^3-M95^3)+J95/(4*10^9)*(L95^4-M95^4)-(10^6*K95)*(1/M95-1/L95))/1000 -> 14.130909 | P95: VII | Q95: soot-forming | R95: xi_3 | S95: 2 | V95: -1 | Y95: 1
F96: C2+ | L96: =$K$35+273 -> 663 | M96: =$D$35+273 -> 293 | N96: =N95 -> 14.130909 | O96: approximation with CH4 values | P96: VIII | R96: xi_4 | S96: 5 | T96: 2 | W96: -1 | X96: -2
F97: H2O | G97: 30.092 | H97: 6.832514 | I97: 6.793435 | J97: -2.53448 | K97: 0.082139 | L97: =$K$35+273 -> 663 | M97: =$D$35+273 -> 293 | N97: =(G97*(L97-M97)+H97/2000*(L97^2-M97^2)+I97/(3*10^6)*(L97^3-M97^3)+J97/(4*10^9)*(L97^4-M97^4)-(10^6*K97)*(1/M97-1/L97))/1000 -> 12.671218
F98: Feed (390->520°C) | P98: II* | Q98: I-II | S98: =S89-S90 -> 2 | T98: =T89-T90 -> 2 | U98: =U89-U90 -> -1 | V98: =V89-V90 -> -1 | W98: =W89-W90 -> 0 | X98: =X89-X90 -> 0 | Y98: =Y89-Y90 -> 0
F99: H2 | G99: 33.066178 | H99: -11.363417 | I99: 11.432816 | J99: -2.772874 | K99: -0.158558 | L99: =$S$35+273 -> 793 | M99: =$K$35+273 -> 663 | N99: =(G99*(L99-M99)+H99/2000*(L99^2-M99^2)+I99/(3*10^6)*(L99^3-M99^3)+J99/(4*10^9)*(L99^4-M99^4)-(10^6*K99)*(1/M99-1/L99))/1000 -> 3.9119754 | P99: III* | Q99: 2I-III | S99: =2*S89-S91 -> 2 | T99: =2*T89-T91 -> 2 | U99: =2*U89-U91 -> -1 | V99: =2*V89-V91 -> -1 | W99: =2*W89-W91 -> 0 | X99: =2*X89-X91 -> 0 | Y99: =2*Y89-Y91 -> 0
F100: N2 | G100: 19.50583 | H100: 19.88705 | I100: -8.598535 | J100: 1.369784 | K100: 0.527601 | L100: =$S$35+273 -> 793 | M100: =$K$35+273 -> 663 | N100: =(G100*(L100-M100)+H100/2000*(L100^2-M100^2)+I100/(3*10^6)*(L100^3-M100^3)+J100/(4*10^9)*(L100^4-M100^4)-(10^6*K100)*(1/M100-1/L100))/1000 -> 3.7626703 | P100: V* | Q100: I+V | S100: =S89+S93 -> 2 | T100: =T89+T93 -> 0 | U100: =U89+U93 -> 0 | V100: =V89+V93 -> -1 | W100: =W89+W93 -> 0 | X100: =X89+X93 -> 0 | Y100: =Y89+Y93 -> 1
F101: CO | L101: =$S$35+273 -> 793 | M101: =$K$35+273 -> 663 | P101: VI* | Q101: VI-II | S101: =S94-S90 -> -1 | T101: =T94-T90 -> -1 | U101: =U94-U90 -> 0 | V101: =V94-V90 -> 0 | W101: =W94-W90 -> 0 | X101: =X94-X90 -> 1 | Y101: =Y94-Y90 -> 1
F102: CO2 | G102: 24.99735 | H102: 55.18696 | I102: -33.69137 | J102: 7.948387 | K102: -0.136638 | L102: =$S$35+273 -> 793 | M102: =$K$35+273 -> 663 | N102: =(G102*(L102-M102)+H102/2000*(L102^2-M102^2)+I102/(3*10^6)*(L102^3-M102^3)+J102/(4*10^9)*(L102^4-M102^4)-(10^6*K102)*(1/M102-1/L102))/1000 -> 6.580752
F103: CH4 | G103: -0.703029 | H103: 108.4773 | I103: -42.52157 | J103: 5.862788 | K103: 0.678565 | L103: =$S$35+273 -> 793 | M103: =$K$35+273 -> 663 | N103: =(G103*(L103-M103)+H103/2000*(L103^2-M103^2)+I103/(3*10^6)*(L103^3-M103^3)+J103/(4*10^9)*(L103^4-M103^4)-(10^6*K103)*(1/M103-1/L103))/1000 -> 7.3660903 | AB103: Double-check
F104: C2+ | L104: =$S$35+273 -> 793 | M104: =$K$35+273 -> 663 | N104: =N103 -> 7.3660903 | S104: xi_1 | T104: xi_2 | U104: xi_3 | V104: xi_4 | AB104: balance | AC104: calculated | AD104: error
F105: H2O (236->520°C) | G105: 30.092 | H105: 6.832514 | I105: 6.793435 | J105: -2.53448 | K105: 0.082139 | L105: =$S$35+273 -> 793 | M105: =$Q$17+273 -> 509 | N105: =(G105*(L105-M105)+H105/2000*(L105^2-M105^2)+I105/(3*10^6)*(L105^3-M105^3)+J105/(4*10^9)*(L105^4-M105^4)-(10^6*K105)*(1/M105-1/L105))/1000 -> 10.374144 | R105: deltaN_H2 | S105: =S89 -> 3 | T105: =S90 -> 1 | U105: =S95 -> 2 | V105: =S96 -> 5 | AB105: =AB27/100*AC34-S27/100*T34 -> 215726.93 | AC105: =S105*Z$108+T105*Z$107+U105*Z$111+V105*Z$109 -> 213869.47 | AD105: =(AC105-AB105)/AB105 -> -0.0086102541
F106: Feed (520->850°C) | R106: deltaN_CO | S106: =T89 -> 1 | T106: =T90 -> -1 | V106: =T96 -> 2 | AB106: =AB29/100*AC34-S29/100*T34 -> 45130.878 | AC106: =S106*Z$108+T106*Z$107+U106*Z$111+V106*Z$109 -> 43957.148 | AD106: =(AC106-AB106)/AB106 -> -0.026007244
F107: H2 | G107: 33.066178 | H107: -11.363417 | I107: 11.432816 | J107: -2.772874 | K107: -0.158558 | L107: =$AB$35+273 -> 1123 | M107: =$S$35+273 -> 793 | N107: =(G107*(L107-M107)+H107/2000*(L107^2-M107^2)+I107/(3*10^6)*(L107^3-M107^3)+J107/(4*10^9)*(L107^4-M107^4)-(10^6*K107)*(1/M107-1/L107))/1000 -> 10.046576 | R107: deltaN_CO2 | T107: =U90 -> 1 | W107: =AB30/100*AC34-S30/100*T34 -> 21221.987 | X107: -> | Y107: xi_2 = | Z107: =W107*T107 -> 21221.987 | AA107: mol
F108: N2 | G108: 19.50583 | H108: 19.88705 | I108: -8.598535 | J108: 1.369784 | K108: 0.527601 | L108: =$AB$35+273 -> 1123 | M108: =$S$35+273 -> 793 | N108: =(G108*(L108-M108)+H108/2000*(L108^2-M108^2)+I108/(3*10^6)*(L108^3-M108^3)+J108/(4*10^9)*(L108^4-M108^4)-(10^6*K108)*(1/M108-1/L108))/1000 -> 10.307807 | R108: deltaN_CH4 | S108: =V89 -> -1 | U108: =V95 -> -1 | W108: =AB31/100*AC34-S31/100*T34 -> -59399.283 | X108: -> | Y108: xi_1 = | Z108: =(W108-(U108*Z111))/S108 -> 59399.283 | AA108: mol
F109: CO | L109: =$AB$35+273 -> 1123 | M109: =$S$35+273 -> 793 | R109: deltaN_C2H6 | V109: =W96 -> -1 | W109: =AB32/100*AC34-S32/100*T34 -> -2889.9261 | X109: -> | Y109: xi_4 = | Z109: =W109*V109 -> 2889.9261 | AA109: mol
F110: CO2 | G110: 24.99735 | H110: 55.18696 | I110: -33.69137 | J110: 7.948387 | K110: -0.136638 | L110: =$AB$35+273 -> 1123 | M110: =$S$35+273 -> 793 | N110: =(G110*(L110-M110)+H110/2000*(L110^2-M110^2)+I110/(3*10^6)*(L110^3-M110^3)+J110/(4*10^9)*(L110^4-M110^4)-(10^6*K110)*(1/M110-1/L110))/1000 -> 17.816398 | R110: deltaN_H2O | S110: =X89 -> -1 | T110: =X90 -> -1 | V110: -2 | AB110: =AB33/100*AC34-S33/100*T34 -> -86975.878 | AC110: =S110*Z$108+T110*Z$107+U110*Z$111+V110*Z$109 -> -86401.122 | AD110: =(AC110-AB110)/AB110 -> -0.0066082259
F111: CH4 | G111: -0.703029 | H111: 108.4773 | I111: -42.52157 | J111: 5.862788 | K111: 0.678565 | L111: =$AB$35+273 -> 1123 | M111: =$S$35+273 -> 793 | N111: =(G111*(L111-M111)+H111/2000*(L111^2-M111^2)+I111/(3*10^6)*(L111^3-M111^3)+J111/(4*10^9)*(L111^4-M111^4)-(10^6*K111)*(1/M111-1/L111))/1000 -> 22.55655 | R111: deltaN_C | U111: =Y95 -> 1 | W111: 0 | X111: -> | Y111: xi_3 = | Z111: 0 | AA111: mol | AB111: 0 | AC111: =S111*Z$110+T111*Z$107+U111*Z$105+V111*Z$109 -> 0
F112: C2+ | L112: =$AB$35+273 -> 1123 | M112: =$S$35+273 -> 793 | N112: =N111 -> 22.55655
F113: H2O | G113: 30.092 | H113: 6.832514 | I113: 6.793435 | J113: -2.53448 | K113: 0.082139 | L113: =$AB$35+273 -> 1123 | M113: =$S$35+273 -> 793 | N113: =(G113*(L113-M113)+H113/2000*(L113^2-M113^2)+I113/(3*10^6)*(L113^3-M113^3)+J113/(4*10^9)*(L113^4-M113^4)-(10^6*K113)*(1/M113-1/L113))/1000 -> 13.380599
F114: Feed (850->350°C) | P114: Reaction enthalpy determination
F115: H2 | G115: 33.066178 | H115: -11.363417 | I115: 11.432816 | J115: -2.772874 | K115: -0.158558 | L115: =$AH$23+273 -> 623 | M115: =$AB$35+273 -> 1123 | N115: =(G115*(L115-M115)+H115/2000*(L115^2-M115^2)+I115/(3*10^6)*(L115^3-M115^3)+J115/(4*10^9)*(L115^4-M115^4)-(10^6*K115)*(1/M115-1/L115))/1000 -> -15.163908 | AB115: neglected because ideal gas
...

Sheet SMR, rev. DMR, C-forming, C2H6
B10: Parameter | C10: Feed, 1 | D10: Before desulfurization, 2 | E10: Reformer inlet, 3 | F10: Reformer outlet, 4 | G10: Pressure swing adsorption, 5 | H10: H2 product, 6
B11: H2, vol % | C11: 0 | D11: 4.8 | E11: 1.1 | F11: 51.9 | G11: 74.6 | H11: 99.99 | Q11: Steam export | R11: 4700 | S11: kg/h
B12: N2, vol % | C12: 1 | D12: 1 | E12: 0.3 | F12: 0.2 | G12: 0.25 | H12: 0.01 | R12: 3 | S12: MPa
B13: CO, vol % | C13: 0 | D13: 0 | E13: 0 | F13: 10.7 | G13: 5.3 | H13: 0 | R13: 255 | S13: °C | U13: Off gas
B14: CO2, vol % | C14: 0.5 | D14: 0.5 | E14: 0.1 | F14: 5.1 | G14: 14.8 | H14: 0 | W14: min | X14: max | Y14: average
B15: CH4, vol % | C15: 95 | D15: 90.4 | E15: 26.1 | F15: 3.8 | G15: 4.9 | H15: 0 | U15: Insulation losses | V15: Furnace section | W15: 0.01 | X15: 0.05 | Y15: =AVERAGE(W15:X15) -> 0.03
B16: C2+, vol % | C16: 3.5 | D16: 3.3 | E16: 1 | F16: 0 | G16: 0 | H16: 0 | V16: Convection zone | W16: 0.06 | X16: 0.1 | Y16: =AVERAGE(W16:X16) -> 0.08
B17: H2O, vol % | C17: 0 | D17: 0 | E17: 71.4 | F17: 28.3 | G17: 0.15 | H17: 0 | W17: [Ullmanns, Hydrogen, 2. Production, 266] | X17: [Ullmanns, Hydrogen, 2. Production, 266]
B18: Quantity, m3 (STP/h) | C18: 2160 | D18: 2070 | E18: 7160 | F18: 10450 | G18: 8180 | H18: 5000.5 | P18: SMR steam
B19: Temperature, °C | C19: 20 | D19: 390 | E19: 520 | F19: 850 | G19: 20 | H19: 20 | X19: Water
B20: Pressure, MPa | C20: 2 | D20: 1.9 | E20: 1.9 | F20: 1.7 | G20: 1.6 | H20: 1.5
H26: Parameter | I26: Feed, 1 | L26: Parameter | M26: Before desulfurization, 2 | R26: Parameter | S26: Reformer inlet, 3 | V26: Parameter | W26: Reformer outlet, 4 | AD26: Parameter | AE26: Pressure swing adsorption, 5 | AH26: Parameter | AI26: H2 product, 6
H27: H2, vol % | I27: 0 | L27: H2, vol % | M27: 4.8 | R27: H2, vol % | S27: 1.1 | V27: H2, vol % | W27: 51.9 | AD27: H2, vol % | AE27: 74.6 | AH27: H2, vol % | AI27: 99.99
H28: N2, vol % | I28: 1 | L28: N2, vol % | M28: 1 | R28: N2, vol % | S28: 0.3 | V28: N2, vol % | W28: 0.2 | AD28: N2, vol % | AE28: 0.25 | AH28: N2, vol % | AI28: 0.01
H29: CO, vol % | I29: 0 | L29: CO, vol % | M29: 0 | R29: CO, vol % | S29: 0 | V29: CO, vol % | W29: 10.7 | AD29: CO, vol % | AE29: 5.3 | AH29: CO, vol % | AI29: 0
H30: CO2, vol % | I30: 0.5 | L30: CO2, vol % | M30: 0.5 | R30: CO2, vol % | S30: 0.1 | V30: CO2, vol % | W30: 5.1 | AD30: CO2, vol % | AE30: 14.8 | AH30: CO2, vol % | AI30: 0
H31: CH4, vol % | I31: 95 | L31: CH4, vol % | M31: 90.4 | R31: CH4, vol % | S31: 26.1 | V31: CH4, vol % | W31: 3.8 | AD31: CH4, vol % | AE31: 4.9 | AH31: CH4, vol % | AI31: 0
H32: C2+, vol % | I32: 3.5 | L32: C2+, vol % | M32: 3.3 | R32: C2+, vol % | S32: 1 | V32: C2+, vol % | W32: 0 | AD32: C2+, vol % | AE32: 0 | AH32: C2+, vol % | AI32: 0
H33: H2O, vol % | I33: 0 | L33: H2O, vol % | M33: 0 | R33: H2O, vol % | S33: 71.4 | V33: H2O, vol % | W33: 28.3 | AD33: H2O, vol % | AE33: 0.15 | AH33: H2O, vol % | AI33: 0
H34: Quantity, m3 (STP/h) | I34: 2160 | L34: Quantity, m3 (STP/h) | M34: 2070 | R34: Quantity, m3 (STP/h) | S34: 7160 | T34: =O49 -> 288992.61 | V34: Quantity, m3 (STP/h) | W34: 10450 | X34: =($K$49)*($W$34*1000)/($N$39*$L$49) -> 421783.91 | AD34: Quantity, m3 (STP/h) | AE34: 8180 | AH34: Quantity, m3 (STP/h) | AI34: 5000.5
H35: Temperature, °C | I35: 20 | L35: Temperature, °C | M35: 390 | R35: Temperature, °C | S35: 520 | V35: Temperature, °C | W35: 850 | AD35: Temperature, °C | AE35: 20 | AH35: Temperature, °C | AI35: 20
H36: Pressure, MPa | I36: 2 | L36: Pressure, MPa | M36: 1.9 | R36: Pressure, MPa | S36: 1.9 | V36: Pressure, MPa | W36: 1.7 | AD36: Pressure, MPa | AE36: 1.6 | AH36: Pressure, MPa | AI36: 1.5
N37: Ideal gas | AA37: Ideal gas
N38: n = p*V/(R*T) | AA38: n = p*V/(R*T) | AD38: Delta T
M39: R = | N39: 0.08314 | O39: bar*l/(mol*K) | Z39: R = | AA39: 0.08314 | AB39: bar*l/(mol*K) | AD39: 230 | AE39: K
M41: Parameter | N41: Reformer inlet, 3 | O41: Mole | P41: Molar heat capacity [kJ/(mol K)] | Q41: Heat-up energy [kJ] | S41: Reaction enthalpy [kJ] | T41: Insulation losses [kJ] | Y41: Parameter | Z41: Purge gas | AA41: Mole | AB41: Molar heat capacity 25°C [kJ/(mol K)] | AC41: Vapourisation enthalpy 25°C [kJ/mol] | AD41: LHV 25°C [kJ/mol] | AE41: Combustion energy [kJ]
M42: H2, vol % | N42: 1.1 | O42: =($K$49)*($N$49*N42/100*1000)/($N$39*$L$49) -> 3178.9187 | P42: see below | Q42: =O42*SUM(F100:F430) -> 20051.823 | R42: I | S42: =T93*W104 -> 9891716.8 | Y42: H2, vol % | Z42: =($AE$34*AE27/100-$AI$34*AI27/100-$W$80*W70/100)/$Z$49*100 -> 32.560964 | AA42: =($W$49)*($Z$49*Z42/100*1000)/($AA$39*$X$49) -> 40479.956 | AD42: 244 | AE42: =AD42*AA42*-1 -> -9877109.2
M43: N2, vol % | N43: 0.3 | O43: =($K$49)*($N$49*N43/100*1000)/($N$39*$L$49) -> 866.97783 | P43: see below | Q43: =O43*SUM(G100:G430) -> 9303.7102 | R43: IV | S43: =T90*W109 -> -6610180.4 | Y43: N2, vol % | Z43: =($AE$34*AE28/100-$AI$34*AI28/100-$W$80*W71/100)/$Z$49*100 -> 0.64737568 | AA43: =($W$49)*($Z$49*Z43/100*1000)/($AA$39*$X$49) -> 804.82073 | AE43: neglegible
M44: CO, vol % | N44: 0 | O44: =($K$49)*($N$49*N44/100*1000)/($N$39*$L$49) -> 0 | Q44: 0 | R44: VII | S44: neglected | Y44: CO, vol % | Z44: =($AE$34*AE29/100-$AI$34*AI29/100-$W$80*W72/100)/$Z$49*100 -> 14.07538 | AA44: =($W$49)*($Z$49*Z44/100*1000)/($AA$39*$X$49) -> 17498.583 | AD44: 283.24 | AE44: =AD44*AA44*-1 -> -4956298.7
M45: CO2, vol % | N45: 0.1 | O45: =($K$49)*($N$49*N45/100*1000)/($N$39*$L$49) -> 288.99261 | P45: see below | Q45: =O45*SUM(H100:H430) -> 5134.9963 | R45: VIII | S45: =T92*W118 -> 14393.65 | Y45: CO2, vol % | Z45: =($AE$34*AE30/100-$AI$34*AI30/100-$W$80*W73/100)/$Z$49*100 -> 39.304834 | AA45: =($W$49)*($Z$49*Z45/100*1000)/($AA$39*$X$49) -> 48863.968 | AB45: =H80 -> 0.037122832 | AE45: =AA45*AB45*AD39 -> 417212.84
M46: CH4, vol % | N46: 26.1 | O46: =($K$49)*($N$49*N46/100*1000)/($N$39*$L$49) -> 75427.071 | P46: see below | Q46: =O46*SUM(D100:D430) -> 1744545.8 | Y46: CH4, vol % | Z46: =($AE$34*AE31/100-$AI$34*AI31/100-$W$80*W74/100)/$Z$49*100 -> 13.013087 | AA46: =($W$49)*($Z$49*Z46/100*1000)/($AA$39*$X$49) -> 16177.935 | AD46: 802.34 | AE46: =AD46*AA46*-1 -> -12980205
M47: C2+, vol % | N47: 1 | O47: =($K$49)*($N$49*N47/100*1000)/($N$39*$L$49) -> 2889.9261 | P47: approximation with CH4 values | Q47: =O47*SUM(F100:F430) -> 18228.93 | Y47: C2+, vol % | Z47: =($AE$34*AE32/100-$AI$34*AI32/100-$W$80*W75/100)/$Z$49*100 -> 0 | AA47: =($W$49)*($Z$49*Z47/100*1000)/($AA$39*$X$49) -> 0
M48: H2O, vol % | N48: 71.4 | O48: =($K$49)*($N$49*N48/100*1000)/($N$39*$L$49) -> 206340.72 | P48: see below | Q48: =O48*SUM(E100:E430) -> 36719652 | Y48: H2O, vol % | Z48: =($AE$34*AE33/100-$AI$34*AI33/100-$W$80*W76/100)/$Z$49*100 -> 0.3983598 | AA48: =($W$49)*($Z$49*Z48/100*1000)/($AA$39*$X$49) -> 495.24292 | AC48: 43.99 | AE48: neglegible
K49: 1 | L49: 298 | M49: Quantity, m3 (STP/h) | N49: 7160 | O49: =($K$49)*($N$49*1000)/($N$39*$L$49) -> 288992.61 | W49: 1 | X49: 298 | Y49: Quantity, m3 (STP/h) | Z49: =AE34-AI34-W80 -> 3080.1301
M50: Temperature, °C | N50: 520 | Y50: Temperature, °C | Z50: =AE35 -> 20
M51: Pressure, MPa | N51: 1.9 | Y51: Pressure, MPa | Z51: =AE36 -> 1.6
M52: SUM | Q52: =SUM(Q42:Q48) -> 38516917 | S52: =SUM(S42:S43,S45) -> 3295930.1 | T52: =SUM(Q52:S52)/(1-SUM(Y15:Y16))*SUM(Y15:Y16) -> 5167880 | Y52: SUM | AE52: =SUM(AE42,AE44:AE46) -> -27396400
AC53: https://de.wikipedia.org/wiki/Verdampfungsenthalpie | AD53: https://en.wikipedia.org/wiki/Heat_of_combustion
U58: Fuel gas
U59: Combustion energy [kJ] | V59: =SUM(Q52:T52,AE52)*-1 -> -19584327
V69: Parameter | W69: Purge gas
A70: Molar heat capacity (temperature dependant) | J70: Reaction rate determination | V70: H2, vol % | W70: {=AI27:AI33} -> 99.99
D71: 1 bar, ideal gas | E71: 1 bar, ideal gas | F71: 1 bar, ideal gas | G71: 1 bar, ideal gas | H71: 1 bar, ideal gas | M71: H2 | N71: CO | O71: CO2 | P71: CH4 | Q71: C2H6 | R71: H2O | S71: C | U71: Comment | V71: N2, vol % | W71: 0.01
D72: CH4 | E72: H2O | F72: H2 | G72: N2 | H72: CO2 | J72: I | L72: xi_1 | M72: 3 | N72: 1 | P72: -1 | R72: -1 | V72: CO, vol % | W72: 0
C73: A | D73: -0.703029 | E73: -203.606 | F73: 33.066178 | G73: 19.50583 | H73: 24.99735 | J73: II | M73: 1 | N73: -1 | O73: 1 | R73: -1 | T73: linear dependant equation | U73: Not possible to choose equation II, as in that case deltaN_C is said to be zero, which leads to a huge error in H balance, as the H balance will be a degree of freedom in that case. | V73: CO2, vol % | W73: 0
C74: B | D74: 108.4773 | E74: 1523.29 | F74: -11.363417 | G74: 19.88705 | H74: 55.18696 | J74: III | M74: 4 | O74: 1 | P74: -1 | R74: -2 | T74: linear dependant equation | V74: CH4, vol % | W74: 0
C75: C | D75: -42.52157 | E75: -3196.413 | F75: 11.432816 | G75: -8.598535 | H75: -33.69137 | J75: IV | L75: xi_2 | M75: 2 | N75: 2 | O75: -1 | P75: -1 | V75: C2+, vol % | W75: 0
C76: D | D76: 5.862788 | E76: 2474.255 | F76: -2.772874 | G76: 1.369784 | H76: 7.948387 | J76: V | K76: soot-forming | M76: -1 | N76: -1 | R76: 1 | S76: 1 | T76: linear dependant equation | V76: H2O, vol % | W76: 0
C77: E | D77: 0.678565 | E77: 3.855326 | F77: -9.980797 | G77: 0.527601 | H77: -0.136638 | J77: VI | K77: soot-forming | N77: -2 | O77: 1 | S77: 1 | T77: linear dependant equation
J78: VII | K78: soot-forming | L78: xi_3 | M78: 2 | P78: -1 | S78: 1
A79: Temp [K] | B79: T/1000 | C79: Temp [°C] | D79: Molar heat capacity c_p [kJ/(mol K)] | J79: VIII | L79: xi_4 | M79: 5 | N79: 2 | Q79: -1 | R79: -2
A80: 298 | B80: =A80/1000 -> 0.298 | C80: =A80-273 -> 25 | D80: =(D$73+D$74*$B80+D$75*($B80^2)+D$76*($B80^3)+D$77/($B80^2))/1000 -> 0.035643425 | E80: =(E$73+E$74*$B80+E$75*($B80^2)+E$76*($B80^3)+E$77/($B80^2))/1000 -> 0.075371713 | F80: =(F$73+F$74*$B80+F$75*($B80^2)+F$76*($B80^3)+F$77/($B80^2))/1000 -> -0.081769521 | G80: =(G$73+G$74*$B80+G$75*($B80^2)+G$76*($B80^3)+G$77/($B80^2))/1000 -> 0.030646021 | H80: =(H$73+H$74*$B80+H$75*($B80^2)+H$76*($B80^3)+H$77/($B80^2))/1000 -> 0.037122832 | V80: Quantity, m3 (STP/h) | W80: =M27/100*M34/(W70/100) -> 99.369937
A81: 774 | B81: =A81/1000 -> 0.774 | C81: =A81-273 -> 501 | D81: =(D$73+D$74*$B81+D$75*($B81^2)+D$76*($B81^3)+D$77/($B81^2))/1000 -> 0.061635921 | E81: =(E$73+E$74*$B81+E$75*($B81^2)+E$76*($B81^3)+E$77/($B81^2))/1000 -> 0.21423609 | F81: =(F$73+F$74*$B81+F$75*($B81^2)+F$76*($B81^3)+F$77/($B81^2))/1000 -> 0.013173961 | G81: =(G$73+G$74*$B81+G$75*($B81^2)+G$76*($B81^3)+G$77/($B81^2))/1000 -> 0.03126307 | H81: =(H$73+H$74*$B81+H$75*($B81^2)+H$76*($B81^3)+H$77/($B81^2))/1000 -> 0.050985831 | J81: II* | K81: I-II | M81: =M72-M73 -> 2 | N81: =N72-N73 -> 2 | O81: =O72-O73 -> -1 | P81: =P72-P73 -> -1 | Q81: =Q72-Q73 -> 0 | R81: =R72-R73 -> 0 | S81: =S72-S73 -> 0 | V81: Temperature, °C | W81: =AI35 -> 20
A82: 775 | B82: =A82/1000 -> 0.775 | C82: =A82-273 -> 502 | D82: =(D$73+D$74*$B82+D$75*($B82^2)+D$76*($B82^3)+D$77/($B82^2))/1000 -> 0.061686162 | E82: =(E$73+E$74*$B82+E$75*($B82^2)+E$76*($B82^3)+E$77/($B82^2))/1000 -> 0.21524409 | F82: =(F$73+F$74*$B82+F$75*($B82^2)+F$76*($B82^3)+F$77/($B82^2))/1000 -> 0.013218283 | G82: =(G$73+G$74*$B82+G$75*($B82^2)+G$76*($B82^3)+G$77/($B82^2))/1000 -> 0.031269832 | H82: =(H$73+H$74*$B82+H$75*($B82^2)+H$76*($B82^3)+H$77/($B82^2))/1000 -> 0.051003722 | J82: III* | K82: 2I-III | M82: =2*M72-M74 -> 2 | N82: =2*N72-N74 -> 2 | O82: =2*O72-O74 -> -1 | P82: =2*P72-P74 -> -1 | Q82: =2*Q72-Q74 -> 0 | R82: =2*R72-R74 -> 0 | S82: =2*S72-S74 -> 0 | V82: Pressure, MPa | W82: =M36 -> 1.9
A83: 776 | B83: =A83/1000 -> 0.776 | C83: =A83-273 -> 503 | D83: =(D$73+D$74*$B83+D$75*($B83^2)+D$76*($B83^3)+D$77/($B83^2))/1000 -> 0.061736356 | E83: =(E$73+E$74*$B83+E$75*($B83^2)+E$76*($B83^3)+E$77/($B83^2))/1000 -> 0.21625727 | F83: =(F$73+F$74*$B83+F$75*($B83^2)+F$76*($B83^3)+F$77/($B83^2))/1000 -> 0.01326245 | G83: =(G$73+G$74*$B83+G$75*($B83^2)+G$76*($B83^3)+G$77/($B83^2))/1000 -> 0.031276591 | H83: =(H$73+H$74*$B83+H$75*($B83^2)+H$76*($B83^3)+H$77/($B83^2))/1000 -> 0.05102158 | J83: V* | K83: I+V | M83: =M72+M76 -> 2 | N83: =N72+N76 -> 0 | O83: =O72+O76 -> 0 | P83: =P72+P76 -> -1 | Q83: =Q72+Q76 -> 0 | R83: =R72+R76 -> 0 | S83: =S72+S76 -> 1
A84: 777 | B84: =A84/1000 -> 0.777 | C84: =A84-273 -> 504 | D84: =(D$73+D$74*$B84+D$75*($B84^2)+D$76*($B84^3)+D$77/($B84^2))/1000 -> 0.061786503 | E84: =(E$73+E$74*$B84+E$75*($B84^2)+E$76*($B84^3)+E$77/($B84^2))/1000 -> 0.21727563 | F84: =(F$73+F$74*$B84+F$75*($B84^2)+F$76*($B84^3)+F$77/($B84^2))/1000 -> 0.013306462 | G84: =(G$73+G$74*$B84+G$75*($B84^2)+G$76*($B84^3)+G$77/($B84^2))/1000 -> 0.031283349 | H84: =(H$73+H$74*$B84+H$75*($B84^2)+H$76*($B84^3)+H$77/($B84^2))/1000 -> 0.051039405 | J84: VI* | K84: VI-II | M84: =M77-M73 -> -1 | N84: =N77-N73 -> -1 | O84: =O77-O73 -> 0 | P84: =P77-P73 -> 0 | Q84: =Q77-Q73 -> 0 | R84: =R77-R73 -> 1 | S84: =S77-S73 -> 1
A85: 778 | B85: =A85/1000 -> 0.778 | C85: =A85-273 -> 505 | D85: =(D$73+D$74*$B85+D$75*($B85^2)+D$76*($B85^3)+D$77/($B85^2))/1000 -> 0.061836604 | E85: =(E$73+E$74*$B85+E$75*($B85^2)+E$76*($B85^3)+E$77/($B85^2))/1000 -> 0.2182992 | F85: =(F$73+F$74*$B85+F$75*($B85^2)+F$76*($B85^3)+F$77/($B85^2))/1000 -> 0.013350319 | G85: =(G$73+G$74*$B85+G$75*($B85^2)+G$76*($B85^3)+G$77/($B85^2))/1000 -> 0.031290104 | H85: =(H$73+H$74*$B85+H$75*($B85^2)+H$76*($B85^3)+H$77/($B85^2))/1000 -> 0.051057198
A86: 779 | B86: =A86/1000 -> 0.779 | C86: =A86-273 -> 506 | D86: =(D$73+D$74*$B86+D$75*($B86^2)+D$76*($B86^3)+D$77/($B86^2))/1000 -> 0.061886659 | E86: =(E$73+E$74*$B86+E$75*($B86^2)+E$76*($B86^3)+E$77/($B86^2))/1000 -> 0.21932799 | F86: =(F$73+F$74*$B86+F$75*($B86^2)+F$76*($B86^3)+F$77/($B86^2))/1000 -> 0.013394022 | G86: =(G$73+G$74*$B86+G$75*($B86^2)+G$76*($B86^3)+G$77/($B86^2))/1000 -> 0.031296857 | H86: =(H$73+H$74*$B86+H$75*($B86^2)+H$76*($B86^3)+H$77/($B86^2))/1000 -> 0.051074959 | V86: Double-check
A87: 780 | B87: =A87/1000 -> 0.78 | C87: =A87-273 -> 507 | D87: =(D$73+D$74*$B87+D$75*($B87^2)+D$76*($B87^3)+D$77/($B87^2))/1000 -> 0.061936667 | E87: =(E$73+E$74*$B87+E$75*($B87^2)+E$76*($B87^3)+E$77/($B87^2))/1000 -> 0.22036202 | F87: =(F$73+F$74*$B87+F$75*($B87^2)+F$76*($B87^3)+F$77/($B87^2))/1000 -> 0.013437573 | G87: =(G$73+G$74*$B87+G$75*($B87^2)+G$76*($B87^3)+G$77/($B87^2))/1000 -> 0.031303608 | H87: =(H$73+H$74*$B87+H$75*($B87^2)+H$76*($B87^3)+H$77/($B87^2))/1000 -> 0.051092686 | M87: xi_1 | N87: xi_2 | O87: xi_3 | P87: xi_4 | V87: balance | W87: calculated | X87: error
A88: 781 | B88: =A88/1000 -> 0.781 | C88: =A88-273 -> 508 | D88: =(D$73+D$74*$B88+D$75*($B88^2)+D$76*($B88^3)+D$77/($B88^2))/1000 -> 0.061986628 | E88: =(E$73+E$74*$B88+E$75*($B88^2)+E$76*($B88^3)+E$77/($B88^2))/1000 -> 0.22140129 | F88: =(F$73+F$74*$B88+F$75*($B88^2)+F$76*($B88^3)+F$77/($B88^2))/1000 -> 0.013480972 | G88: =(G$73+G$74*$B88+G$75*($B88^2)+G$76*($B88^3)+G$77/($B88^2))/1000 -> 0.031310357 | H88: =(H$73+H$74*$B88+H$75*($B88^2)+H$76*($B88^3)+H$77/($B88^2))/1000 -> 0.051110382 | L88: deltaN_H2 | M88: =M72 -> 3 | N88: =M75 -> 2 | O88: =M78 -> 2 | P88: =M79 -> 5 | Q88: =W27/100*X34-S27/100*T34 -> 215726.93 | R88: -> | S88: xi_3 = | T88: =(Q88-(T93*M88+T90*N88+T92*P88))/O88 -> 66.597459 | U88: mol
A89: 782 | B89: =A89/1000 -> 0.782 | C89: =A89-273 -> 509 | D89: =(D$73+D$74*$B89+D$75*($B89^2)+D$76*($B89^3)+D$77/($B89^2))/1000 -> 0.062036543 | E89: =(E$73+E$74*$B89+E$75*($B89^2)+E$76*($B89^3)+E$77/($B89^2))/1000 -> 0.22244583 | F89: =(F$73+F$74*$B89+F$75*($B89^2)+F$76*($B89^3)+F$77/($B89^2))/1000 -> 0.01352422 | G89: =(G$73+G$74*$B89+G$75*($B89^2)+G$76*($B89^3)+G$77/($B89^2))/1000 -> 0.031317104 | H89: =(H$73+H$74*$B89+H$75*($B89^2)+H$76*($B89^3)+H$77/($B89^2))/1000 -> 0.051128045 | L89: deltaN_CO | M89: =N72 -> 1 | N89: =N75 -> 2 | P89: =N79 -> 2 | V89: =W29/100*X34-S29/100*T34 -> 45130.878 | W89: =M89*T$93+N89*T$90+O89*T$88+P89*T$92 -> 44531.905 | X89: =(W89-V89)/V89 -> -0.013271922
A90: 783 | B90: =A90/1000 -> 0.783 | C90: =A90-273 -> 510 | D90: =(D$73+D$74*$B90+D$75*($B90^2)+D$76*($B90^3)+D$77/($B90^2))/1000 -> 0.062086411 | E90: =(E$73+E$74*$B90+E$75*($B90^2)+E$76*($B90^3)+E$77/($B90^2))/1000 -> 0.22349565 | F90: =(F$73+F$74*$B90+F$75*($B90^2)+F$76*($B90^3)+F$77/($B90^2))/1000 -> 0.013567318 | G90: =(G$73+G$74*$B90+G$75*($B90^2)+G$76*($B90^3)+G$77/($B90^2))/1000 -> 0.031323848 | H90: =(H$73+H$74*$B90+H$75*($B90^2)+H$76*($B90^3)+H$77/($B90^2))/1000 -> 0.051145676 | L90: deltaN_CO2 | N90: =O75 -> -1 | Q90: =W30/100*X34-S30/100*T34 -> 21221.987 | R90: -> | S90: xi_2 = | T90: =Q90*N90 -> -21221.987 | U90: mol
A91: 784 | B91: =A91/1000 -> 0.784 | C91: =A91-273 -> 511 | D91: =(D$73+D$74*$B91+D$75*($B91^2)+D$76*($B91^3)+D$77/($B91^2))/1000 -> 0.062136232 | E91: =(E$73+E$74*$B91+E$75*($B91^2)+E$76*($B91^3)+E$77/($B91^2))/1000 -> 0.22455076 | F91: =(F$73+F$74*$B91+F$75*($B91^2)+F$76*($B91^3)+F$77/($B91^2))/1000 -> 0.013610266 | G91: =(G$73+G$74*$B91+G$75*($B91^2)+G$76*($B91^3)+G$77/($B91^2))/1000 -> 0.03133059 | H91: =(H$73+H$74*$B91+H$75*($B91^2)+H$76*($B91^3)+H$77/($B91^2))/1000 -> 0.051163275 | L91: deltaN_CH4 | M91: =P72 -> -1 | N91: =P75 -> -1 | O91: =P78 -> -1 | V91: =W31/100*X34-S31/100*T34 -> -59399.283 | W91: =M91*T$93+N91*T$90+O91*T$88+P91*T$92 -> -60040.637 | X91: =(W91-V91)/V91 -> 0.010797331
A92: 785 | B92: =A92/1000 -> 0.785 | C92: =A92-273 -> 512 | D92: =(D$73+D$74*$B92+D$75*($B92^2)+D$76*($B92^3)+D$77/($B92^2))/1000 -> 0.062186007 | E92: =(E$73+E$74*$B92+E$75*($B92^2)+E$76*($B92^3)+E$77/($B92^2))/1000 -> 0.22561117 | F92: =(F$73+F$74*$B92+F$75*($B92^2)+F$76*($B92^3)+F$77/($B92^2))/1000 -> 0.013653065 | G92: =(G$73+G$74*$B92+G$75*($B92^2)+G$76*($B92^3)+G$77/($B92^2))/1000 -> 0.031337329 | H92: =(H$73+H$74*$B92+H$75*($B92^2)+H$76*($B92^3)+H$77/($B92^2))/1000 -> 0.051180841 | L92: deltaN_C2H6 | P92: =Q79 -> -1 | Q92: =W32/100*X34-S32/100*T34 -> -2889.9261 | R92: -> | S92: xi_4 = | T92: =Q92*P92 -> 2889.9261 | U92: mol
A93: 786 | B93: =A93/1000 -> 0.786 | C93: =A93-273 -> 513 | D93: =(D$73+D$74*$B93+D$75*($B93^2)+D$76*($B93^3)+D$77/($B93^2))/1000 -> 0.062235735 | E93: =(E$73+E$74*$B93+E$75*($B93^2)+E$76*($B93^3)+E$77/($B93^2))/1000 -> 0.22667691 | F93: =(F$73+F$74*$B93+F$75*($B93^2)+F$76*($B93^3)+F$77/($B93^2))/1000 -> 0.013695717 | G93: =(G$73+G$74*$B93+G$75*($B93^2)+G$76*($B93^3)+G$77/($B93^2))/1000 -> 0.031344066 | H93: =(H$73+H$74*$B93+H$75*($B93^2)+H$76*($B93^3)+H$77/($B93^2))/1000 -> 0.051198375 | L93: deltaN_H2O | M93: =R72 -> -1 | P93: -2 | Q93: =W33/100*X34-S33/100*T34 -> -86975.878 | R93: -> | S93: xi_1 = | T93: =(Q93-(P93*T92))/M93 -> 81196.026 | U93: mol
A94: 787 | B94: =A94/1000 -> 0.787 | C94: =A94-273 -> 514 | D94: =(D$73+D$74*$B94+D$75*($B94^2)+D$76*($B94^3)+D$77/($B94^2))/1000 -> 0.062285416 | E94: =(E$73+E$74*$B94+E$75*($B94^2)+E$76*($B94^3)+E$77/($B94^2))/1000 -> 0.22774799 | F94: =(F$73+F$74*$B94+F$75*($B94^2)+F$76*($B94^3)+F$77/($B94^2))/1000 -> 0.013738221 | G94: =(G$73+G$74*$B94+G$75*($B94^2)+G$76*($B94^3)+G$77/($B94^2))/1000 -> 0.031350801 | H94: =(H$73+H$74*$B94+H$75*($B94^2)+H$76*($B94^3)+H$77/($B94^2))/1000 -> 0.051215878 | L94: deltaN_C | O94: =S78 -> 1 | V94: 0 | W94: =M94*T$93+N94*T$90+O94*T$88+P94*T$92 -> 66.597459
A95: 788 | B95: =A95/1000 -> 0.788 | C95: =A95-273 -> 515 | D95: =(D$73+D$74*$B95+D$75*($B95^2)+D$76*($B95^3)+D$77/($B95^2))/1000 -> 0.06233505 | E95: =(E$73+E$74*$B95+E$75*($B95^2)+E$76*($B95^3)+E$77/($B95^2))/1000 -> 0.22882441 | F95: =(F$73+F$74*$B95+F$75*($B95^2)+F$76*($B95^3)+F$77/($B95^2))/1000 -> 0.01378058 | G95: =(G$73+G$74*$B95+G$75*($B95^2)+G$76*($B95^3)+G$77/($B95^2))/1000 -> 0.031357533 | H95: =(H$73+H$74*$B95+H$75*($B95^2)+H$76*($B95^3)+H$77/($B95^2))/1000 -> 0.051233348
A96: 789 | B96: =A96/1000 -> 0.789 | C96: =A96-273 -> 516 | D96: =(D$73+D$74*$B96+D$75*($B96^2)+D$76*($B96^3)+D$77/($B96^2))/1000 -> 0.062384638 | E96: =(E$73+E$74*$B96+E$75*($B96^2)+E$76*($B96^3)+E$77/($B96^2))/1000 -> 0.2299062 | F96: =(F$73+F$74*$B96+F$75*($B96^2)+F$76*($B96^3)+F$77/($B96^2))/1000 -> 0.013822792 | G96: =(G$73+G$74*$B96+G$75*($B96^2)+G$76*($B96^3)+G$77/($B96^2))/1000 -> 0.031364263 | H96: =(H$73+H$74*$B96+H$75*($B96^2)+H$76*($B96^3)+H$77/($B96^2))/1000 -> 0.051250787 | J96: Reaction enthalpy determination
A97: 790 | B97: =A97/1000 -> 0.79 | C97: =A97-273 -> 517 | D97: =(D$73+D$74*$B97+D$75*($B97^2)+D$76*($B97^3)+D$77/($B97^2))/1000 -> 0.062434179 | E97: =(E$73+E$74*$B97+E$75*($B97^2)+E$76*($B97^3)+E$77/($B97^2))/1000 -> 0.23099337 | F97: =(F$73+F$74*$B97+F$75*($B97^2)+F$76*($B97^3)+F$77/($B97^2))/1000 -> 0.01386486 | G97: =(G$73+G$74*$B97+G$75*($B97^2)+G$76*($B97^3)+G$77/($B97^2))/1000 -> 0.03137099 | H97: =(H$73+H$74*$B97+H$75*($B97^2)+H$76*($B97^3)+H$77/($B97^2))/1000 -> 0.051268193
A98: 791 | B98: =A98/1000 -> 0.791 | C98: =A98-273 -> 518 | D98: =(D$73+D$74*$B98+D$75*($B98^2)+D$76*($B98^3)+D$77/($B98^2))/1000 -> 0.062483673 | E98: =(E$73+E$74*$B98+E$75*($B98^2)+E$76*($B98^3)+E$77/($B98^2))/1000 -> 0.23208594 | F98: =(F$73+F$74*$B98+F$75*($B98^2)+F$76*($B98^3)+F$77/($B98^2))/1000 -> 0.013906784 | G98: =(G$73+G$74*$B98+G$75*($B98^2)+G$76*($B98^3)+G$77/($B98^2))/1000 -> 0.031377714 | H98: =(H$73+H$74*$B98+H$75*($B98^2)+H$76*($B98^3)+H$77/($B98^2))/1000 -> 0.051285568 | V98: neglected because ideal gas
A99: 792 | B99: =A99/1000 -> 0.792 | C99: =A99-273 -> 519 | D99: =(D$73+D$74*$B99+D$75*($B99^2)+D$76*($B99^3)+D$77/($B99^2))/1000 -> 0.06253312 | E99: =(E$73+E$74*$B99+E$75*($B99^2)+E$76*($B99^3)+E$77/($B99^2))/1000 -> 0.23318392 | F99: =(F$73+F$74*$B99+F$75*($B99^2)+F$76*($B99^3)+F$77/($B99^2))/1000 -> 0.013948564 | G99: =(G$73+G$74*$B99+G$75*($B99^2)+G$76*($B99^3)+G$77/($B99^2))/1000 -> 0.031384436 | H99: =(H$73+H$74*$B99+H$75*($B99^2)+H$76*($B99^3)+H$77/($B99^2))/1000 -> 0.051302911 | K99: species | L99: nu_j | M99: deltah_j_std [kJ/mol] | N99: A | O99: B | P99: C | Q99: D | R99: E | S99: T_1 | T99: T_0 | U99: deltah_Tj | V99: deltah_pj
A100: 793 | B100: =A100/1000 -> 0.793 | C100: =A100-273 -> 520 | D100: =(D$73+D$74*$B100+D$75*($B100^2)+D$76*($B100^3)+D$77/($B100^2))/1000 -> 0.062582521 | E100: =(E$73+E$74*$B100+E$75*($B100^2)+E$76*($B100^3)+E$77/($B100^2))/1000 -> 0.23428731 | F100: =(F$73+F$74*$B100+F$75*($B100^2)+F$76*($B100^3)+F$77/($B100^2))/1000 -> 0.013990202 | G100: =(G$73+G$74*$B100+G$75*($B100^2)+G$76*($B100^3)+G$77/($B100^2))/1000 -> 0.031391155 | H100: =(H$73+H$74*$B100+H$75*($B100^2)+H$76*($B100^3)+H$77/($B100^2))/1000 -> 0.051320222 | J100: I | K100: CH4 | L100: -1 | M100: -74.6 | N100: -0.703029 | O100: 108.4773 | P100: -42.52157 | Q100: 5.862788 | R100: 0.678565 | S100: 1123 | T100: 298 | U100: =(N100*(S100-T100)+O100/2000*(S100^2-T100^2)+P100/(3*10^6)*(S100^3-T100^3)+Q100/(4*10^9)*(S100^4-T100^4)-(10^6*R100)*(1/T100-1/S100))/1000 -> 43.953456 | V100: -
A101: 794 | B101: =A101/1000 -> 0.794 | C101: =A101-273 -> 521 | D101: =(D$73+D$74*$B101+D$75*($B101^2)+D$76*($B101^3)+D$77/($B101^2))/1000 -> 0.062631875 | E101: =(E$73+E$74*$B101+E$75*($B101^2)+E$76*($B101^3)+E$77/($B101^2))/1000 -> 0.23539615 | F101: =(F$73+F$74*$B101+F$75*($B101^2)+F$76*($B101^3)+F$77/($B101^2))/1000 -> 0.014031698 | G101: =(G$73+G$74*$B101+G$75*($B101^2)+G$76*($B101^3)+G$77/($B101^2))/1000 -> 0.031397872 | H101: =(H$73+H$74*$B101+H$75*($B101^2)+H$76*($B101^3)+H$77/($B101^2))/1000 -> 0.051337502 | K101: H2O | L101: -1 | M101: -241.8 | N101: -203.606 | O101: 1523.29 | P101: -3196.413 | Q101: 2474.255 | R101: 3.855326 | S101: 1123 | T101: 298 | U101: =(N101*(S101-T101)+O101/2000*(S101^2-T101^2)+P101/(3*10^6)*(S101^3-T101^3)+Q101/(4*10^9)*(S101^4-T101^4)-(10^6*R101)*(1/T101-1/S101))/1000 -> 213.55578 | V101: -
A102: 795 | B102: =A102/1000 -> 0.795 | C102: =A102-273 -> 522 | D102: =(D$73+D$74*$B102+D$75*($B102^2)+D$76*($B102^3)+D$77/($B102^2))/1000 -> 0.062681181 | E102: =(E$73+E$74*$B102+E$75*($B102^2)+E$76*($B102^3)+E$77/($B102^2))/1000 -> 0.23651044 | F102: =(F$73+F$74*$B102+F$75*($B102^2)+F$76*($B102^3)+F$77/($B102^2))/1000 -> 0.014073053 | G102: =(G$73+G$74*$B102+G$75*($B102^2)+G$76*($B102^3)+G$77/($B102^2))/1000 -> 0.031404586 | H102: =(H$73+H$74*$B102+H$75*($B102^2)+H$76*($B102^3)+H$77/($B102^2))/1000 -> 0.05135475 | K102: CO | L102: 1 | M102: -110.5 | N102: 25.56759 | O102: 6.09613 | P102: 4.054656 | Q102: -2.671301 | R102: 0.131021 | S102: 1123 | T102: 298 | U102: =(N102*(S102-T102)+O102/2000*(S102^2-T102^2)+P102/(3*10^6)*(S102^3-T102^3)+Q102/(4*10^9)*(S102^4-T102^4)-(10^6*R102)*(1/T102-1/S102))/1000 -> 25.165079 | V102: -
A103: 796 | B103: =A103/1000 -> 0.796 | C103: =A103-273 -> 523 | D103: =(D$73+D$74*$B103+D$75*($B103^2)+D$76*($B103^3)+D$77/($B103^2))/1000 -> 0.062730441 | E103: =(E$73+E$74*$B103+E$75*($B103^2)+E$76*($B103^3)+E$77/($B103^2))/1000 -> 0.2376302 | F103: =(F$73+F$74*$B103+F$75*($B103^2)+F$76*($B103^3)+F$77/($B103^2))/1000 -> 0.014114268 | G103: =(G$73+G$74*$B103+G$75*($B103^2)+G$76*($B103^3)+G$77/($B103^2))/1000 -> 0.031411297 | H103: =(H$73+H$74*$B103+H$75*($B103^2)+H$76*($B103^3)+H$77/($B103^2))/1000 -> 0.051371966 | K103: H2 | L103: 3 | M103: 0 | N103: 33.066178 | O103: -11.363417 | P103: 11.432816 | Q103: -2.772874 | R103: -9.980797 | S103: 1123 | T103: 298 | U103: =(N103*(S103-T103)+O103/2000*(S103^2-T103^2)+P103/(3*10^6)*(S103^3-T103^3)+Q103/(4*10^9)*(S103^4-T103^4)-(10^6*R103)*(1/T103-1/S103))/1000 -> 49.423098 | V103: -
A104: 797 | B104: =A104/1000 -> 0.797 | C104: =A104-273 -> 524 | D104: =(D$73+D$74*$B104+D$75*($B104^2)+D$76*($B104^3)+D$77/($B104^2))/1000 -> 0.062779654 | E104: =(E$73+E$74*$B104+E$75*($B104^2)+E$76*($B104^3)+E$77/($B104^2))/1000 -> 0.23875543 | F104: =(F$73+F$74*$B104+F$75*($B104^2)+F$76*($B104^3)+F$77/($B104^2))/1000 -> 0.014155344 | G104: =(G$73+G$74*$B104+G$75*($B104^2)+G$76*($B104^3)+G$77/($B104^2))/1000 -> 0.031418005 | H104: =(H$73+H$74*$B104+H$75*($B104^2)+H$76*($B104^3)+H$77/($B104^2))/1000 -> 0.051389151 | M104: =SUMPRODUCT(L100:L103,M100:M103) -> 205.9 | U104: =SUMPRODUCT(L100:L103,U100:U103) -> -84.074865 | W104: =SUM(M104,U104) -> 121.82514 | X104: kJ/mol
A105: 798 | B105: =A105/1000 -> 0.798 | C105: =A105-273 -> 525 | D105: =(D$73+D$74*$B105+D$75*($B105^2)+D$76*($B105^3)+D$77/($B105^2))/1000 -> 0.06282882 | E105: =(E$73+E$74*$B105+E$75*($B105^2)+E$76*($B105^3)+E$77/($B105^2))/1000 -> 0.23988617 | F105: =(F$73+F$74*$B105+F$75*($B105^2)+F$76*($B105^3)+F$77/($B105^2))/1000 -> 0.01419628 | G105: =(G$73+G$74*$B105+G$75*($B105^2)+G$76*($B105^3)+G$77/($B105^2))/1000 -> 0.031424711 | H105: =(H$73+H$74*$B105+H$75*($B105^2)+H$76*($B105^3)+H$77/($B105^2))/1000 -> 0.051406305 | J105: IV | K105: CH4 | L105: -1 | M105: -74.6 | N105: -0.703029 | O105: 108.4773 | P105: -42.52157 | Q105: 5.862788 | R105: 0.678565 | S105: 1123 | T105: 298 | U105: =(N105*(S105-T105)+O105/2000*(S105^2-T105^2)+P105/(3*10^6)*(S105^3-T105^3)+Q105/(4*10^9)*(S105^4-T105^4)-(10^6*R105)*(1/T105-1/S105))/1000 -> 43.953456
A106: 799 | B106: =A106/1000 -> 0.799 | C106: =A106-273 -> 526 | D106: =(D$73+D$74*$B106+D$75*($B106^2)+D$76*($B106^3)+D$77/($B106^2))/1000 -> 0.062877939 | E106: =(E$73+E$74*$B106+E$75*($B106^2)+E$76*($B106^3)+E$77/($B106^2))/1000 -> 0.24102242 | F106: =(F$73+F$74*$B106+F$75*($B106^2)+F$76*($B106^3)+F$77/($B106^2))/1000 -> 0.014237079 | G106: =(G$73+G$74*$B106+G$75*($B106^2)+G$76*($B106^3)+G$77/($B106^2))/1000 -> 0.031431414 | H106: =(H$73+H$74*$B106+H$75*($B106^2)+H$76*($B106^3)+H$77/($B106^2))/1000 -> 0.051423427 | K106: CO2 | L106: -1 | M106: -393.5 | N106: 24.99735 | O106: 55.18696 | P106: -33.69137 | Q106: 7.948387 | R106: -0.136638 | S106: 1123 | T106: 298 | U106: =(N106*(S106-T106)+O106/2000*(S106^2-T106^2)+P106/(3*10^6)*(S106^3-T106^3)+Q106/(4*10^9)*(S106^4-T106^4)-(10^6*R106)*(1/T106-1/S106))/1000 -> 40.844973
A107: 800 | B107: =A107/1000 -> 0.8 | C107: =A107-273 -> 527 | D107: =(D$73+D$74*$B107+D$75*($B107^2)+D$76*($B107^3)+D$77/($B107^2))/1000 -> 0.062927011 | E107: =(E$73+E$74*$B107+E$75*($B107^2)+E$76*($B107^3)+E$77/($B107^2))/1000 -> 0.24216419 | F107: =(F$73+F$74*$B107+F$75*($B107^2)+F$76*($B107^3)+F$77/($B107^2))/1000 -> 0.01427774 | G107: =(G$73+G$74*$B107+G$75*($B107^2)+G$76*($B107^3)+G$77/($B107^2))/1000 -> 0.031438114 | H107: =(H$73+H$74*$B107+H$75*($B107^2)+H$76*($B107^3)+H$77/($B107^2))/1000 -> 0.051440518 | K107: CO | L107: 2 | M107: -110.5 | N107: 25.56759 | O107: 6.09613 | P107: 4.054656 | Q107: -2.671301 | R107: 0.131021 | S107: 1123 | T107: 298 | U107: =(N107*(S107-T107)+O107/2000*(S107^2-T107^2)+P107/(3*10^6)*(S107^3-T107^3)+Q107/(4*10^9)*(S107^4-T107^4)-(10^6*R107)*(1/T107-1/S107))/1000 -> 25.165079
A108: 801 | B108: =A108/1000 -> 0.801 | C108: =A108-273 -> 528 | D108: =(D$73+D$74*$B108+D$75*($B108^2)+D$76*($B108^3)+D$77/($B108^2))/1000 -> 0.062976037 | E108: =(E$73+E$74*$B108+E$75*($B108^2)+E$76*($B108^3)+E$77/($B108^2))/1000 -> 0.2433115 | F108: =(F$73+F$74*$B108+F$75*($B108^2)+F$76*($B108^3)+F$77/($B108^2))/1000 -> 0.014318264 | G108: =(G$73+G$74*$B108+G$75*($B108^2)+G$76*($B108^3)+G$77/($B108^2))/1000 -> 0.031444811 | H108: =(H$73+H$74*$B108+H$75*($B108^2)+H$76*($B108^3)+H$77/($B108^2))/1000 -> 0.051457578 | K108: H2 | L108: 2 | M108: 0 | N108: 33.066178 | O108: -11.363417 | P108: 11.432816 | Q108: -2.772874 | R108: -9.980797 | S108: 1123 | T108: 298 | U108: =(N108*(S108-T108)+O108/2000*(S108^2-T108^2)+P108/(3*10^6)*(S108^3-T108^3)+Q108/(4*10^9)*(S108^4-T108^4)-(10^6*R108)*(1/T108-1/S108))/1000 -> 49.423098
A109: 802 | B109: =A109/1000 -> 0.802 | C109: =A109-273 -> 529 | D109: =(D$73+D$74*$B109+D$75*($B109^2)+D$76*($B109^3)+D$77/($B109^2))/1000 -> 0.063025015 | E109: =(E$73+E$74*$B109+E$75*($B109^2)+E$76*($B109^3)+E$77/($B109^2))/1000 -> 0.24446436 | F109: =(F$73+F$74*$B109+F$75*($B109^2)+F$76*($B109^3)+F$77/($B109^2))/1000 -> 0.014358653 | G109: =(G$73+G$74*$B109+G$75*($B109^2)+G$76*($B109^3)+G$77/($B109^2))/1000 -> 0.031451505 | H109: =(H$73+H$74*$B109+H$75*($B109^2)+H$76*($B109^3)+H$77/($B109^2))/1000 -> 0.051474607 | M109: =SUMPRODUCT(L105:L108,M105:M108) -> 247.1 | U109: =SUMPRODUCT(L105:L108,U105:U108) -> 64.377926 | W109: =SUM(M109,U109) -> 311.47793 | X109: kJ/mol
A110: 803 | B110: =A110/1000 -> 0.803 | C110: =A110-273 -> 530 | D110: =(D$73+D$74*$B110+D$75*($B110^2)+D$76*($B110^3)+D$77/($B110^2))/1000 -> 0.063073946 | E110: =(E$73+E$74*$B110+E$75*($B110^2)+E$76*($B110^3)+E$77/($B110^2))/1000 -> 0.2456228 | F110: =(F$73+F$74*$B110+F$75*($B110^2)+F$76*($B110^3)+F$77/($B110^2))/1000 -> 0.014398906 | G110: =(G$73+G$74*$B110+G$75*($B110^2)+G$76*($B110^3)+G$77/($B110^2))/1000 -> 0.031458196 | H110: =(H$73+H$74*$B110+H$75*($B110^2)+H$76*($B110^3)+H$77/($B110^2))/1000 -> 0.051491604 | J110: VII | K110: CH4 | L110: -1
A111: 804 | B111: =A111/1000 -> 0.804 | C111: =A111-273 -> 531 | D111: =(D$73+D$74*$B111+D$75*($B111^2)+D$76*($B111^3)+D$77/($B111^2))/1000 -> 0.06312283 | E111: =(E$73+E$74*$B111+E$75*($B111^2)+E$76*($B111^3)+E$77/($B111^2))/1000 -> 0.24678682 | F111: =(F$73+F$74*$B111+F$75*($B111^2)+F$76*($B111^3)+F$77/($B111^2))/1000 -> 0.014439025 | G111: =(G$73+G$74*$B111+G$75*($B111^2)+G$76*($B111^3)+G$77/($B111^2))/1000 -> 0.031464884 | H111: =(H$73+H$74*$B111+H$75*($B111^2)+H$76*($B111^3)+H$77/($B111^2))/1000 -> 0.051508571 | K111: C | L111: 1
A112: 805 | B112: =A112/1000 -> 0.805 | C112: =A112-273 -> 532 | D112: =(D$73+D$74*$B112+D$75*($B112^2)+D$76*($B112^3)+D$77/($B112^2))/1000 -> 0.063171668 | E112: =(E$73+E$74*$B112+E$75*($B112^2)+E$76*($B112^3)+E$77/($B112^2))/1000 -> 0.24795644 | F112: =(F$73+F$74*$B112+F$75*($B112^2)+F$76*($B112^3)+F$77/($B112^2))/1000 -> 0.01447901 | G112: =(G$73+G$74*$B112+G$75*($B112^2)+G$76*($B112^3)+G$77/($B112^2))/1000 -> 0.031471569 | H112: =(H$73+H$74*$B112+H$75*($B112^2)+H$76*($B112^3)+H$77/($B112^2))/1000 -> 0.051525506 | K112: H2 | L112: 2
A113: 806 | B113: =A113/1000 -> 0.806 | C113: =A113-273 -> 533 | D113: =(D$73+D$74*$B113+D$75*($B113^2)+D$76*($B113^3)+D$77/($B113^2))/1000 -> 0.063220458 | E113: =(E$73+E$74*$B113+E$75*($B113^2)+E$76*($B113^3)+E$77/($B113^2))/1000 -> 0.24913167 | F113: =(F$73+F$74*$B113+F$75*($B113^2)+F$76*($B113^3)+F$77/($B113^2))/1000 -> 0.014518862 | G113: =(G$73+G$74*$B113+G$75*($B113^2)+G$76*($B113^3)+G$77/($B113^2))/1000 -> 0.031478251 | H113: =(H$73+H$74*$B113+H$75*($B113^2)+H$76*($B113^3)+H$77/($B113^2))/1000 -> 0.051542411 | W113: insignificant
A114: 807 | B114: =A114/1000 -> 0.807 | C114: =A114-273 -> 534 | D114: =(D$73+D$74*$B114+D$75*($B114^2)+D$76*($B114^3)+D$77/($B114^2))/1000 -> 0.063269201 | E114: =(E$73+E$74*$B114+E$75*($B114^2)+E$76*($B114^3)+E$77/($B114^2))/1000 -> 0.25031252 | F114: =(F$73+F$74*$B114+F$75*($B114^2)+F$76*($B114^3)+F$77/($B114^2))/1000 -> 0.014558581 | G114: =(G$73+G$74*$B114+G$75*($B114^2)+G$76*($B114^3)+G$77/($B114^2))/1000 -> 0.03148493 | H114: =(H$73+H$74*$B114+H$75*($B114^2)+H$76*($B114^3)+H$77/($B114^2))/1000 -> 0.051559284 | J114: VIII | K114: C2H6 | L114: -1 | M114: 84 | N114: - | O114: - | P114: - | Q114: - | R114: - | S114: 1123 | T114: 298 | U114: =U100 -> 43.953456
A115: 808 | B115: =A115/1000 -> 0.808 | C115: =A115-273 -> 535 | D115: =(D$73+D$74*$B115+D$75*($B115^2)+D$76*($B115^3)+D$77/($B115^2))/1000 -> 0.063317897 | E115: =(E$73+E$74*$B115+E$75*($B115^2)+E$76*($B115^3)+E$77/($B115^2))/1000 -> 0.25149902 | F115: =(F$73+F$74*$B115+F$75*($B115^2)+F$76*($B115^3)+F$77/($B115^2))/1000 -> 0.014598169 | G115: =(G$73+G$74*$B115+G$75*($B115^2)+G$76*($B115^3)+G$77/($B115^2))/1000 -> 0.031491606 | H115: =(H$73+H$74*$B115+H$75*($B115^2)+H$76*($B115^3)+H$77/($B115^2))/1000 -> 0.051576127 | K115: H2O | L115: -2 | M115: -241.8 | N115: -203.606 | O115: 1523.29 | P115: -3196.413 | Q115: 2474.255 | R115: 3.855326 | S115: 1123 | T115: 298 | U115: =(N115*(S115-T115)+O115/2000*(S115^2-T115^2)+P115/(3*10^6)*(S115^3-T115^3)+Q115/(4*10^9)*(S115^4-T115^4)-(10^6*R115)*(1/T115-1/S115))/1000 -> 213.55578
A116: 809 | B116: =A116/1000 -> 0.809 | C116: =A116-273 -> 536 | D116: =(D$73+D$74*$B116+D$75*($B116^2)+D$76*($B116^3)+D$77/($B116^2))/1000 -> 0.063366546 | E116: =(E$73+E$74*$B116+E$75*($B116^2)+E$76*($B116^3)+E$77/($B116^2))/1000 -> 0.25269118 | F116: =(F$73+F$74*$B116+F$75*($B116^2)+F$76*($B116^3)+F$77/($B116^2))/1000 -> 0.014637625 | G116: =(G$73+G$74*$B116+G$75*($B116^2)+G$76*($B116^3)+G$77/($B116^2))/1000 -> 0.031498279 | H116: =(H$73+H$74*$B116+H$75*($B116^2)+H$76*($B116^3)+H$77/($B116^2))/1000 -> 0.051592939 | K116: CO | L116: 2 | M116: -110.5 | N116: 25.56759 | O116: 6.09613 | P116: 4.054656 | Q116: -2.671301 | R116: 0.131021 | S116: 1123 | T116: 298 | U116: =(N116*(S116-T116)+O116/2000*(S116^2-T116^2)+P116/(3*10^6)*(S116^3-T116^3)+Q116/(4*10^9)*(S116^4-T116^4)-(10^6*R116)*(1/T116-1/S116))/1000 -> 25.165079
A117: 810 | B117: =A117/1000 -> 0.81 | C117: =A117-273 -> 537 | D117: =(D$73+D$74*$B117+D$75*($B117^2)+D$76*($B117^3)+D$77/($B117^2))/1000 -> 0.063415148 | E117: =(E$73+E$74*$B117+E$75*($B117^2)+E$76*($B117^3)+E$77/($B117^2))/1000 -> 0.25388901 | F117: =(F$73+F$74*$B117+F$75*($B117^2)+F$76*($B117^3)+F$77/($B117^2))/1000 -> 0.014676951 | G117: =(G$73+G$74*$B117+G$75*($B117^2)+G$76*($B117^3)+G$77/($B117^2))/1000 -> 0.031504948 | H117: =(H$73+H$74*$B117+H$75*($B117^2)+H$76*($B117^3)+H$77/($B117^2))/1000 -> 0.051609721 | K117: H2 | L117: 5 | M117: 0 | N117: 33.066178 | O117: -11.363417 | P117: 11.432816 | Q117: -2.772874 | R117: -9.980797 | S117: 1123 | T117: 298 | U117: =(N117*(S117-T117)+O117/2000*(S117^2-T117^2)+P117/(3*10^6)*(S117^3-T117^3)+Q117/(4*10^9)*(S117^4-T117^4)-(10^6*R117)*(1/T117-1/S117))/1000 -> 49.423098
A118: 811 | B118: =A118/1000 -> 0.811 | C118: =A118-273 -> 538 | D118: =(D$73+D$74*$B118+D$75*($B118^2)+D$76*($B118^3)+D$77/($B118^2))/1000 -> 0.063463703 | E118: =(E$73+E$74*$B118+E$75*($B118^2)+E$76*($B118^3)+E$77/($B118^2))/1000 -> 0.25509252 | F118: =(F$73+F$74*$B118+F$75*($B118^2)+F$76*($B118^3)+F$77/($B118^2))/1000 -> 0.014716148 | G118: =(G$73+G$74*$B118+G$75*($B118^2)+G$76*($B118^3)+G$77/($B118^2))/1000 -> 0.031511615 | H118: =(H$73+H$74*$B118+H$75*($B118^2)+H$76*($B118^3)+H$77/($B118^2))/1000 -> 0.051626471 | M118: =SUMPRODUCT(L114:L117,M114:M117) -> 178.6 | U118: =SUMPRODUCT(L114:L117,U114:U117) -> -173.61937 | W118: =SUM(M118,U118) -> 4.9806292 | X118: kJ/mol
A119: 812 | B119: =A119/1000 -> 0.812 | C119: =A119-273 -> 539 | D119: =(D$73+D$74*$B119+D$75*($B119^2)+D$76*($B119^3)+D$77/($B119^2))/1000 -> 0.063512211 | E119: =(E$73+E$74*$B119+E$75*($B119^2)+E$76*($B119^3)+E$77/($B119^2))/1000 -> 0.25630173 | F119: =(F$73+F$74*$B119+F$75*($B119^2)+F$76*($B119^3)+F$77/($B119^2))/1000 -> 0.014755215 | G119: =(G$73+G$74*$B119+G$75*($B119^2)+G$76*($B119^3)+G$77/($B119^2))/1000 -> 0.031518278 | H119: =(H$73+H$74*$B119+H$75*($B119^2)+H$76*($B119^3)+H$77/($B119^2))/1000 -> 0.051643191
A120: 813 | B120: =A120/1000 -> 0.813 | C120: =A120-273 -> 540 | D120: =(D$73+D$74*$B120+D$75*($B120^2)+D$76*($B120^3)+D$77/($B120^2))/1000 -> 0.063560671 | E120: =(E$73+E$74*$B120+E$75*($B120^2)+E$76*($B120^3)+E$77/($B120^2))/1000 -> 0.25751666 | F120: =(F$73+F$74*$B120+F$75*($B120^2)+F$76*($B120^3)+F$77/($B120^2))/1000 -> 0.014794154 | G120: =(G$73+G$74*$B120+G$75*($B120^2)+G$76*($B120^3)+G$77/($B120^2))/1000 -> 0.031524938 | H120: =(H$73+H$74*$B120+H$75*($B120^2)+H$76*($B120^3)+H$77/($B120^2))/1000 -> 0.051659881
A121: 814 | B121: =A121/1000 -> 0.814 | C121: =A121-273 -> 541 | D121: =(D$73+D$74*$B121+D$75*($B121^2)+D$76*($B121^3)+D$77/($B121^2))/1000 -> 0.063609085 | E121: =(E$73+E$74*$B121+E$75*($B121^2)+E$76*($B121^3)+E$77/($B121^2))/1000 -> 0.25873732 | F121: =(F$73+F$74*$B121+F$75*($B121^2)+F$76*($B121^3)+F$77/($B121^2))/1000 -> 0.014832965 | G121: =(G$73+G$74*$B121+G$75*($B121^2)+G$76*($B121^3)+G$77/($B121^2))/1000 -> 0.031531595 | H121: =(H$73+H$74*$B121+H$75*($B121^2)+H$76*($B121^3)+H$77/($B121^2))/1000 -> 0.05167654
A122: 815 | B122: =A122/1000 -> 0.815 | C122: =A122-273 -> 542 | D122: =(D$73+D$74*$B122+D$75*($B122^2)+D$76*($B122^3)+D$77/($B122^2))/1000 -> 0.063657451 | E122: =(E$73+E$74*$B122+E$75*($B122^2)+E$76*($B122^3)+E$77/($B122^2))/1000 -> 0.25996372 | F122: =(F$73+F$74*$B122+F$75*($B122^2)+F$76*($B122^3)+F$77/($B122^2))/1000 -> 0.014871649 | G122: =(G$73+G$74*$B122+G$75*($B122^2)+G$76*($B122^3)+G$77/($B122^2))/1000 -> 0.031538248 | H122: =(H$73+H$74*$B122+H$75*($B122^2)+H$76*($B122^3)+H$77/($B122^2))/1000 -> 0.051693168
A123: 816 | B123: =A123/1000 -> 0.816 | C123: =A123-273 -> 543 | D123: =(D$73+D$74*$B123+D$75*($B123^2)+D$76*($B123^3)+D$77/($B123^2))/1000 -> 0.06370577 | E123: =(E$73+E$74*$B123+E$75*($B123^2)+E$76*($B123^3)+E$77/($B123^2))/1000 -> 0.26119589 | F123: =(F$73+F$74*$B123+F$75*($B123^2)+F$76*($B123^3)+F$77/($B123^2))/1000 -> 0.014910207 | G123: =(G$73+G$74*$B123+G$75*($B123^2)+G$76*($B123^3)+G$77/($B123^2))/1000 -> 0.031544898 | H123: =(H$73+H$74*$B123+H$75*($B123^2)+H$76*($B123^3)+H$77/($B123^2))/1000 -> 0.051709767
A124: 817 | B124: =A124/1000 -> 0.817 | C124: =A124-273 -> 544 | D124: =(D$73+D$74*$B124+D$75*($B124^2)+D$76*($B124^3)+D$77/($B124^2))/1000 -> 0.063754042 | E124: =(E$73+E$74*$B124+E$75*($B124^2)+E$76*($B124^3)+E$77/($B124^2))/1000 -> 0.26243382 | F124: =(F$73+F$74*$B124+F$75*($B124^2)+F$76*($B124^3)+F$77/($B124^2))/1000 -> 0.014948639 | G124: =(G$73+G$74*$B124+G$75*($B124^2)+G$76*($B124^3)+G$77/($B124^2))/1000 -> 0.031551545 | H124: =(H$73+H$74*$B124+H$75*($B124^2)+H$76*($B124^3)+H$77/($B124^2))/1000 -> 0.051726335
A125: 818 | B125: =A125/1000 -> 0.818 | C125: =A125-273 -> 545 | D125: =(D$73+D$74*$B125+D$75*($B125^2)+D$76*($B125^3)+D$77/($B125^2))/1000 -> 0.063802267 | E125: =(E$73+E$74*$B125+E$75*($B125^2)+E$76*($B125^3)+E$77/($B125^2))/1000 -> 0.26367754 | F125: =(F$73+F$74*$B125+F$75*($B125^2)+F$76*($B125^3)+F$77/($B125^2))/1000 -> 0.014986946 | G125: =(G$73+G$74*$B125+G$75*($B125^2)+G$76*($B125^3)+G$77/($B125^2))/1000 -> 0.031558188 | H125: =(H$73+H$74*$B125+H$75*($B125^2)+H$76*($B125^3)+H$77/($B125^2))/1000 -> 0.051742872
A126: 819 | B126: =A126/1000 -> 0.819 | C126: =A126-273 -> 546 | D126: =(D$73+D$74*$B126+D$75*($B126^2)+D$76*($B126^3)+D$77/($B126^2))/1000 -> 0.063850445 | E126: =(E$73+E$74*$B126+E$75*($B126^2)+E$76*($B126^3)+E$77/($B126^2))/1000 -> 0.26492707 | F126: =(F$73+F$74*$B126+F$75*($B126^2)+F$76*($B126^3)+F$77/($B126^2))/1000 -> 0.015025128 | G126: =(G$73+G$74*$B126+G$75*($B126^2)+G$76*($B126^3)+G$77/($B126^2))/1000 -> 0.031564828 | H126: =(H$73+H$74*$B126+H$75*($B126^2)+H$76*($B126^3)+H$77/($B126^2))/1000 -> 0.05175938
A127: 820 | B127: =A127/1000 -> 0.82 | C127: =A127-273 -> 547 | D127: =(D$73+D$74*$B127+D$75*($B127^2)+D$76*($B127^3)+D$77/($B127^2))/1000 -> 0.063898576 | E127: =(E$73+E$74*$B127+E$75*($B127^2)+E$76*($B127^3)+E$77/($B127^2))/1000 -> 0.26618241 | F127: =(F$73+F$74*$B127+F$75*($B127^2)+F$76*($B127^3)+F$77/($B127^2))/1000 -> 0.015063186 | G127: =(G$73+G$74*$B127+G$75*($B127^2)+G$76*($B127^3)+G$77/($B127^2))/1000 -> 0.031571465 | H127: =(H$73+H$74*$B127+H$75*($B127^2)+H$76*($B127^3)+H$77/($B127^2))/1000 -> 0.051775857
A128: 821 | B128: =A128/1000 -> 0.821 | C128: =A128-273 -> 548 | D128: =(D$73+D$74*$B128+D$75*($B128^2)+D$76*($B128^3)+D$77/($B128^2))/1000 -> 0.063946659 | E128: =(E$73+E$74*$B128+E$75*($B128^2)+E$76*($B128^3)+E$77/($B128^2))/1000 -> 0.26744358 | F128: =(F$73+F$74*$B128+F$75*($B128^2)+F$76*($B128^3)+F$77/($B128^2))/1000 -> 0.015101122 | G128: =(G$73+G$74*$B128+G$75*($B128^2)+G$76*($B128^3)+G$77/($B128^2))/1000 -> 0.031578098 | H128: =(H$73+H$74*$B128+H$75*($B128^2)+H$76*($B128^3)+H$77/($B128^2))/1000 -> 0.051792304
...
